Workbook

Sheet Tienda_1
A1: Producto | B1: Categoría del Producto | C1: Precio | D1: Costo de envío | E1: Fecha de Compra | F1: Vendedor | G1: Lugar de Compra | H1: Calificación | I1: Método de pago | J1: Cantidad de cuotas | K1: lat | L1: lon
A2: Asistente virtual | B2: Electrónicos | C2: 164300 | D2: 6900 | E2: 16/01/2021 | F2: Pedro Gomez | G2: Bogotá | H2: 4 | I2: Tarjeta de crédito | J2: 8 | K2: 4.60971 | L2: -74.08175
A3: Mesa de comedor | B3: Muebles | C3: 192300 | D3: 8400 | E3: 18/05/2022 | F3: Beatriz Morales | G3: Medellín | H3: 1 | I3: Tarjeta de crédito | J3: 4 | K3: 6.25184 | L3: -75.56359
A4: Juego de mesa | B4: Juguetes | C4: 209600 | D4: 15900 | E4: 15/03/2021 | F4: Juan Fernandez | G4: Cartagena | H4: 1 | I4: Tarjeta de crédito | J4: 1 | K4: 10.39972 | L4: -75.51444
A5: Microondas | B5: Electrodomésticos | C5: 757500 | D5: 41000 | E5: 03/05/2022 | F5: Juan Fernandez | G5: Cali | H5: 4 | I5: Nequi | J5: 1 | K5: 3.43722 | L5: -76.5225
A6: Silla de oficina | B6: Muebles | C6: 335200 | D6: 20200 | E6: 07/11/2020 | F6: Maria Alfonso | G6: Medellín | H6: 5 | I6: Nequi | J6: 1 | K6: 6.25184 | L6: -75.56359
A7: Bloques de construcción | B7: Juguetes | C7: 24200 | D7: 0 | E7: 03/12/2020 | F7: Beatriz Morales | G7: Cali | H7: 5 | I7: Cupón | J7: 1 | K7: 3.43722 | L7: -76.5225
A8: Muñeca bebé | B8: Juguetes | C8: 44200 | D8: 0 | E8: 07/08/2021 | F8: Juan Fernandez | G8: Bogotá | H8: 3 | I8: Nequi | J8: 1 | K8: 4.60971 | L8: -74.08175
A9: Lavavajillas | B9: Electrodomésticos | C9: 1189700 | D9: 63700 | E9: 18/06/2021 | F9: Felipe Santos | G9: Santa Marta | H9: 5 | I9: Tarjeta de crédito | J9: 10 | K9: 11.24079 | L9: -74.19904
A10: Lavadora de ropa | B10: Electrodomésticos | C10: 1518200 | D10: 79000 | E10: 08/01/2022 | F10: Izabela de León | G10: Bogotá | H10: 1 | I10: Tarjeta de crédito | J10: 5 | K10: 4.60971 | L10: -74.08175
A11: Carrito de control remoto | B11: Juguetes | C11: 75200 | D11: 5100 | E11: 24/02/2020 | F11: Beatriz Morales | G11: Bogotá | H11: 5 | I11: Nequi | J11: 1 | K11: 4.60971 | L11: -74.08175
A12: Refrigerador | B12: Electrodomésticos | C12: 2431300 | D12: 127600 | E12: 03/04/2020 | F12: Blanca Ramirez | G12: Bogotá | H12: 5 | I12: Tarjeta de crédito | J12: 2 | K12: 4.60971 | L12: -74.08175
A13: Lavavajillas | B13: Electrodomésticos | C13: 1417100 | D13: 75700 | E13: 05/07/2021 | F13: Rafael Acosta | G13: Cartagena | H13: 5 | I13: Tarjeta de crédito | J13: 1 | K13: 10.39972 | L13: -75.51444
... A2360: Smartwatch | B2360: Electrónicos | C2360: 195000 | D2360: 8600 | E2360: 18/06/2022 | F2360: Felipe Santos | G2360: Cali | H2360: 4 | I2360: Tarjeta de crédito | J2360: 1 | K2360: 3.43722 | L2360: -76.5225

Sheet Tienda_2
A1: Producto | B1: Categoría del Producto | C1: Precio | D1: Costo de envío | E1: Fecha de Compra | F1: Vendedor | G1: Lugar de Compra | H1: Calificación | I1: Método de pago | J1: Cantidad de cuotas | K1: lat | L1: lon
A2: Silla de oficina | B2: Muebles | C2: 283600 | D2: 15300 | E2: 04/08/2021 | F2: Izabela de León | G2: Medellín | H2: 1 | I2: Nequi | J2: 1 | K2: 6.25184 | L2: -75.56359
A3: Pandereta | B3: Instrumentos musicales | C3: 76800 | D3: 2300 | E3: 26/11/2020 | F3: Blanca Ramirez | G3: Medellín | H3: 3 | I3: Tarjeta de crédito | J3: 4 | K3: 6.25184 | L3: -75.56359
A4: Cama king | B4: Muebles | C4: 443300 | D4: 23800 | E4: 22/10/2021 | F4: Izabela de León | G4: Pereira | H4: 5 | I4: Tarjeta de crédito | J4: 10 | K4: 4.81333 | L4: -75.69611
A5: Cama king | B5: Muebles | C5: 906200 | D5: 46400 | E5: 04/05/2022 | F5: Maria Alfonso | G5: Cali | H5: 5 | I5: Tarjeta de crédito | J5: 10 | K5: 3.43722 | L5: -76.5225
A6: Silla de oficina | B6: Muebles | C6: 397800 | D6: 19400 | E6: 26/02/2022 | F6: Lucas Olivera | G6: Bogotá | H6: 4 | I6: Tarjeta de crédito | J6: 3 | K6: 4.60971 | L6: -74.08175
A7: Guitarra acústica | B7: Instrumentos musicales | C7: 298400 | D7: 16100 | E7: 10/09/2021 | F7: Beatriz Morales | G7: Leticia | H7: 5 | I7: Tarjeta de crédito | J7: 3 | K7: -4.21528 | L7: -69.94056
A8: Mochila | B8: Deportes y diversión | C8: 105900 | D8: 9000 | E8: 10/06/2020 | F8: Blanca Ramirez | G8: Bogotá | H8: 1 | I8: Cupón | J8: 1 | K8: 4.60971 | L8: -74.08175
A9: Tablet ABXY | B9: Electrónicos | C9: 962600 | D9: 49400 | E9: 12/04/2022 | F9: Juliana Costa | G9: Medellín | H9: 4 | I9: Nequi | J9: 1 | K9: 6.25184 | L9: -75.56359
A10: Olla de presión | B10: Artículos para el hogar | C10: 82800 | D10: 4800 | E10: 11/04/2022 | F10: Izabela de León | G10: Barranquilla | H10: 5 | I10: Nequi | J10: 1 | K10: 10.96854 | L10: -74.78132
A11: Cubo mágico 8x8 | B11: Juguetes | C11: 9100 | D11: 3800 | E11: 04/09/2021 | F11: Camila Rivera | G11: Bogotá | H11: 5 | I11: Tarjeta de crédito | J11: 1 | K11: 4.60971 | L11: -74.08175
A12: Mochila | B12: Deportes y diversión | C12: 86800 | D12: 9300 | E12: 18/04/2020 | F12: Izabela de León | G12: Medellín | H12: 5 | I12: Tarjeta de crédito | J12: 5 | K12: 6.25184 | L12: -75.56359
A13: Secadora de ropa | B13: Electrodomésticos | C13: 878900 | D13: 47000 | E13: 25/09/2021 | F13: Rafael Acosta | G13: Barranquilla | H13: 1 | I13: Tarjeta de crédito | J13: 2 | K13: 10.96854 | L13: -74.78132
... A2360: Bicicleta | B2360: Deportes y diversión | C2360: 551000 | D2360: 27500 | E2360: 03/09/2022 | F2360: Maria Alfonso | G2360: Medellín | H2360: 4 | I2360: Tarjeta de crédito | J2360: 1 | K2360: 6.25184 | L2360: -75.56359

Sheet Tienda_3
A1: Producto | B1: Categoría del Producto | C1: Precio | D1: Costo de envío | E1: Fecha de Compra | F1: Vendedor | G1: Lugar de Compra | H1: Calificación | I1: Método de pago | J1: Cantidad de cuotas | K1: lat | L1: lon
A2: Secadora de ropa | B2: Electrodomésticos | C2: 1285100 | D2: 66600 | E2: 17/12/2021 | F2: Camila Rivera | G2: Santa Marta | H2: 4 | I2: Tarjeta de crédito | J2: 4 | K2: 11.24079 | L2: -74.19904
A3: Mesa de noche | B3: Muebles | C3: 290100 | D3: 13600 | E3: 10/02/2021 | F3: Maria Alfonso | G3: Cali | H3: 3 | I3: Tarjeta de crédito | J3: 1 | K3: 3.43722 | L3: -76.5225
A4: Guitarra acústica | B4: Instrumentos musicales | C4: 303500 | D4: 17400 | E4: 22/01/2023 | F4: Lucas Olivera | G4: Bogotá | H4: 5 | I4: Tarjeta de crédito | J4: 3 | K4: 4.60971 | L4: -74.08175
A5: Balón de voleibol | B5: Deportes y diversión | C5: 58800 | D5: 3300 | E5: 22/03/2022 | F5: Pedro Gomez | G5: Barranquilla | H5: 4 | I5: Tarjeta de crédito | J5: 6 | K5: 10.96854 | L5: -74.78132
A6: Armario | B6: Muebles | C6: 521100 | D6: 25900 | E6: 12/01/2022 | F6: Blanca Ramirez | G6: Bogotá | H6: 1 | I6: Tarjeta de crédito | J6: 1 | K6: 4.60971 | L6: -74.08175
A7: Impresora | B7: Electrónicos | C7: 230700 | D7: 10500 | E7: 20/11/2022 | F7: Mariana Herrera | G7: Medellín | H7: 5 | I7: Tarjeta de crédito | J7: 5 | K7: 6.25184 | L7: -75.56359
A8: Carrito de control remoto | B8: Juguetes | C8: 55700 | D8: 3200 | E8: 07/07/2020 | F8: Ángel Rodriguez | G8: Bogotá | H8: 2 | I8: Nequi | J8: 1 | K8: 4.60971 | L8: -74.08175
A9: Silla de oficina | B9: Muebles | C9: 464600 | D9: 25100 | E9: 01/05/2022 | F9: Santiago Silva | G9: Bogotá | H9: 5 | I9: Nequi | J9: 1 | K9: 4.60971 | L9: -74.08175
A10: Pandereta | B10: Instrumentos musicales | C10: 43500 | D10: 2700 | E10: 27/10/2021 | F10: Maria Alfonso | G10: Medellín | H10: 5 | I10: Tarjeta de crédito | J10: 3 | K10: 6.25184 | L10: -75.56359
A11: Cubertería | B11: Artículos para el hogar | C11: 33500 | D11: 0 | E11: 03/05/2022 | F11: Felipe Santos | G11: Medellín | H11: 5 | I11: Nequi | J11: 1 | K11: 6.25184 | L11: -75.56359
A12: Muñeca bebé | B12: Juguetes | C12: 45500 | D12: 0 | E12: 16/08/2021 | F12: Beatriz Morales | G12: Neiva | H12: 5 | I12: Nequi | J12: 1 | K12: 2.9273 | L12: -75.28189
A13: Silla de oficina | B13: Muebles | C13: 435200 | D13: 21400 | E13: 25/09/2022 | F13: Felipe Santos | G13: Cúcuta | H13: 2 | I13: Tarjeta de crédito | J13: 1 | K13: 7.89391 | L13: -72.50782
... A2360: Modelado predictivo | B2360: Libros | C2360: 63400 | D2360: 9400 | E2360: 24/05/2022 | F2360: Mariana Herrera | G2360: Medellín | H2360: 5 | I2360: Tarjeta de crédito | J2360: 10 | K2360: 6.25184 | L2360: -75.56359

Sheet Tienda_4
A1: Producto | B1: Categoría del Producto | C1: Precio | D1: Costo de envío | E1: Fecha de Compra | F1: Vendedor | G1: Lugar de Compra | H1: Calificación | I1: Método de pago | J1: Cantidad de cuotas | K1: lat | L1: lon
A2: Lavavajillas | B2: Electrodomésticos | C2: 1084800 | D2: 56000 | E2: 11/11/2022 | F2: Rafael Acosta | G2: Bogotá | H2: 4 | I2: Tarjeta de crédito | J2: 3 | K2: 4.60971 | L2: -74.08175
A3: Cama box | B3: Muebles | C3: 473800 | D3: 25400 | E3: 03/01/2020 | F3: Izabela de León | G3: Cúcuta | H3: 5 | I3: Tarjeta de crédito | J3: 2 | K3: 7.89391 | L3: -72.50782
A4: Balón de baloncesto | B4: Deportes y diversión | C4: 23700 | D4: 0 | E4: 25/12/2022 | F4: Maria Alfonso | G4: Medellín | H4: 5 | I4: Nequi | J4: 1 | K4: 6.25184 | L4: -75.56359
A5: Modelado predictivo | B5: Libros | C5: 57700 | D5: 1300 | E5: 23/11/2021 | F5: Lucas Olivera | G5: Medellín | H5: 3 | I5: Nequi | J5: 1 | K5: 6.25184 | L5: -75.56359
A6: Auriculares | B6: Electrónicos | C6: 138900 | D6: 5600 | E6: 25/04/2022 | F6: Blanca Ramirez | G6: Bogotá | H6: 4 | I6: Tarjeta de crédito | J6: 7 | K6: 4.60971 | L6: -74.08175
A7: Refrigerador | B7: Electrodomésticos | C7: 1591900 | D7: 83000 | E7: 30/05/2020 | F7: Beatriz Morales | G7: Cartagena | H7: 1 | I7: Tarjeta de crédito | J7: 10 | K7: 10.39972 | L7: -75.51444
A8: Guitarra eléctrica | B8: Instrumentos musicales | C8: 626200 | D8: 38000 | E8: 11/07/2021 | F8: Izabela de León | G8: Medellín | H8: 5 | I8: Tarjeta de crédito | J8: 1 | K8: 6.25184 | L8: -75.56359
A9: Auriculares con micrófono | B9: Electrónicos | C9: 94500 | D9: 11900 | E9: 19/02/2022 | F9: Santiago Silva | G9: Medellín | H9: 4 | I9: Tarjeta de crédito | J9: 2 | K9: 6.25184 | L9: -75.56359
A10: Iphone 15 | B10: Electrónicos | C10: 2339000 | D10: 122700 | E10: 15/10/2022 | F10: Camila Rivera | G10: Bogotá | H10: 5 | I10: Tarjeta de crédito | J10: 3 | K10: 4.60971 | L10: -74.08175
A11: Mesa de noche | B11: Muebles | C11: 273300 | D11: 21900 | E11: 18/11/2022 | F11: Rafael Acosta | G11: Bogotá | H11: 1 | I11: Tarjeta de crédito | J11: 3 | K11: 4.60971 | L11: -74.08175
A12: Balón de baloncesto | B12: Deportes y diversión | C12: 68000 | D12: 6000 | E12: 03/03/2022 | F12: Felipe Santos | G12: Manizales | H12: 4 | I12: Nequi | J12: 1 | K12: 5.06889 | L12: -75.51738
A13: Muñeca bebé | B13: Juguetes | C13: 47500 | D13: 0 | E13: 16/09/2020 | F13: Pedro Gomez | G13: Bogotá | H13: 5 | I13: Tarjeta de crédito | J13: 2 | K13: 4.60971 | L13: -74.08175
... A2359: Cuerda para saltar | B2359: Deportes y diversión | C2359: 11200 | D2359: 1300 | E2359: 17/11/2021 | F2359: Felipe Santos | G2359: Bogotá | H2359: 5 | I2359: Tarjeta de crédito | J2359: 1 | K2359: 4.60971 | L2359: -74.08175

Sheet Análisis
A1: Análisis de ventas — Tiendas 1 a 4
A2: Todas las cifras se recalculan automáticamente al editar los datos de las hojas Tienda_1 a Tienda_4. | J2: Datos de apoyo para gráficos (calculados)
A4: 1. Resumen por tienda | J4: Tienda | K4: Ingresos
A5: Métrica | B5: Tienda 1 | C5: Tienda 2 | D5: Tienda 3 | E5: Tienda 4 | F5: Total / Prom. | J5: =B5 -> Tienda 1 | K5: =B7 -> 1150880400
A6: N° de ventas | B6: =COUNTA(Tienda_1!$A$2:$A$100000) -> 2359 | C6: =COUNTA(Tienda_2!$A$2:$A$100000) -> 2359 | D6: =COUNTA(Tienda_3!$A$2:$A$100000) -> 2359 | E6: =COUNTA(Tienda_4!$A$2:$A$100000) -> 2358 | F6: =SUM(B6:E6) -> 9435 | J6: =C5 -> Tienda 2 | K6: =C7 -> 1116343500
A7: Ingresos totales ($) | B7: =SUM(Tienda_1!$C$2:$C$100000) -> 1150880400 | C7: =SUM(Tienda_2!$C$2:$C$100000) -> 1116343500 | D7: =SUM(Tienda_3!$C$2:$C$100000) -> 1098019600 | E7: =SUM(Tienda_4!$C$2:$C$100000) -> 1038375700 | F7: =SUM(B7:E7) -> 4403619200 | J7: =D5 -> Tienda 3 | K7: =D7 -> 1098019600
A8: Ticket promedio ($) | B8: =IFERROR(B7/B6,0) -> 487867.91 | C8: =IFERROR(C7/C6,0) -> 473227.43 | D8: =IFERROR(D7/D6,0) -> 465459.77 | E8: =IFERROR(E7/E6,0) -> 440362.89 | F8: =IFERROR(F7/F6,0) -> 466732.29 | J8: =E5 -> Tienda 4 | K8: =E7 -> 1038375700
A9: Costo de envío total ($) | B9: =SUM(Tienda_1!$D$2:$D$100000) -> 61377900 | C9: =SUM(Tienda_2!$D$2:$D$100000) -> 59485100 | D9: =SUM(Tienda_3!$D$2:$D$100000) -> 58516600 | E9: =SUM(Tienda_4!$D$2:$D$100000) -> 55317400 | F9: =SUM(B9:E9) -> 234697000
A10: Costo de envío promedio ($) | B10: =IFERROR(B9/B6,0) -> 26018.61 | C10: =IFERROR(C9/C6,0) -> 25216.236 | D10: =IFERROR(D9/D6,0) -> 24805.68 | E10: =IFERROR(E9/E6,0) -> 23459.457 | F10: =IFERROR(F9/F6,0) -> 24875.146 | J10: Categoría | K10: Ingresos
A11: Ingreso neto de envíos ($) | B11: =B7-B9 -> 1089502500 | C11: =C7-C9 -> 1056858400 | D11: =D7-D9 -> 1039503000 | E11: =E7-E9 -> 983058300 | F11: =F7-F9 -> 4168922200 | J11: =A18 -> Artículos para el hogar | K11: =F18 -> 57579800
A12: Calificación promedio | B12: =IFERROR(AVERAGE(Tienda_1!$H$2:$H$100000),0) -> 3.976685 | C12: =IFERROR(AVERAGE(Tienda_2!$H$2:$H$100000),0) -> 4.0373039 | D12: =IFERROR(AVERAGE(Tienda_3!$H$2:$H$100000),0) -> 4.0483256 | E12: =IFERROR(AVERAGE(Tienda_4!$H$2:$H$100000),0) -> 3.9957591 | F12: =IFERROR(SUMPRODUCT(B12:E12,B6:E6)/F6,0) -> 4.0145204 | J12: =A19 -> Deportes y diversión | K12: =F19 -> 142977700
A13: Cuotas promedio | B13: =IFERROR(AVERAGE(Tienda_1!$J$2:$J$100000),0) -> 2.9431963 | C13: =IFERROR(AVERAGE(Tienda_2!$J$2:$J$100000),0) -> 2.9025011 | D13: =IFERROR(AVERAGE(Tienda_3!$J$2:$J$100000),0) -> 2.967783 | E13: =IFERROR(AVERAGE(Tienda_4!$J$2:$J$100000),0) -> 2.8960984 | F13: =IFERROR(SUMPRODUCT(B13:E13,B6:E6)/F6,0) -> 2.927398 | J13: =A20 -> Electrodomésticos | K13: =F20 -> 1324751100
A14: Participación en ingresos | B14: =IFERROR(B7/$F$7,0) -> 0.26134876 | C14: =IFERROR(C7/$F$7,0) -> 0.25350591 | D14: =IFERROR(D7/$F$7,0) -> 0.24934481 | E14: =IFERROR(E7/$F$7,0) -> 0.23580052 | F14: =SUM(B14:E14) -> 1 | J14: =A21 -> Electrónicos | K14: =F21 -> 1660576500
J15: =A22 -> Instrumentos musicales | K15: =F22 -> 348772600
A16: 2. Ingresos por categoría de producto | J16: =A23 -> Juguetes | K16: =F23 -> 73604400
A17: Categoría | B17: Tienda 1 | C17: Tienda 2 | D17: Tienda 3 | E17: Tienda 4 | F17: Total ingresos | G17: % del total | H17: N° de ventas | J17: =A24 -> Libros | K17: =F24 -> 37696100
A18: Artículos para el hogar | B18: =SUMIF(Tienda_1!$B$2:$B$100000,$A18,Tienda_1!$C$2:$C$100000) -> 12698400 | C18: =SUMIF(Tienda_2!$B$2:$B$100000,$A18,Tienda_2!$C$2:$C$100000) -> 14746900 | D18: =SUMIF(Tienda_3!$B$2:$B$100000,$A18,Tienda_3!$C$2:$C$100000) -> 15060000 | E18: =SUMIF(Tienda_4!$B$2:$B$100000,$A18,Tienda_4!$C$2:$C$100000) -> 15074500 | F18: =SUM(B18:E18) -> 57579800 | G18: =IFERROR(F18/$F$26,0) -> 0.013075563 | H18: =COUNTIF(Tienda_1!$B$2:$B$100000,$A18)+COUNTIF(Tienda_2!$B$2:$B$100000,$A18)+COUNTIF(Tienda_3!$B$2:$B$100000,$A18)+COUNTIF(Tienda_4!$B$2:$B$100000,$A18) -> 730 | J18: =A25 -> Muebles | K18: =F25 -> 757661000
A19: Deportes y diversión | B19: =SUMIF(Tienda_1!$B$2:$B$100000,$A19,Tienda_1!$C$2:$C$100000) -> 39290000 | C19: =SUMIF(Tienda_2!$B$2:$B$100000,$A19,Tienda_2!$C$2:$C$100000) -> 34744500 | D19: =SUMIF(Tienda_3!$B$2:$B$100000,$A19,Tienda_3!$C$2:$C$100000) -> 35593100 | E19: =SUMIF(Tienda_4!$B$2:$B$100000,$A19,Tienda_4!$C$2:$C$100000) -> 33350100 | F19: =SUM(B19:E19) -> 142977700 | G19: =IFERROR(F19/$F$26,0) -> 0.032468225 | H19: =COUNTIF(Tienda_1!$B$2:$B$100000,$A19)+COUNTIF(Tienda_2!$B$2:$B$100000,$A19)+COUNTIF(Tienda_3!$B$2:$B$100000,$A19)+COUNTIF(Tienda_4!$B$2:$B$100000,$A19) -> 1113
A20: Electrodomésticos | B20: =SUMIF(Tienda_1!$B$2:$B$100000,$A20,Tienda_1!$C$2:$C$100000) -> 363685200 | C20: =SUMIF(Tienda_2!$B$2:$B$100000,$A20,Tienda_2!$C$2:$C$100000) -> 348567800 | D20: =SUMIF(Tienda_3!$B$2:$B$100000,$A20,Tienda_3!$C$2:$C$100000) -> 329237900 | E20: =SUMIF(Tienda_4!$B$2:$B$100000,$A20,Tienda_4!$C$2:$C$100000) -> 283260200 | F20: =SUM(B20:E20) -> 1324751100 | G20: =IFERROR(F20/$F$26,0) -> 0.30083235 | H20: =COUNTIF(Tienda_1!$B$2:$B$100000,$A20)+COUNTIF(Tienda_2!$B$2:$B$100000,$A20)+COUNTIF(Tienda_3!$B$2:$B$100000,$A20)+COUNTIF(Tienda_4!$B$2:$B$100000,$A20) -> 1149
A21: Electrónicos | B21: =SUMIF(Tienda_1!$B$2:$B$100000,$A21,Tienda_1!$C$2:$C$100000) -> 429493500 | C21: =SUMIF(Tienda_2!$B$2:$B$100000,$A21,Tienda_2!$C$2:$C$100000) -> 410831100 | D21: =SUMIF(Tienda_3!$B$2:$B$100000,$A21,Tienda_3!$C$2:$C$100000) -> 410775800 | E21: =SUMIF(Tienda_4!$B$2:$B$100000,$A21,Tienda_4!$C$2:$C$100000) -> 409476100 | F21: =SUM(B21:E21) -> 1660576500 | G21: =IFERROR(F21/$F$26,0) -> 0.37709357 | H21: =COUNTIF(Tienda_1!$B$2:$B$100000,$A21)+COUNTIF(Tienda_2!$B$2:$B$100000,$A21)+COUNTIF(Tienda_3!$B$2:$B$100000,$A21)+COUNTIF(Tienda_4!$B$2:$B$100000,$A21) -> 1772 | J21: Año | K21: Ingresos
A22: Instrumentos musicales | B22: =SUMIF(Tienda_1!$B$2:$B$100000,$A22,Tienda_1!$C$2:$C$100000) -> 91299000 | C22: =SUMIF(Tienda_2!$B$2:$B$100000,$A22,Tienda_2!$C$2:$C$100000) -> 104990300 | D22: =SUMIF(Tienda_3!$B$2:$B$100000,$A22,Tienda_3!$C$2:$C$100000) -> 77380900 | E22: =SUMIF(Tienda_4!$B$2:$B$100000,$A22,Tienda_4!$C$2:$C$100000) -> 75102400 | F22: =SUM(B22:E22) -> 348772600 | G22: =IFERROR(F22/$F$26,0) -> 0.079201353 | H22: =COUNTIF(Tienda_1!$B$2:$B$100000,$A22)+COUNTIF(Tienda_2!$B$2:$B$100000,$A22)+COUNTIF(Tienda_3!$B$2:$B$100000,$A22)+COUNTIF(Tienda_4!$B$2:$B$100000,$A22) -> 753 | J22: =TEXT(A71,"0") -> 2020 | K22: =F71 -> 1341955000
A23: Juguetes | B23: =SUMIF(Tienda_1!$B$2:$B$100000,$A23,Tienda_1!$C$2:$C$100000) -> 17995700 | C23: =SUMIF(Tienda_2!$B$2:$B$100000,$A23,Tienda_2!$C$2:$C$100000) -> 15945400 | D23: =SUMIF(Tienda_3!$B$2:$B$100000,$A23,Tienda_3!$C$2:$C$100000) -> 19401100 | E23: =SUMIF(Tienda_4!$B$2:$B$100000,$A23,Tienda_4!$C$2:$C$100000) -> 20262200 | F23: =SUM(B23:E23) -> 73604400 | G23: =IFERROR(F23/$F$26,0) -> 0.016714524 | H23: =COUNTIF(Tienda_1!$B$2:$B$100000,$A23)+COUNTIF(Tienda_2!$B$2:$B$100000,$A23)+COUNTIF(Tienda_3!$B$2:$B$100000,$A23)+COUNTIF(Tienda_4!$B$2:$B$100000,$A23) -> 1290 | J23: =TEXT(A72,"0") -> 2021 | K23: =F72 -> 1424114300
A24: Libros | B24: =SUMIF(Tienda_1!$B$2:$B$100000,$A24,Tienda_1!$C$2:$C$100000) -> 8784900 | C24: =SUMIF(Tienda_2!$B$2:$B$100000,$A24,Tienda_2!$C$2:$C$100000) -> 10091200 | D24: =SUMIF(Tienda_3!$B$2:$B$100000,$A24,Tienda_3!$C$2:$C$100000) -> 9498700 | E24: =SUMIF(Tienda_4!$B$2:$B$100000,$A24,Tienda_4!$C$2:$C$100000) -> 9321300 | F24: =SUM(B24:E24) -> 37696100 | G24: =IFERROR(F24/$F$26,0) -> 0.0085602543 | H24: =COUNTIF(Tienda_1!$B$2:$B$100000,$A24)+COUNTIF(Tienda_2!$B$2:$B$100000,$A24)+COUNTIF(Tienda_3!$B$2:$B$100000,$A24)+COUNTIF(Tienda_4!$B$2:$B$100000,$A24) -> 742 | J24: =TEXT(A73,"0") -> 2022 | K24: =F73 -> 1327451900
A25: Muebles | B25: =SUMIF(Tienda_1!$B$2:$B$100000,$A25,Tienda_1!$C$2:$C$100000) -> 187633700 | C25: =SUMIF(Tienda_2!$B$2:$B$100000,$A25,Tienda_2!$C$2:$C$100000) -> 176426300 | D25: =SUMIF(Tienda_3!$B$2:$B$100000,$A25,Tienda_3!$C$2:$C$100000) -> 201072100 | E25: =SUMIF(Tienda_4!$B$2:$B$100000,$A25,Tienda_4!$C$2:$C$100000) -> 192528900 | F25: =SUM(B25:E25) -> 757661000 | G25: =IFERROR(F25/$F$26,0) -> 0.17205416 | H25: =COUNTIF(Tienda_1!$B$2:$B$100000,$A25)+COUNTIF(Tienda_2!$B$2:$B$100000,$A25)+COUNTIF(Tienda_3!$B$2:$B$100000,$A25)+COUNTIF(Tienda_4!$B$2:$B$100000,$A25) -> 1886 | J25: =TEXT(A74,"0") -> 2023 | K25: =F74 -> 310098000
A26: Total | B26: =SUM(B18:B25) -> 1150880400 | C26: =SUM(C18:C25) -> 1116343500 | D26: =SUM(D18:D25) -> 1098019600 | E26: =SUM(E18:E25) -> 1038375700 | F26: =SUM(F18:F25) -> 4403619200 | G26: =SUM(G18:G25) -> 1 | H26: =SUM(H18:H25) -> 9435
A28: 3. Ingresos por ciudad de compra
A29: Ciudad | B29: Tienda 1 | C29: Tienda 2 | D29: Tienda 3 | E29: Tienda 4 | F29: Total ingresos | G29: % del total | H29: N° de ventas
A30: Armenia | B30: =SUMIF(Tienda_1!$G$2:$G$100000,$A30,Tienda_1!$C$2:$C$100000) -> 4615700 | C30: =SUMIF(Tienda_2!$G$2:$G$100000,$A30,Tienda_2!$C$2:$C$100000) -> 3363200 | D30: =SUMIF(Tienda_3!$G$2:$G$100000,$A30,Tienda_3!$C$2:$C$100000) -> 3980300 | E30: =SUMIF(Tienda_4!$G$2:$G$100000,$A30,Tienda_4!$C$2:$C$100000) -> 283700 | F30: =SUM(B30:E30) -> 12242900 | G30: =IFERROR(F30/$F$49,0) -> 0.0027801904 | H30: =COUNTIF(Tienda_1!$G$2:$G$100000,$A30)+COUNTIF(Tienda_2!$G$2:$G$100000,$A30)+COUNTIF(Tienda_3!$G$2:$G$100000,$A30)+COUNTIF(Tienda_4!$G$2:$G$100000,$A30) -> 28
A31: Barranquilla | B31: =SUMIF(Tienda_1!$G$2:$G$100000,$A31,Tienda_1!$C$2:$C$100000) -> 32907700 | C31: =SUMIF(Tienda_2!$G$2:$G$100000,$A31,Tienda_2!$C$2:$C$100000) -> 27741300 | D31: =SUMIF(Tienda_3!$G$2:$G$100000,$A31,Tienda_3!$C$2:$C$100000) -> 36768500 | E31: =SUMIF(Tienda_4!$G$2:$G$100000,$A31,Tienda_4!$C$2:$C$100000) -> 34623000 | F31: =SUM(B31:E31) -> 132040500 | G31: =IFERROR(F31/$F$49,0) -> 0.029984541 | H31: =COUNTIF(Tienda_1!$G$2:$G$100000,$A31)+COUNTIF(Tienda_2!$G$2:$G$100000,$A31)+COUNTIF(Tienda_3!$G$2:$G$100000,$A31)+COUNTIF(Tienda_4!$G$2:$G$100000,$A31) -> 310
A32: Bogotá | B32: =SUMIF(Tienda_1!$G$2:$G$100000,$A32,Tienda_1!$C$2:$C$100000) -> 440005000 | C32: =SUMIF(Tienda_2!$G$2:$G$100000,$A32,Tienda_2!$C$2:$C$100000) -> 479959200 | D32: =SUMIF(Tienda_3!$G$2:$G$100000,$A32,Tienda_3!$C$2:$C$100000) -> 475562100 | E32: =SUMIF(Tienda_4!$G$2:$G$100000,$A32,Tienda_4!$C$2:$C$100000) -> 419332000 | F32: =SUM(B32:E32) -> 1814858300 | G32: =IFERROR(F32/$F$49,0) -> 0.4121288 | H32: =COUNTIF(Tienda_1!$G$2:$G$100000,$A32)+COUNTIF(Tienda_2!$G$2:$G$100000,$A32)+COUNTIF(Tienda_3!$G$2:$G$100000,$A32)+COUNTIF(Tienda_4!$G$2:$G$100000,$A32) -> 3943
A33: Bucaramanga | B33: =SUMIF(Tienda_1!$G$2:$G$100000,$A33,Tienda_1!$C$2:$C$100000) -> 17579200 | C33: =SUMIF(Tienda_2!$G$2:$G$100000,$A33,Tienda_2!$C$2:$C$100000) -> 23895600 | D33: =SUMIF(Tienda_3!$G$2:$G$100000,$A33,Tienda_3!$C$2:$C$100000) -> 23538900 | E33: =SUMIF(Tienda_4!$G$2:$G$100000,$A33,Tienda_4!$C$2:$C$100000) -> 25559600 | F33: =SUM(B33:E33) -> 90573300 | G33: =IFERROR(F33/$F$49,0) -> 0.020567923 | H33: =COUNTIF(Tienda_1!$G$2:$G$100000,$A33)+COUNTIF(Tienda_2!$G$2:$G$100000,$A33)+COUNTIF(Tienda_3!$G$2:$G$100000,$A33)+COUNTIF(Tienda_4!$G$2:$G$100000,$A33) -> 181
A34: Cali | B34: =SUMIF(Tienda_1!$G$2:$G$100000,$A34,Tienda_1!$C$2:$C$100000) -> 154493700 | C34: =SUMIF(Tienda_2!$G$2:$G$100000,$A34,Tienda_2!$C$2:$C$100000) -> 118257600 | D34: =SUMIF(Tienda_3!$G$2:$G$100000,$A34,Tienda_3!$C$2:$C$100000) -> 109287600 | E34: =SUMIF(Tienda_4!$G$2:$G$100000,$A34,Tienda_4!$C$2:$C$100000) -> 124487200 | F34: =SUM(B34:E34) -> 506526100 | G34: =IFERROR(F34/$F$49,0) -> 0.11502495 | H34: =COUNTIF(Tienda_1!$G$2:$G$100000,$A34)+COUNTIF(Tienda_2!$G$2:$G$100000,$A34)+COUNTIF(Tienda_3!$G$2:$G$100000,$A34)+COUNTIF(Tienda_4!$G$2:$G$100000,$A34) -> 1007
A35: Cartagena | B35: =SUMIF(Tienda_1!$G$2:$G$100000,$A35,Tienda_1!$C$2:$C$100000) -> 22296700 | C35: =SUMIF(Tienda_2!$G$2:$G$100000,$A35,Tienda_2!$C$2:$C$100000) -> 21548300 | D35: =SUMIF(Tienda_3!$G$2:$G$100000,$A35,Tienda_3!$C$2:$C$100000) -> 34144100 | E35: =SUMIF(Tienda_4!$G$2:$G$100000,$A35,Tienda_4!$C$2:$C$100000) -> 24387600 | F35: =SUM(B35:E35) -> 102376700 | G35: =IFERROR(F35/$F$49,0) -> 0.023248309 | H35: =COUNTIF(Tienda_1!$G$2:$G$100000,$A35)+COUNTIF(Tienda_2!$G$2:$G$100000,$A35)+COUNTIF(Tienda_3!$G$2:$G$100000,$A35)+COUNTIF(Tienda_4!$G$2:$G$100000,$A35) -> 242
A36: Cúcuta | B36: =SUMIF(Tienda_1!$G$2:$G$100000,$A36,Tienda_1!$C$2:$C$100000) -> 37879500 | C36: =SUMIF(Tienda_2!$G$2:$G$100000,$A36,Tienda_2!$C$2:$C$100000) -> 28991500 | D36: =SUMIF(Tienda_3!$G$2:$G$100000,$A36,Tienda_3!$C$2:$C$100000) -> 25165500 | E36: =SUMIF(Tienda_4!$G$2:$G$100000,$A36,Tienda_4!$C$2:$C$100000) -> 7332600 | F36: =SUM(B36:E36) -> 99369100 | G36: =IFERROR(F36/$F$49,0) -> 0.022565325 | H36: =COUNTIF(Tienda_1!$G$2:$G$100000,$A36)+COUNTIF(Tienda_2!$G$2:$G$100000,$A36)+COUNTIF(Tienda_3!$G$2:$G$100000,$A36)+COUNTIF(Tienda_4!$G$2:$G$100000,$A36) -> 186
A37: Inírida | B37: =SUMIF(Tienda_1!$G$2:$G$100000,$A37,Tienda_1!$C$2:$C$100000) -> 2722500 | C37: =SUMIF(Tienda_2!$G$2:$G$100000,$A37,Tienda_2!$C$2:$C$100000) -> 2504600 | D37: =SUMIF(Tienda_3!$G$2:$G$100000,$A37,Tienda_3!$C$2:$C$100000) -> 1333700 | E37: =SUMIF(Tienda_4!$G$2:$G$100000,$A37,Tienda_4!$C$2:$C$100000) -> 1527100 | F37: =SUM(B37:E37) -> 8087900 | G37: =IFERROR(F37/$F$49,0) -> 0.0018366484 | H37: =COUNTIF(Tienda_1!$G$2:$G$100000,$A37)+COUNTIF(Tienda_2!$G$2:$G$100000,$A37)+COUNTIF(Tienda_3!$G$2:$G$100000,$A37)+COUNTIF(Tienda_4!$G$2:$G$100000,$A37) -> 14
A38: Leticia | B38: =SUMIF(Tienda_1!$G$2:$G$100000,$A38,Tienda_1!$C$2:$C$100000) -> 14669800 | C38: =SUMIF(Tienda_2!$G$2:$G$100000,$A38,Tienda_2!$C$2:$C$100000) -> 16159000 | D38: =SUMIF(Tienda_3!$G$2:$G$100000,$A38,Tienda_3!$C$2:$C$100000) -> 19212800 | E38: =SUMIF(Tienda_4!$G$2:$G$100000,$A38,Tienda_4!$C$2:$C$100000) -> 17108300 | F38: =SUM(B38:E38) -> 67149900 | G38: =IFERROR(F38/$F$49,0) -> 0.015248798 | H38: =COUNTIF(Tienda_1!$G$2:$G$100000,$A38)+COUNTIF(Tienda_2!$G$2:$G$100000,$A38)+COUNTIF(Tienda_3!$G$2:$G$100000,$A38)+COUNTIF(Tienda_4!$G$2:$G$100000,$A38) -> 142
A39: Manizales | B39: =SUMIF(Tienda_1!$G$2:$G$100000,$A39,Tienda_1!$C$2:$C$100000) -> 8027600 | C39: =SUMIF(Tienda_2!$G$2:$G$100000,$A39,Tienda_2!$C$2:$C$100000) -> 3539900 | D39: =SUMIF(Tienda_3!$G$2:$G$100000,$A39,Tienda_3!$C$2:$C$100000) -> 6501800 | E39: =SUMIF(Tienda_4!$G$2:$G$100000,$A39,Tienda_4!$C$2:$C$100000) -> 1298600 | F39: =SUM(B39:E39) -> 19367900 | G39: =IFERROR(F39/$F$49,0) -> 0.0043981778 | H39: =COUNTIF(Tienda_1!$G$2:$G$100000,$A39)+COUNTIF(Tienda_2!$G$2:$G$100000,$A39)+COUNTIF(Tienda_3!$G$2:$G$100000,$A39)+COUNTIF(Tienda_4!$G$2:$G$100000,$A39) -> 41
A40: Medellín | B40: =SUMIF(Tienda_1!$G$2:$G$100000,$A40,Tienda_1!$C$2:$C$100000) -> 296858100 | C40: =SUMIF(Tienda_2!$G$2:$G$100000,$A40,Tienda_2!$C$2:$C$100000) -> 297246700 | D40: =SUMIF(Tienda_3!$G$2:$G$100000,$A40,Tienda_3!$C$2:$C$100000) -> 250580600 | E40: =SUMIF(Tienda_4!$G$2:$G$100000,$A40,Tienda_4!$C$2:$C$100000) -> 251983800 | F40: =SUM(B40:E40) -> 1096669200 | G40: =IFERROR(F40/$F$49,0) -> 0.24903815 | H40: =COUNTIF(Tienda_1!$G$2:$G$100000,$A40)+COUNTIF(Tienda_2!$G$2:$G$100000,$A40)+COUNTIF(Tienda_3!$G$2:$G$100000,$A40)+COUNTIF(Tienda_4!$G$2:$G$100000,$A40) -> 2314
A41: Neiva | B41: =SUMIF(Tienda_1!$G$2:$G$100000,$A41,Tienda_1!$C$2:$C$100000) -> 3494000 | C41: =SUMIF(Tienda_2!$G$2:$G$100000,$A41,Tienda_2!$C$2:$C$100000) -> 3839400 | D41: =SUMIF(Tienda_3!$G$2:$G$100000,$A41,Tienda_3!$C$2:$C$100000) -> 4359500 | E41: =SUMIF(Tienda_4!$G$2:$G$100000,$A41,Tienda_4!$C$2:$C$100000) -> 9205100 | F41: =SUM(B41:E41) -> 20898000 | G41: =IFERROR(F41/$F$49,0) -> 0.0047456419 | H41: =COUNTIF(Tienda_1!$G$2:$G$100000,$A41)+COUNTIF(Tienda_2!$G$2:$G$100000,$A41)+COUNTIF(Tienda_3!$G$2:$G$100000,$A41)+COUNTIF(Tienda_4!$G$2:$G$100000,$A41) -> 40
... A48: Villavicencio | B48: =SUMIF(Tienda_1!$G$2:$G$100000,$A48,Tienda_1!$C$2:$C$100000) -> 7161900 | C48: =SUMIF(Tienda_2!$G$2:$G$100000,$A48,Tienda_2!$C$2:$C$100000) -> 3597100 | D48: =SUMIF(Tienda_3!$G$2:$G$100000,$A48,Tienda_3!$C$2:$C$100000) -> 988000 | E48: =SUMIF(Tienda_4!$G$2:$G$100000,$A48,Tienda_4!$C$2:$C$100000) -> 1586600 | F48: =SUM(B48:E48) -> 13333600 | G48: =IFERROR(F48/$F$49,0) -> 0.0030278731 | H48: =COUNTIF(Tienda_1!$G$2:$G$100000,$A48)+COUNTIF(Tienda_2!$G$2:$G$100000,$A48)+COUNTIF(Tienda_3!$G$2:$G$100000,$A48)+COUNTIF(Tienda_4!$G$2:$G$100000,$A48) -> 29
A49: Total | B49: =SUM(B30:B48) -> 1150880400 | C49: =SUM(C30:C48) -> 1116343500 | D49: =SUM(D30:D48) -> 1098019600 | E49: =SUM(E30:E48) -> 1038375700 | F49: =SUM(F30:F48) -> 4403619200 | G49: =SUM(G30:G48) -> 1 | H49: =SUM(H30:H48) -> 9435
A51: 4. Desempeño por vendedor
A52: Vendedor | B52: N° de ventas | C52: Ingresos totales | D52: Ticket promedio | E52: Calificación promedio | F52: % del total
A53: Beatriz Morales | B53: =COUNTIF(Tienda_1!$F$2:$F$100000,$A53)+COUNTIF(Tienda_2!$F$2:$F$100000,$A53)+COUNTIF(Tienda_3!$F$2:$F$100000,$A53)+COUNTIF(Tienda_4!$F$2:$F$100000,$A53) -> 650 | C53: =SUMIF(Tienda_1!$F$2:$F$100000,$A53,Tienda_1!$C$2:$C$100000)+SUMIF(Tienda_2!$F$2:$F$100000,$A53,Tienda_2!$C$2:$C$100000)+SUMIF(Tienda_3!$F$2:$F$100000,$A53,Tienda_3!$C$2:$C$100000)+SUMIF(Tienda_4!$F$2:$F$100000,$A53,Tienda_4!$C$2:$C$100000) -> 302695600 | D53: =IFERROR(C53/B53,0) -> 465685.54 | E53: =IFERROR((SUMIF(Tienda_1!$F$2:$F$100000,$A53,Tienda_1!$H$2:$H$100000)+SUMIF(Tienda_2!$F$2:$F$100000,$A53,Tienda_2!$H$2:$H$100000)+SUMIF(Tienda_3!$F$2:$F$100000,$A53,Tienda_3!$H$2:$H$100000)+SUMIF(Tienda_4!$F$2:$F$100000,$A53,Tienda_4!$H$2:$H$100000))/B53,0) -> 4.0476923 | F53: =IFERROR(C53/$C$67,0) -> 0.068737914
A54: Blanca Ramirez | B54: =COUNTIF(Tienda_1!$F$2:$F$100000,$A54)+COUNTIF(Tienda_2!$F$2:$F$100000,$A54)+COUNTIF(Tienda_3!$F$2:$F$100000,$A54)+COUNTIF(Tienda_4!$F$2:$F$100000,$A54) -> 679 | C54: =SUMIF(Tienda_1!$F$2:$F$100000,$A54,Tienda_1!$C$2:$C$100000)+SUMIF(Tienda_2!$F$2:$F$100000,$A54,Tienda_2!$C$2:$C$100000)+SUMIF(Tienda_3!$F$2:$F$100000,$A54,Tienda_3!$C$2:$C$100000)+SUMIF(Tienda_4!$F$2:$F$100000,$A54,Tienda_4!$C$2:$C$100000) -> 299586600 | D54: =IFERROR(C54/B54,0) -> 441217.38 | E54: =IFERROR((SUMIF(Tienda_1!$F$2:$F$100000,$A54,Tienda_1!$H$2:$H$100000)+SUMIF(Tienda_2!$F$2:$F$100000,$A54,Tienda_2!$H$2:$H$100000)+SUMIF(Tienda_3!$F$2:$F$100000,$A54,Tienda_3!$H$2:$H$100000)+SUMIF(Tienda_4!$F$2:$F$100000,$A54,Tienda_4!$H$2:$H$100000))/B54,0) -> 3.994109 | F54: =IFERROR(C54/$C$67,0) -> 0.068031904
A55: Camila Rivera | B55: =COUNTIF(Tienda_1!$F$2:$F$100000,$A55)+COUNTIF(Tienda_2!$F$2:$F$100000,$A55)+COUNTIF(Tienda_3!$F$2:$F$100000,$A55)+COUNTIF(Tienda_4!$F$2:$F$100000,$A55) -> 667 | C55: =SUMIF(Tienda_1!$F$2:$F$100000,$A55,Tienda_1!$C$2:$C$100000)+SUMIF(Tienda_2!$F$2:$F$100000,$A55,Tienda_2!$C$2:$C$100000)+SUMIF(Tienda_3!$F$2:$F$100000,$A55,Tienda_3!$C$2:$C$100000)+SUMIF(Tienda_4!$F$2:$F$100000,$A55,Tienda_4!$C$2:$C$100000) -> 303184200 | D55: =IFERROR(C55/B55,0) -> 454549.03 | E55: =IFERROR((SUMIF(Tienda_1!$F$2:$F$100000,$A55,Tienda_1!$H$2:$H$100000)+SUMIF(Tienda_2!$F$2:$F$100000,$A55,Tienda_2!$H$2:$H$100000)+SUMIF(Tienda_3!$F$2:$F$100000,$A55,Tienda_3!$H$2:$H$100000)+SUMIF(Tienda_4!$F$2:$F$100000,$A55,Tienda_4!$H$2:$H$100000))/B55,0) -> 4.0329835 | F55: =IFERROR(C55/$C$67,0) -> 0.068848869
A56: Felipe Santos | B56: =COUNTIF(Tienda_1!$F$2:$F$100000,$A56)+COUNTIF(Tienda_2!$F$2:$F$100000,$A56)+COUNTIF(Tienda_3!$F$2:$F$100000,$A56)+COUNTIF(Tienda_4!$F$2:$F$100000,$A56) -> 701 | C56: =SUMIF(Tienda_1!$F$2:$F$100000,$A56,Tienda_1!$C$2:$C$100000)+SUMIF(Tienda_2!$F$2:$F$100000,$A56,Tienda_2!$C$2:$C$100000)+SUMIF(Tienda_3!$F$2:$F$100000,$A56,Tienda_3!$C$2:$C$100000)+SUMIF(Tienda_4!$F$2:$F$100000,$A56,Tienda_4!$C$2:$C$100000) -> 353796000 | D56: =IFERROR(C56/B56,0) -> 504701.85 | E56: =IFERROR((SUMIF(Tienda_1!$F$2:$F$100000,$A56,Tienda_1!$H$2:$H$100000)+SUMIF(Tienda_2!$F$2:$F$100000,$A56,Tienda_2!$H$2:$H$100000)+SUMIF(Tienda_3!$F$2:$F$100000,$A56,Tienda_3!$H$2:$H$100000)+SUMIF(Tienda_4!$F$2:$F$100000,$A56,Tienda_4!$H$2:$H$100000))/B56,0) -> 4.0756063 | F56: =IFERROR(C56/$C$67,0) -> 0.080342097
A57: Izabela de León | B57: =COUNTIF(Tienda_1!$F$2:$F$100000,$A57)+COUNTIF(Tienda_2!$F$2:$F$100000,$A57)+COUNTIF(Tienda_3!$F$2:$F$100000,$A57)+COUNTIF(Tienda_4!$F$2:$F$100000,$A57) -> 744 | C57: =SUMIF(Tienda_1!$F$2:$F$100000,$A57,Tienda_1!$C$2:$C$100000)+SUMIF(Tienda_2!$F$2:$F$100000,$A57,Tienda_2!$C$2:$C$100000)+SUMIF(Tienda_3!$F$2:$F$100000,$A57,Tienda_3!$C$2:$C$100000)+SUMIF(Tienda_4!$F$2:$F$100000,$A57,Tienda_4!$C$2:$C$100000) -> 350342400 | D57: =IFERROR(C57/B57,0) -> 470890.32 | E57: =IFERROR((SUMIF(Tienda_1!$F$2:$F$100000,$A57,Tienda_1!$H$2:$H$100000)+SUMIF(Tienda_2!$F$2:$F$100000,$A57,Tienda_2!$H$2:$H$100000)+SUMIF(Tienda_3!$F$2:$F$100000,$A57,Tienda_3!$H$2:$H$100000)+SUMIF(Tienda_4!$F$2:$F$100000,$A57,Tienda_4!$H$2:$H$100000))/B57,0) -> 3.858871 | F57: =IFERROR(C57/$C$67,0) -> 0.079557833
A58: Juan Fernandez | B58: =COUNTIF(Tienda_1!$F$2:$F$100000,$A58)+COUNTIF(Tienda_2!$F$2:$F$100000,$A58)+COUNTIF(Tienda_3!$F$2:$F$100000,$A58)+COUNTIF(Tienda_4!$F$2:$F$100000,$A58) -> 694 | C58: =SUMIF(Tienda_1!$F$2:$F$100000,$A58,Tienda_1!$C$2:$C$100000)+SUMIF(Tienda_2!$F$2:$F$100000,$A58,Tienda_2!$C$2:$C$100000)+SUMIF(Tienda_3!$F$2:$F$100000,$A58,Tienda_3!$C$2:$C$100000)+SUMIF(Tienda_4!$F$2:$F$100000,$A58,Tienda_4!$C$2:$C$100000) -> 308562100 | D58: =IFERROR(C58/B58,0) -> 444613.98 | E58: =IFERROR((SUMIF(Tienda_1!$F$2:$F$100000,$A58,Tienda_1!$H$2:$H$100000)+SUMIF(Tienda_2!$F$2:$F$100000,$A58,Tienda_2!$H$2:$H$100000)+SUMIF(Tienda_3!$F$2:$F$100000,$A58,Tienda_3!$H$2:$H$100000)+SUMIF(Tienda_4!$F$2:$F$100000,$A58,Tienda_4!$H$2:$H$100000))/B58,0) -> 4.0331412 | F58: =IFERROR(C58/$C$67,0) -> 0.070070114
A59: Juliana Costa | B59: =COUNTIF(Tienda_1!$F$2:$F$100000,$A59)+COUNTIF(Tienda_2!$F$2:$F$100000,$A59)+COUNTIF(Tienda_3!$F$2:$F$100000,$A59)+COUNTIF(Tienda_4!$F$2:$F$100000,$A59) -> 677 | C59: =SUMIF(Tienda_1!$F$2:$F$100000,$A59,Tienda_1!$C$2:$C$100000)+SUMIF(Tienda_2!$F$2:$F$100000,$A59,Tienda_2!$C$2:$C$100000)+SUMIF(Tienda_3!$F$2:$F$100000,$A59,Tienda_3!$C$2:$C$100000)+SUMIF(Tienda_4!$F$2:$F$100000,$A59,Tienda_4!$C$2:$C$100000) -> 338364700 | D59: =IFERROR(C59/B59,0) -> 499800.15 | E59: =IFERROR((SUMIF(Tienda_1!$F$2:$F$100000,$A59,Tienda_1!$H$2:$H$100000)+SUMIF(Tienda_2!$F$2:$F$100000,$A59,Tienda_2!$H$2:$H$100000)+SUMIF(Tienda_3!$F$2:$F$100000,$A59,Tienda_3!$H$2:$H$100000)+SUMIF(Tienda_4!$F$2:$F$100000,$A59,Tienda_4!$H$2:$H$100000))/B59,0) -> 3.9187592 | F59: =IFERROR(C59/$C$67,0) -> 0.076837866
A60: Lucas Olivera | B60: =COUNTIF(Tienda_1!$F$2:$F$100000,$A60)+COUNTIF(Tienda_2!$F$2:$F$100000,$A60)+COUNTIF(Tienda_3!$F$2:$F$100000,$A60)+COUNTIF(Tienda_4!$F$2:$F$100000,$A60) -> 674 | C60: =SUMIF(Tienda_1!$F$2:$F$100000,$A60,Tienda_1!$C$2:$C$100000)+SUMIF(Tienda_2!$F$2:$F$100000,$A60,Tienda_2!$C$2:$C$100000)+SUMIF(Tienda_3!$F$2:$F$100000,$A60,Tienda_3!$C$2:$C$100000)+SUMIF(Tienda_4!$F$2:$F$100000,$A60,Tienda_4!$C$2:$C$100000) -> 305403600 | D60: =IFERROR(C60/B60,0) -> 453121.07 | E60: =IFERROR((SUMIF(Tienda_1!$F$2:$F$100000,$A60,Tienda_1!$H$2:$H$100000)+SUMIF(Tienda_2!$F$2:$F$100000,$A60,Tienda_2!$H$2:$H$100000)+SUMIF(Tienda_3!$F$2:$F$100000,$A60,Tienda_3!$H$2:$H$100000)+SUMIF(Tienda_4!$F$2:$F$100000,$A60,Tienda_4!$H$2:$H$100000))/B60,0) -> 3.962908 | F60: =IFERROR(C60/$C$67,0) -> 0.069352863
A61: Maria Alfonso | B61: =COUNTIF(Tienda_1!$F$2:$F$100000,$A61)+COUNTIF(Tienda_2!$F$2:$F$100000,$A61)+COUNTIF(Tienda_3!$F$2:$F$100000,$A61)+COUNTIF(Tienda_4!$F$2:$F$100000,$A61) -> 679 | C61: =SUMIF(Tienda_1!$F$2:$F$100000,$A61,Tienda_1!$C$2:$C$100000)+SUMIF(Tienda_2!$F$2:$F$100000,$A61,Tienda_2!$C$2:$C$100000)+SUMIF(Tienda_3!$F$2:$F$100000,$A61,Tienda_3!$C$2:$C$100000)+SUMIF(Tienda_4!$F$2:$F$100000,$A61,Tienda_4!$C$2:$C$100000) -> 349694800 | D61: =IFERROR(C61/B61,0) -> 515014.43 | E61: =IFERROR((SUMIF(Tienda_1!$F$2:$F$100000,$A61,Tienda_1!$H$2:$H$100000)+SUMIF(Tienda_2!$F$2:$F$100000,$A61,Tienda_2!$H$2:$H$100000)+SUMIF(Tienda_3!$F$2:$F$100000,$A61,Tienda_3!$H$2:$H$100000)+SUMIF(Tienda_4!$F$2:$F$100000,$A61,Tienda_4!$H$2:$H$100000))/B61,0) -> 3.9572901 | F61: =IFERROR(C61/$C$67,0) -> 0.079410772
A62: Mariana Herrera | B62: =COUNTIF(Tienda_1!$F$2:$F$100000,$A62)+COUNTIF(Tienda_2!$F$2:$F$100000,$A62)+COUNTIF(Tienda_3!$F$2:$F$100000,$A62)+COUNTIF(Tienda_4!$F$2:$F$100000,$A62) -> 656 | C62: =SUMIF(Tienda_1!$F$2:$F$100000,$A62,Tienda_1!$C$2:$C$100000)+SUMIF(Tienda_2!$F$2:$F$100000,$A62,Tienda_2!$C$2:$C$100000)+SUMIF(Tienda_3!$F$2:$F$100000,$A62,Tienda_3!$C$2:$C$100000)+SUMIF(Tienda_4!$F$2:$F$100000,$A62,Tienda_4!$C$2:$C$100000) -> 283302600 | D62: =IFERROR(C62/B62,0) -> 431863.72 | E62: =IFERROR((SUMIF(Tienda_1!$F$2:$F$100000,$A62,Tienda_1!$H$2:$H$100000)+SUMIF(Tienda_2!$F$2:$F$100000,$A62,Tienda_2!$H$2:$H$100000)+SUMIF(Tienda_3!$F$2:$F$100000,$A62,Tienda_3!$H$2:$H$100000)+SUMIF(Tienda_4!$F$2:$F$100000,$A62,Tienda_4!$H$2:$H$100000))/B62,0) -> 4.0716463 | F62: =IFERROR(C62/$C$67,0) -> 0.064334037
A63: Pedro Gomez | B63: =COUNTIF(Tienda_1!$F$2:$F$100000,$A63)+COUNTIF(Tienda_2!$F$2:$F$100000,$A63)+COUNTIF(Tienda_3!$F$2:$F$100000,$A63)+COUNTIF(Tienda_4!$F$2:$F$100000,$A63) -> 655 | C63: =SUMIF(Tienda_1!$F$2:$F$100000,$A63,Tienda_1!$C$2:$C$100000)+SUMIF(Tienda_2!$F$2:$F$100000,$A63,Tienda_2!$C$2:$C$100000)+SUMIF(Tienda_3!$F$2:$F$100000,$A63,Tienda_3!$C$2:$C$100000)+SUMIF(Tienda_4!$F$2:$F$100000,$A63,Tienda_4!$C$2:$C$100000) -> 313350900 | D63: =IFERROR(C63/B63,0) -> 478398.32 | E63: =IFERROR((SUMIF(Tienda_1!$F$2:$F$100000,$A63,Tienda_1!$H$2:$H$100000)+SUMIF(Tienda_2!$F$2:$F$100000,$A63,Tienda_2!$H$2:$H$100000)+SUMIF(Tienda_3!$F$2:$F$100000,$A63,Tienda_3!$H$2:$H$100000)+SUMIF(Tienda_4!$F$2:$F$100000,$A63,Tienda_4!$H$2:$H$100000))/B63,0) -> 4.0412214 | F63: =IFERROR(C63/$C$67,0) -> 0.071157583
A64: Rafael Acosta | B64: =COUNTIF(Tienda_1!$F$2:$F$100000,$A64)+COUNTIF(Tienda_2!$F$2:$F$100000,$A64)+COUNTIF(Tienda_3!$F$2:$F$100000,$A64)+COUNTIF(Tienda_4!$F$2:$F$100000,$A64) -> 625 | C64: =SUMIF(Tienda_1!$F$2:$F$100000,$A64,Tienda_1!$C$2:$C$100000)+SUMIF(Tienda_2!$F$2:$F$100000,$A64,Tienda_2!$C$2:$C$100000)+SUMIF(Tienda_3!$F$2:$F$100000,$A64,Tienda_3!$C$2:$C$100000)+SUMIF(Tienda_4!$F$2:$F$100000,$A64,Tienda_4!$C$2:$C$100000) -> 310292300 | D64: =IFERROR(C64/B64,0) -> 496467.68 | E64: =IFERROR((SUMIF(Tienda_1!$F$2:$F$100000,$A64,Tienda_1!$H$2:$H$100000)+SUMIF(Tienda_2!$F$2:$F$100000,$A64,Tienda_2!$H$2:$H$100000)+SUMIF(Tienda_3!$F$2:$F$100000,$A64,Tienda_3!$H$2:$H$100000)+SUMIF(Tienda_4!$F$2:$F$100000,$A64,Tienda_4!$H$2:$H$100000))/B64,0) -> 4.064 | F64: =IFERROR(C64/$C$67,0) -> 0.070463018
... A66: Ángel Rodriguez | B66: =COUNTIF(Tienda_1!$F$2:$F$100000,$A66)+COUNTIF(Tienda_2!$F$2:$F$100000,$A66)+COUNTIF(Tienda_3!$F$2:$F$100000,$A66)+COUNTIF(Tienda_4!$F$2:$F$100000,$A66) -> 684 | C66: =SUMIF(Tienda_1!$F$2:$F$100000,$A66,Tienda_1!$C$2:$C$100000)+SUMIF(Tienda_2!$F$2:$F$100000,$A66,Tienda_2!$C$2:$C$100000)+SUMIF(Tienda_3!$F$2:$F$100000,$A66,Tienda_3!$C$2:$C$100000)+SUMIF(Tienda_4!$F$2:$F$100000,$A66,Tienda_4!$C$2:$C$100000) -> 291625200 | D66: =IFERROR(C66/B66,0) -> 426352.63 | E66: =IFERROR((SUMIF(Tienda_1!$F$2:$F$100000,$A66,Tienda_1!$H$2:$H$100000)+SUMIF(Tienda_2!$F$2:$F$100000,$A66,Tienda_2!$H$2:$H$100000)+SUMIF(Tienda_3!$F$2:$F$100000,$A66,Tienda_3!$H$2:$H$100000)+SUMIF(Tienda_4!$F$2:$F$100000,$A66,Tienda_4!$H$2:$H$100000))/B66,0) -> 4.1345029 | F66: =IFERROR(C66/$C$67,0) -> 0.066223982
A67: Total | B67: =SUM(B53:B66) -> 9435 | C67: =SUM(C53:C66) -> 4403619200 | D67: =IFERROR(C67/B67,0) -> 466732.29 | E67: =IFERROR(SUMPRODUCT(E53:E66,B53:B66)/B67,0) -> 4.0145204 | F67: =SUM(F53:F66) -> 1
A69: 5. Ingresos por año de compra
A70: Año | B70: Tienda 1 | C70: Tienda 2 | D70: Tienda 3 | E70: Tienda 4 | F70: Total ingresos | G70: % del total
A71: 2020 | B71: =SUMPRODUCT((RIGHT(Tienda_1!$E$2:$E$5000,4)=TEXT($A71,"0"))*Tienda_1!$C$2:$C$5000) -> 368933200 | C71: =SUMPRODUCT((RIGHT(Tienda_2!$E$2:$E$5000,4)=TEXT($A71,"0"))*Tienda_2!$C$2:$C$5000) -> 320466600 | D71: =SUMPRODUCT((RIGHT(Tienda_3!$E$2:$E$5000,4)=TEXT($A71,"0"))*Tienda_3!$C$2:$C$5000) -> 321707500 | E71: =SUMPRODUCT((RIGHT(Tienda_4!$E$2:$E$5000,4)=TEXT($A71,"0"))*Tienda_4!$C$2:$C$5000) -> 330847700 | F71: =SUM(B71:E71) -> 1341955000 | G71: =IFERROR(F71/$F$75,0) -> 0.30473911
A72: 2021 | B72: =SUMPRODUCT((RIGHT(Tienda_1!$E$2:$E$5000,4)=TEXT($A72,"0"))*Tienda_1!$C$2:$C$5000) -> 362120800 | C72: =SUMPRODUCT((RIGHT(Tienda_2!$E$2:$E$5000,4)=TEXT($A72,"0"))*Tienda_2!$C$2:$C$5000) -> 351215500 | D72: =SUMPRODUCT((RIGHT(Tienda_3!$E$2:$E$5000,4)=TEXT($A72,"0"))*Tienda_3!$C$2:$C$5000) -> 362954400 | E72: =SUMPRODUCT((RIGHT(Tienda_4!$E$2:$E$5000,4)=TEXT($A72,"0"))*Tienda_4!$C$2:$C$5000) -> 347823600 | F72: =SUM(B72:E72) -> 1424114300 | G72: =IFERROR(F72/$F$75,0) -> 0.32339633
A73: 2022 | B73: =SUMPRODUCT((RIGHT(Tienda_1!$E$2:$E$5000,4)=TEXT($A73,"0"))*Tienda_1!$C$2:$C$5000) -> 316565600 | C73: =SUMPRODUCT((RIGHT(Tienda_2!$E$2:$E$5000,4)=TEXT($A73,"0"))*Tienda_2!$C$2:$C$5000) -> 358226500 | D73: =SUMPRODUCT((RIGHT(Tienda_3!$E$2:$E$5000,4)=TEXT($A73,"0"))*Tienda_3!$C$2:$C$5000) -> 350438300 | E73: =SUMPRODUCT((RIGHT(Tienda_4!$E$2:$E$5000,4)=TEXT($A73,"0"))*Tienda_4!$C$2:$C$5000) -> 302221500 | F73: =SUM(B73:E73) -> 1327451900 | G73: =IFERROR(F73/$F$75,0) -> 0.30144566
A74: 2023 | B74: =SUMPRODUCT((RIGHT(Tienda_1!$E$2:$E$5000,4)=TEXT($A74,"0"))*Tienda_1!$C$2:$C$5000) -> 103260800 | C74: =SUMPRODUCT((RIGHT(Tienda_2!$E$2:$E$5000,4)=TEXT($A74,"0"))*Tienda_2!$C$2:$C$5000) -> 86434900 | D74: =SUMPRODUCT((RIGHT(Tienda_3!$E$2:$E$5000,4)=TEXT($A74,"0"))*Tienda_3!$C$2:$C$5000) -> 62919400 | E74: =SUMPRODUCT((RIGHT(Tienda_4!$E$2:$E$5000,4)=TEXT($A74,"0"))*Tienda_4!$C$2:$C$5000) -> 57482900 | F74: =SUM(B74:E74) -> 310098000 | G74: =IFERROR(F74/$F$75,0) -> 0.070418895
A75: Total | B75: =SUM(B71:B74) -> 1150880400 | C75: =SUM(C71:C74) -> 1116343500 | D75: =SUM(D71:D74) -> 1098019600 | E75: =SUM(E71:E74) -> 1038375700 | F75: =SUM(F71:F74) -> 4403619200 | G75: =SUM(G71:G74) -> 1
A77: 6. Ingresos por método de pago
A78: Método de pago | B78: Tienda 1 | C78: Tienda 2 | D78: Tienda 3 | E78: Tienda 4 | F78: Total ingresos | G78: % del total | H78: N° de ventas
A79: Cupón | B79: =SUMIF(Tienda_1!$I$2:$I$100000,$A79,Tienda_1!$C$2:$C$100000) -> 64105500 | C79: =SUMIF(Tienda_2!$I$2:$I$100000,$A79,Tienda_2!$C$2:$C$100000) -> 77366600 | D79: =SUMIF(Tienda_3!$I$2:$I$100000,$A79,Tienda_3!$C$2:$C$100000) -> 47411300 | E79: =SUMIF(Tienda_4!$I$2:$I$100000,$A79,Tienda_4!$C$2:$C$100000) -> 46986200 | F79: =SUM(B79:E79) -> 235869600 | G79: =IFERROR(F79/$F$83,0) -> 0.05356267 | H79: =COUNTIF(Tienda_1!$I$2:$I$100000,$A79)+COUNTIF(Tienda_2!$I$2:$I$100000,$A79)+COUNTIF(Tienda_3!$I$2:$I$100000,$A79)+COUNTIF(Tienda_4!$I$2:$I$100000,$A79) -> 504
A80: Nequi | B80: =SUMIF(Tienda_1!$I$2:$I$100000,$A80,Tienda_1!$C$2:$C$100000) -> 232609700 | C80: =SUMIF(Tienda_2!$I$2:$I$100000,$A80,Tienda_2!$C$2:$C$100000) -> 210748800 | D80: =SUMIF(Tienda_3!$I$2:$I$100000,$A80,Tienda_3!$C$2:$C$100000) -> 229322400 | E80: =SUMIF(Tienda_4!$I$2:$I$100000,$A80,Tienda_4!$C$2:$C$100000) -> 208003300 | F80: =SUM(B80:E80) -> 880684200 | G80: =IFERROR(F80/$F$83,0) -> 0.199991 | H80: =COUNTIF(Tienda_1!$I$2:$I$100000,$A80)+COUNTIF(Tienda_2!$I$2:$I$100000,$A80)+COUNTIF(Tienda_3!$I$2:$I$100000,$A80)+COUNTIF(Tienda_4!$I$2:$I$100000,$A80) -> 1900
A81: Tarjeta de crédito | B81: =SUMIF(Tienda_1!$I$2:$I$100000,$A81,Tienda_1!$C$2:$C$100000) -> 840665800 | C81: =SUMIF(Tienda_2!$I$2:$I$100000,$A81,Tienda_2!$C$2:$C$100000) -> 816659500 | D81: =SUMIF(Tienda_3!$I$2:$I$100000,$A81,Tienda_3!$C$2:$C$100000) -> 804570700 | E81: =SUMIF(Tienda_4!$I$2:$I$100000,$A81,Tienda_4!$C$2:$C$100000) -> 768711100 | F81: =SUM(B81:E81) -> 3230607100 | G81: =IFERROR(F81/$F$83,0) -> 0.73362545 | H81: =COUNTIF(Tienda_1!$I$2:$I$100000,$A81)+COUNTIF(Tienda_2!$I$2:$I$100000,$A81)+COUNTIF(Tienda_3!$I$2:$I$100000,$A81)+COUNTIF(Tienda_4!$I$2:$I$100000,$A81) -> 6898
A82: Tarjeta de débito | B82: =SUMIF(Tienda_1!$I$2:$I$100000,$A82,Tienda_1!$C$2:$C$100000) -> 13499400 | C82: =SUMIF(Tienda_2!$I$2:$I$100000,$A82,Tienda_2!$C$2:$C$100000) -> 11568600 | D82: =SUMIF(Tienda_3!$I$2:$I$100000,$A82,Tienda_3!$C$2:$C$100000) -> 16715200 | E82: =SUMIF(Tienda_4!$I$2:$I$100000,$A82,Tienda_4!$C$2:$C$100000) -> 14675100 | F82: =SUM(B82:E82) -> 56458300 | G82: =IFERROR(F82/$F$83,0) -> 0.012820886 | H82: =COUNTIF(Tienda_1!$I$2:$I$100000,$A82)+COUNTIF(Tienda_2!$I$2:$I$100000,$A82)+COUNTIF(Tienda_3!$I$2:$I$100000,$A82)+COUNTIF(Tienda_4!$I$2:$I$100000,$A82) -> 133
A83: Total | B83: =SUM(B79:B82) -> 1150880400 | C83: =SUM(C79:C82) -> 1116343500 | D83: =SUM(D79:D82) -> 1098019600 | E83: =SUM(E79:E82) -> 1038375700 | F83: =SUM(F79:F82) -> 4403619200 | G83: =SUM(G79:G82) -> 1 | H83: =SUM(H79:H82) -> 9435
A85: 7. Hallazgos clave (dinámicos)
A86: Tienda con mayores ingresos | B86: =INDEX($B$5:$E$5,MATCH(MAX($B$7:$E$7),$B$7:$E$7,0)) -> Tienda 1 | C86: =MAX($B$7:$E$7) -> 1150880400
A87: Tienda con menores ingresos | B87: =INDEX($B$5:$E$5,MATCH(MIN($B$7:$E$7),$B$7:$E$7,0)) -> Tienda 4 | C87: =MIN($B$7:$E$7) -> 1038375700
A88: Tienda mejor calificada | B88: =INDEX($B$5:$E$5,MATCH(MAX($B$12:$E$12),$B$12:$E$12,0)) -> Tienda 3 | C88: =MAX($B$12:$E$12) -> 4.0483256
A89: Tienda peor calificada | B89: =INDEX($B$5:$E$5,MATCH(MIN($B$12:$E$12),$B$12:$E$12,0)) -> Tienda 1 | C89: =MIN($B$12:$E$12) -> 3.976685
A90: Categoría con mayores ingresos | B90: =INDEX($A$18:$A$25,MATCH(MAX($F$18:$F$25),$F$18:$F$25,0)) -> Electrónicos | C90: =MAX($F$18:$F$25) -> 1660576500
A91: Categoría con menores ingresos | B91: =INDEX($A$18:$A$25,MATCH(MIN($F$18:$F$25),$F$18:$F$25,0)) -> Libros | C91: =MIN($F$18:$F$25) -> 37696100
A92: Ciudad con mayores ingresos | B92: =INDEX($A$30:$A$48,MATCH(MAX($F$30:$F$48),$F$30:$F$48,0)) -> Bogotá | C92: =MAX($F$30:$F$48) -> 1814858300
A93: Vendedor con mayores ingresos | B93: =INDEX($A$53:$A$66,MATCH(MAX($C$53:$C$66),$C$53:$C$66,0)) -> Felipe Santos | C93: =MAX($C$53:$C$66) -> 353796000
A94: Vendedor con menores ingresos | B94: =INDEX($A$53:$A$66,MATCH(MIN($C$53:$C$66),$C$53:$C$66,0)) -> Mariana Herrera | C94: =MIN($C$53:$C$66) -> 283302600
A95: Año con mayores ingresos | B95: =INDEX($A$71:$A$74,MATCH(MAX($F$71:$F$74),$F$71:$F$74,0)) -> 2021 | C95: =MAX($F$71:$F$74) -> 1424114300
A96: Método de pago dominante | B96: =INDEX($A$79:$A$82,MATCH(MAX($F$79:$F$82),$F$79:$F$82,0)) -> Tarjeta de crédito | C96: =MAX($F$79:$F$82) -> 3230607100

Sheet Resumen
B2: Resumen ejecutivo — Ventas Tiendas 1 a 4
B3: Vinculado a la hoja Análisis: se actualiza automáticamente al editar los datos de las tiendas.
B5: Indicadores globales
B6: Ingresos totales | C6: =Análisis!$F$7 -> 4403619200
B7: N° total de ventas | C7: =Análisis!$F$6 -> 9435
B8: Ticket promedio | C8: =Análisis!$F$8 -> 466732.29
B9: Costo de envío total | C9: =Análisis!$F$9 -> 234697000
B10: Ingreso neto de envíos | C10: =Análisis!$F$11 -> 4168922200
B11: Calificación promedio (1-5) | C11: =Análisis!$F$12 -> 4.0145204
B12: Cuotas promedio | C12: =Análisis!$F$13 -> 2.927398
B13: Envío como % de ingresos | C13: =IFERROR(Análisis!$F$9/Análisis!$F$7,0) -> 0.053296389
B15: Comparativo por tienda
B16: Tienda | C16: Ingresos | D16: % del total | E16: Ticket promedio | F16: Calificación
B17: =Análisis!B5 -> Tienda 1 | C17: =Análisis!B7 -> 1150880400 | D17: =Análisis!B14 -> 0.26134876 | E17: =Análisis!B8 -> 487867.91 | F17: =Análisis!B12 -> 3.976685
B18: =Análisis!C5 -> Tienda 2 | C18: =Análisis!C7 -> 1116343500 | D18: =Análisis!C14 -> 0.25350591 | E18: =Análisis!C8 -> 473227.43 | F18: =Análisis!C12 -> 4.0373039
B19: =Análisis!D5 -> Tienda 3 | C19: =Análisis!D7 -> 1098019600 | D19: =Análisis!D14 -> 0.24934481 | E19: =Análisis!D8 -> 465459.77 | F19: =Análisis!D12 -> 4.0483256
B20: =Análisis!E5 -> Tienda 4 | C20: =Análisis!E7 -> 1038375700 | D20: =Análisis!E14 -> 0.23580052 | E20: =Análisis!E8 -> 440362.89 | F20: =Análisis!E12 -> 3.9957591
B21: Total | C21: =SUM(C17:C20) -> 4403619200 | D21: =SUM(D17:D20) -> 1 | E21: =Análisis!F8 -> 466732.29 | F21: =Análisis!F12 -> 4.0145204
B23: Rankings (Top 3 y último)
B24: Dimensión / Puesto | C24: Nombre | D24: Ingresos
B25: Categorías
B26: 1° | C26: =INDEX(Análisis!$A$18:$A$25,MATCH(LARGE(Análisis!$F$18:$F$25,1),Análisis!$F$18:$F$25,0)) -> Electrónicos | D26: =LARGE(Análisis!$F$18:$F$25,1) -> 1660576500
B27: 2° | C27: =INDEX(Análisis!$A$18:$A$25,MATCH(LARGE(Análisis!$F$18:$F$25,2),Análisis!$F$18:$F$25,0)) -> Electrodomésticos | D27: =LARGE(Análisis!$F$18:$F$25,2) -> 1324751100
B28: 3° | C28: =INDEX(Análisis!$A$18:$A$25,MATCH(LARGE(Análisis!$F$18:$F$25,3),Análisis!$F$18:$F$25,0)) -> Muebles | D28: =LARGE(Análisis!$F$18:$F$25,3) -> 757661000
B29: Último | C29: =INDEX(Análisis!$A$18:$A$25,MATCH(MIN(Análisis!$F$18:$F$25),Análisis!$F$18:$F$25,0)) -> Libros | D29: =MIN(Análisis!$F$18:$F$25) -> 37696100
B31: Ciudades
B32: 1° | C32: =INDEX(Análisis!$A$30:$A$48,MATCH(LARGE(Análisis!$F$30:$F$48,1),Análisis!$F$30:$F$48,0)) -> Bogotá | D32: =LARGE(Análisis!$F$30:$F$48,1) -> 1814858300
B33: 2° | C33: =INDEX(Análisis!$A$30:$A$48,MATCH(LARGE(Análisis!$F$30:$F$48,2),Análisis!$F$30:$F$48,0)) -> Medellín | D33: =LARGE(Análisis!$F$30:$F$48,2) -> 1096669200
B34: 3° | C34: =INDEX(Análisis!$A$30:$A$48,MATCH(LARGE(Análisis!$F$30:$F$48,3),Análisis!$F$30:$F$48,0)) -> Cali | D34: =LARGE(Análisis!$F$30:$F$48,3) -> 506526100
B35: Último | C35: =INDEX(Análisis!$A$30:$A$48,MATCH(MIN(Análisis!$F$30:$F$48),Análisis!$F$30:$F$48,0)) -> Valledupar | D35: =MIN(Análisis!$F$30:$F$48) -> 5886300
B37: Vendedores
B38: 1° | C38: =INDEX(Análisis!$A$53:$A$66,MATCH(LARGE(Análisis!$C$53:$C$66,1),Análisis!$C$53:$C$66,0)) -> Felipe Santos | D38: =LARGE(Análisis!$C$53:$C$66,1) -> 353796000
B39: 2° | C39: =INDEX(Análisis!$A$53:$A$66,MATCH(LARGE(Análisis!$C$53:$C$66,2),Análisis!$C$53:$C$66,0)) -> Izabela de León | D39: =LARGE(Análisis!$C$53:$C$66,2) -> 350342400
B40: 3° | C40: =INDEX(Análisis!$A$53:$A$66,MATCH(LARGE(Análisis!$C$53:$C$66,3),Análisis!$C$53:$C$66,0)) -> Maria Alfonso | D40: =LARGE(Análisis!$C$53:$C$66,3) -> 349694800
B41: Último | C41: =INDEX(Análisis!$A$53:$A$66,MATCH(MIN(Análisis!$C$53:$C$66),Análisis!$C$53:$C$66,0)) -> Mariana Herrera | D41: =MIN(Análisis!$C$53:$C$66) -> 283302600
B43: Tendencia anual
B44: Año | C44: Ingresos | D44: % del total | E44: Variación vs año anterior
B45: =Análisis!A71 -> 2020 | C45: =Análisis!F71 -> 1341955000 | D45: =Análisis!G71 -> 0.30473911 | E45: =""
B46: =Análisis!A72 -> 2021 | C46: =Análisis!F72 -> 1424114300 | D46: =Análisis!G72 -> 0.32339633 | E46: =IFERROR(C46/C45-1,"") -> 0.061223588
B47: =Análisis!A73 -> 2022 | C47: =Análisis!F73 -> 1327451900 | D47: =Análisis!G73 -> 0.30144566 | E47: =IFERROR(C47/C46-1,"") -> -0.067875451
B48: =Análisis!A74 -> 2023 | C48: =Análisis!F74 -> 310098000 | D48: =Análisis!G74 -> 0.070418895 | E48: =IFERROR(C48/C47-1,"") -> -0.76639606
B49: Total | C49: =SUM(C45:C48) -> 4403619200 | D49: =SUM(D45:D48) -> 1
B51: Conclusiones (se actualizan con los datos)
B52: ="1. La tienda con mayores ingresos es "&Análisis!B86&" con "&TEXT(Análisis!C86,"$#.##0")&", y la de menores ingresos es "&Análisis!B87&" con "&TEXT(Análisis!C87,"$#.##0")&" ("&TEXT(1-Análisis!C87/Análisis!C86,"0,0%")&" por debajo)." -> 1. La tienda con mayores ingresos es Tienda 1 con $1.150.880.400, y la de menores ingresos es Tienda 4 con $1.038.375.700 (9,8% por debajo).
B53: ="2. En calificación de clientes lidera "&Análisis!B88&" ("&TEXT(Análisis!C88,"0,00")&") y la más baja es "&Análisis!B89&" ("&TEXT(Análisis!C89,"0,00")&"), con una diferencia de "&TEXT(Análisis!C88-Análisis!C89,"0,00")&" puntos." -> 2. En calificación de clientes lidera Tienda 3 (4,05) y la más baja es Tienda 1 (3,98), con una diferencia de 0,07 puntos.
B54: ="3. Las categorías "&C26&" y "&C27&" concentran "&TEXT((D26+D27)/$C$6,"0,0%")&" de los ingresos totales; "&C29&" es la de menor aporte." -> 3. Las categorías Electrónicos y Electrodomésticos concentran 67,8% de los ingresos totales; Libros es la de menor aporte.
B55: ="4. "&C32&" concentra "&TEXT(D32/$C$6,"0,0%")&" de los ingresos; las tres primeras ciudades suman "&TEXT((D32+D33+D34)/$C$6,"0,0%")&"." -> 4. Bogotá concentra 41,2% de los ingresos; las tres primeras ciudades suman 77,6%.
B56: ="5. El vendedor con mayores ingresos es "&C38&" ("&TEXT(D38,"$#.##0")&"), frente a "&C41&" con "&TEXT(D41,"$#.##0")&" en el último lugar." -> 5. El vendedor con mayores ingresos es Felipe Santos ($353.796.000), frente a Mariana Herrera con $283.302.600 en el último lugar.
B57: ="6. El año con mayores ingresos fue "&TEXT(INDEX(B45:B48,MATCH(MAX(C45:C48),C45:C48,0)),"0")&"; el último año registrado varía "&TEXT(E48,"0,0%")&" frente al anterior (puede tratarse de un año incompleto)." -> 6. El año con mayores ingresos fue 2021; el último año registrado varía -76,6% frente al anterior (puede tratarse de un año incompleto).
B58: ="7. El costo de envío representa "&TEXT($C$13,"0,0%")&" de los ingresos, dejando un ingreso neto de "&TEXT($C$10,"$#.##0")&"." -> 7. El costo de envío representa 5,3% de los ingresos, dejando un ingreso neto de $4.168.922.200.

Sheet Dashboard
AB1: Datos de apoyo del Dashboard (vinculados a Análisis)
B2: DASHBOARD DE VENTAS — TIENDAS 1 A 4
B3: Todos los indicadores se recalculan automáticamente al editar las hojas Tienda_1 a Tienda_4 | AB3: Tienda | AC3: Ingresos | AD3: Calificación | AE3: Ticket promedio
AB4: =Análisis!B5 -> Tienda 1 | AC4: =Análisis!B7 -> 1150880400 | AD4: =Análisis!B12 -> 3.976685 | AE4: =Análisis!B8 -> 487867.91
B5: INGRESOS TOTALES | F5: N° DE VENTAS | J5: CALIFICACIÓN PROMEDIO | N5: COSTO DE ENVÍO | AB5: =Análisis!C5 -> Tienda 2 | AC5: =Análisis!C7 -> 1116343500 | AD5: =Análisis!C12 -> 4.0373039 | AE5: =Análisis!C8 -> 473227.43
B6: =Análisis!$F$7 -> 4403619200 | F6: =Análisis!$F$6 -> 9435 | J6: =Análisis!$F$12 -> 4.0145204 | N6: =Análisis!$F$9 -> 234697000 | AB6: =Análisis!D5 -> Tienda 3 | AC6: =Análisis!D7 -> 1098019600 | AD6: =Análisis!D12 -> 4.0483256 | AE6: =Análisis!D8 -> 465459.77
B7: ="Ingreso neto de envíos: "&TEXT(Análisis!$F$11,"$#.##0") -> Ingreso neto de envíos: $4.168.922.200 | F7: ="Ticket promedio: "&TEXT(Análisis!$F$8,"$#.##0") -> Ticket promedio: $466.732 | J7: ="Mejor: "&Análisis!$B$88&" ("&TEXT(Análisis!$C$88,"0,00")&")" -> Mejor: Tienda 3 (4,05) | N7: ="Equivale al "&TEXT(Análisis!$F$9/Análisis!$F$7,"0,0%")&" de los ingresos" -> Equivale al 5,3% de los ingresos | AB7: =Análisis!E5 -> Tienda 4 | AC7: =Análisis!E7 -> 1038375700 | AD7: =Análisis!E12 -> 3.9957591 | AE7: =Análisis!E8 -> 440362.89
B9: TIENDA LÍDER | F9: CATEGORÍA LÍDER | J9: CIUDAD LÍDER | N9: VENDEDOR LÍDER | AB9: Categoría | AC9: Ingresos
B10: =Análisis!$B$86 -> Tienda 1 | F10: =Análisis!$B$90 -> Electrónicos | J10: =Análisis!$B$92 -> Bogotá | N10: =Análisis!$B$93 -> Felipe Santos | AB10: =INDEX(Análisis!$A$18:$A$25,MATCH(LARGE(Análisis!$F$18:$F$25,1),Análisis!$F$18:$F$25,0)) -> Electrónicos | AC10: =LARGE(Análisis!$F$18:$F$25,1) -> 1660576500
B11: ="Ingresos: "&TEXT(Análisis!$C$86,"$#.##0") -> Ingresos: $1.150.880.400 | F11: ="Ingresos: "&TEXT(Análisis!$C$90,"$#.##0") -> Ingresos: $1.660.576.500 | J11: ="Ingresos: "&TEXT(Análisis!$C$92,"$#.##0") -> Ingresos: $1.814.858.300 | N11: ="Ingresos: "&TEXT(Análisis!$C$93,"$#.##0") -> Ingresos: $353.796.000 | AB11: =INDEX(Análisis!$A$18:$A$25,MATCH(LARGE(Análisis!$F$18:$F$25,2),Análisis!$F$18:$F$25,0)) -> Electrodomésticos | AC11: =LARGE(Análisis!$F$18:$F$25,2) -> 1324751100
AB12: =INDEX(Análisis!$A$18:$A$25,MATCH(LARGE(Análisis!$F$18:$F$25,3),Análisis!$F$18:$F$25,0)) -> Muebles | AC12: =LARGE(Análisis!$F$18:$F$25,3) -> 757661000
AB13: =INDEX(Análisis!$A$18:$A$25,MATCH(LARGE(Análisis!$F$18:$F$25,4),Análisis!$F$18:$F$25,0)) -> Instrumentos musicales | AC13: =LARGE(Análisis!$F$18:$F$25,4) -> 348772600
AB14: =INDEX(Análisis!$A$18:$A$25,MATCH(LARGE(Análisis!$F$18:$F$25,5),Análisis!$F$18:$F$25,0)) -> Deportes y diversión | AC14: =LARGE(Análisis!$F$18:$F$25,5) -> 142977700
AB15: =INDEX(Análisis!$A$18:$A$25,MATCH(LARGE(Análisis!$F$18:$F$25,6),Análisis!$F$18:$F$25,0)) -> Juguetes | AC15: =LARGE(Análisis!$F$18:$F$25,6) -> 73604400
AB16: =INDEX(Análisis!$A$18:$A$25,MATCH(LARGE(Análisis!$F$18:$F$25,7),Análisis!$F$18:$F$25,0)) -> Artículos para el hogar | AC16: =LARGE(Análisis!$F$18:$F$25,7) -> 57579800
AB17: =INDEX(Análisis!$A$18:$A$25,MATCH(LARGE(Análisis!$F$18:$F$25,8),Análisis!$F$18:$F$25,0)) -> Libros | AC17: =LARGE(Análisis!$F$18:$F$25,8) -> 37696100
AB19: Ciudad | AC19: Ingresos
AB20: =INDEX(Análisis!$A$30:$A$48,MATCH(LARGE(Análisis!$F$30:$F$48,1),Análisis!$F$30:$F$48,0)) -> Bogotá | AC20: =LARGE(Análisis!$F$30:$F$48,1) -> 1814858300
AB21: =INDEX(Análisis!$A$30:$A$48,MATCH(LARGE(Análisis!$F$30:$F$48,2),Análisis!$F$30:$F$48,0)) -> Medellín | AC21: =LARGE(Análisis!$F$30:$F$48,2) -> 1096669200
AB22: =INDEX(Análisis!$A$30:$A$48,MATCH(LARGE(Análisis!$F$30:$F$48,3),Análisis!$F$30:$F$48,0)) -> Cali | AC22: =LARGE(Análisis!$F$30:$F$48,3) -> 506526100
AB23: =INDEX(Análisis!$A$30:$A$48,MATCH(LARGE(Análisis!$F$30:$F$48,4),Análisis!$F$30:$F$48,0)) -> Pereira | AC23: =LARGE(Análisis!$F$30:$F$48,4) -> 225927300
AB24: =INDEX(Análisis!$A$30:$A$48,MATCH(LARGE(Análisis!$F$30:$F$48,5),Análisis!$F$30:$F$48,0)) -> Barranquilla | AC24: =LARGE(Análisis!$F$30:$F$48,5) -> 132040500
AB25: =INDEX(Análisis!$A$30:$A$48,MATCH(LARGE(Análisis!$F$30:$F$48,6),Análisis!$F$30:$F$48,0)) -> Cartagena | AC25: =LARGE(Análisis!$F$30:$F$48,6) -> 102376700
AB26: =INDEX(Análisis!$A$30:$A$48,MATCH(LARGE(Análisis!$F$30:$F$48,7),Análisis!$F$30:$F$48,0)) -> Cúcuta | AC26: =LARGE(Análisis!$F$30:$F$48,7) -> 99369100
AB27: =INDEX(Análisis!$A$30:$A$48,MATCH(LARGE(Análisis!$F$30:$F$48,8),Análisis!$F$30:$F$48,0)) -> Bucaramanga | AC27: =LARGE(Análisis!$F$30:$F$48,8) -> 90573300
AB28: =INDEX(Análisis!$A$30:$A$48,MATCH(LARGE(Análisis!$F$30:$F$48,9),Análisis!$F$30:$F$48,0)) -> Riohacha | AC28: =LARGE(Análisis!$F$30:$F$48,9) -> 73879700
AB29: =INDEX(Análisis!$A$30:$A$48,MATCH(LARGE(Análisis!$F$30:$F$48,10),Análisis!$F$30:$F$48,0)) -> Leticia | AC29: =LARGE(Análisis!$F$30:$F$48,10) -> 67149900
AB31: Año | AC31: Ingresos
AB32: =TEXT(Análisis!A71,"0") -> 2020 | AC32: =Análisis!F71 -> 1341955000
AB33: =TEXT(Análisis!A72,"0") -> 2021 | AC33: =Análisis!F72 -> 1424114300
AB34: =TEXT(Análisis!A73,"0") -> 2022 | AC34: =Análisis!F73 -> 1327451900
AB35: =TEXT(Análisis!A74,"0") -> 2023 | AC35: =Análisis!F74 -> 310098000
AB37: Método de pago | AC37: Ingresos
AB38: =Análisis!A79 -> Cupón | AC38: =Análisis!F79 -> 235869600
AB39: =Análisis!A80 -> Nequi | AC39: =Análisis!F80 -> 880684200
AB40: =Análisis!A81 -> Tarjeta de crédito | AC40: =Análisis!F81 -> 3230607100
AB41: =Análisis!A82 -> Tarjeta de débito | AC41: =Análisis!F82 -> 56458300
AB43: Vendedor | AC43: Ingresos
AB44: =INDEX(Análisis!$A$53:$A$66,MATCH(LARGE(Análisis!$C$53:$C$66,1),Análisis!$C$53:$C$66,0)) -> Felipe Santos | AC44: =LARGE(Análisis!$C$53:$C$66,1) -> 353796000
AB45: =INDEX(Análisis!$A$53:$A$66,MATCH(LARGE(Análisis!$C$53:$C$66,2),Análisis!$C$53:$C$66,0)) -> Izabela de León | AC45: =LARGE(Análisis!$C$53:$C$66,2) -> 350342400
AB46: =INDEX(Análisis!$A$53:$A$66,MATCH(LARGE(Análisis!$C$53:$C$66,3),Análisis!$C$53:$C$66,0)) -> Maria Alfonso | AC46: =LARGE(Análisis!$C$53:$C$66,3) -> 349694800
AB47: =INDEX(Análisis!$A$53:$A$66,MATCH(LARGE(Análisis!$C$53:$C$66,4),Análisis!$C$53:$C$66,0)) -> Juliana Costa | AC47: =LARGE(Análisis!$C$53:$C$66,4) -> 338364700
AB48: =INDEX(Análisis!$A$53:$A$66,MATCH(LARGE(Análisis!$C$53:$C$66,5),Análisis!$C$53:$C$66,0)) -> Pedro Gomez | AC48: =LARGE(Análisis!$C$53:$C$66,5) -> 313350900
AB49: =INDEX(Análisis!$A$53:$A$66,MATCH(LARGE(Análisis!$C$53:$C$66,6),Análisis!$C$53:$C$66,0)) -> Rafael Acosta | AC49: =LARGE(Análisis!$C$53:$C$66,6) -> 310292300
AB50: =INDEX(Análisis!$A$53:$A$66,MATCH(LARGE(Análisis!$C$53:$C$66,7),Análisis!$C$53:$C$66,0)) -> Juan Fernandez | AC50: =LARGE(Análisis!$C$53:$C$66,7) -> 308562100
AB51: =INDEX(Análisis!$A$53:$A$66,MATCH(LARGE(Análisis!$C$53:$C$66,8),Análisis!$C$53:$C$66,0)) -> Lucas Olivera | AC51: =LARGE(Análisis!$C$53:$C$66,8) -> 305403600

Sheet Datos_Consolidados
A1: Tienda | B1: Categoría | C1: Ciudad | D1: Vendedor | E1: Método de pago | F1: Año | G1: Precio | H1: Costo envío | I1: Calificación | J1: Incluir | N1: Listas y datos de apoyo (vinculados)
A2: =IF(Tienda_1!$A2="","","Tienda 1") -> Tienda 1 | B2: =IF($A2="","",Tienda_1!B2) -> Electrónicos | C2: =IF($A2="","",Tienda_1!G2) -> Bogotá | D2: =IF($A2="","",Tienda_1!F2) -> Pedro Gomez | E2: =IF($A2="","",Tienda_1!I2) -> Tarjeta de crédito | F2: =IF($A2="","",VALUE(RIGHT(Tienda_1!E2,4))) -> 2021 | G2: =IF($A2="","",Tienda_1!C2) -> 164300 | H2: =IF($A2="","",Tienda_1!D2) -> 6900 | I2: =IF($A2="","",Tienda_1!H2) -> 4 | J2: =IF($A2="",0,IF(AND(OR('Cuadro-de-mando'!$B$4="(Todas)",'Cuadro-de-mando'!$B$4=$A2),OR('Cuadro-de-mando'!$E$4="(Todas)",'Cuadro-de-mando'!$E$4=$B2),OR('Cuadro-de-mando'!$H$4="(Todas)",'Cuadro-de-mando'!$H$4=$C2),OR('Cuadro-de-mando'!$K$4="(Todas)",'Cuadro-de-mando'!$K$4=$E2),OR('Cuadro-de-mando'!$N$4="(Todos)",'Cuadro-de-mando'!$N$4=$F2)),1,0)) -> 1 | N2: Tiendas | O2: Categorías | P2: Ciudades | Q2: Métodos de pago | R2: Años | T2: Tienda | U2: Ingresos (filtrado) | W2: Categoría | X2: Ingresos | Y2: Desempate | Z2: Top categorías | AA2: Ingresos
A3: =IF(Tienda_1!$A3="","","Tienda 1") -> Tienda 1 | B3: =IF($A3="","",Tienda_1!B3) -> Muebles | C3: =IF($A3="","",Tienda_1!G3) -> Medellín | D3: =IF($A3="","",Tienda_1!F3) -> Beatriz Morales | E3: =IF($A3="","",Tienda_1!I3) -> Tarjeta de crédito | F3: =IF($A3="","",VALUE(RIGHT(Tienda_1!E3,4))) -> 2022 | G3: =IF($A3="","",Tienda_1!C3) -> 192300 | H3: =IF($A3="","",Tienda_1!D3) -> 8400 | I3: =IF($A3="","",Tienda_1!H3) -> 1 | J3: =IF($A3="",0,IF(AND(OR('Cuadro-de-mando'!$B$4="(Todas)",'Cuadro-de-mando'!$B$4=$A3),OR('Cuadro-de-mando'!$E$4="(Todas)",'Cuadro-de-mando'!$E$4=$B3),OR('Cuadro-de-mando'!$H$4="(Todas)",'Cuadro-de-mando'!$H$4=$C3),OR('Cuadro-de-mando'!$K$4="(Todas)",'Cuadro-de-mando'!$K$4=$E3),OR('Cuadro-de-mando'!$N$4="(Todos)",'Cuadro-de-mando'!$N$4=$F3)),1,0)) -> 1 | N3: (Todas) | O3: (Todas) | P3: (Todas) | Q3: (Todas) | R3: (Todos) | T3: =N4 -> Tienda 1 | U3: =SUMIFS(Datos_Consolidados!$G$2:$G$9601,Datos_Consolidados!$J$2:$J$9601,1,Datos_Consolidados!$A$2:$A$9601,$T3) -> 1150880400 | W3: =O4 -> Artículos para el hogar | X3: =SUMIFS(Datos_Consolidados!$G$2:$G$9601,Datos_Consolidados!$J$2:$J$9601,1,Datos_Consolidados!$B$2:$B$9601,$W3) -> 57579800 | Y3: =X3-ROW()*0.000001 -> 57579800 | Z3: =IFERROR(INDEX($W$3:$W$10,MATCH(LARGE($Y$3:$Y$10,1),$Y$3:$Y$10,0)),"") -> Electrónicos | AA3: =IFERROR(INDEX($X$3:$X$10,MATCH(LARGE($Y$3:$Y$10,1),$Y$3:$Y$10,0)),0) -> 1660576500
A4: =IF(Tienda_1!$A4="","","Tienda 1") -> Tienda 1 | B4: =IF($A4="","",Tienda_1!B4) -> Juguetes | C4: =IF($A4="","",Tienda_1!G4) -> Cartagena | D4: =IF($A4="","",Tienda_1!F4) -> Juan Fernandez | E4: =IF($A4="","",Tienda_1!I4) -> Tarjeta de crédito | F4: =IF($A4="","",VALUE(RIGHT(Tienda_1!E4,4))) -> 2021 | G4: =IF($A4="","",Tienda_1!C4) -> 209600 | H4: =IF($A4="","",Tienda_1!D4) -> 15900 | I4: =IF($A4="","",Tienda_1!H4) -> 1 | J4: =IF($A4="",0,IF(AND(OR('Cuadro-de-mando'!$B$4="(Todas)",'Cuadro-de-mando'!$B$4=$A4),OR('Cuadro-de-mando'!$E$4="(Todas)",'Cuadro-de-mando'!$E$4=$B4),OR('Cuadro-de-mando'!$H$4="(Todas)",'Cuadro-de-mando'!$H$4=$C4),OR('Cuadro-de-mando'!$K$4="(Todas)",'Cuadro-de-mando'!$K$4=$E4),OR('Cuadro-de-mando'!$N$4="(Todos)",'Cuadro-de-mando'!$N$4=$F4)),1,0)) -> 1 | N4: =Análisis!B5 -> Tienda 1 | O4: =Análisis!A18 -> Artículos para el hogar | P4: =Análisis!A30 -> Armenia | Q4: =Análisis!A79 -> Cupón | R4: =Análisis!A71 -> 2020 | T4: =N5 -> Tienda 2 | U4: =SUMIFS(Datos_Consolidados!$G$2:$G$9601,Datos_Consolidados!$J$2:$J$9601,1,Datos_Consolidados!$A$2:$A$9601,$T4) -> 1116343500 | W4: =O5 -> Deportes y diversión | X4: =SUMIFS(Datos_Consolidados!$G$2:$G$9601,Datos_Consolidados!$J$2:$J$9601,1,Datos_Consolidados!$B$2:$B$9601,$W4) -> 142977700 | Y4: =X4-ROW()*0.000001 -> 1.429777e+08 | Z4: =IFERROR(INDEX($W$3:$W$10,MATCH(LARGE($Y$3:$Y$10,2),$Y$3:$Y$10,0)),"") -> Electrodomésticos | AA4: =IFERROR(INDEX($X$3:$X$10,MATCH(LARGE($Y$3:$Y$10,2),$Y$3:$Y$10,0)),0) -> 1324751100
A5: =IF(Tienda_1!$A5="","","Tienda 1") -> Tienda 1 | B5: =IF($A5="","",Tienda_1!B5) -> Electrodomésticos | C5: =IF($A5="","",Tienda_1!G5) -> Cali | D5: =IF($A5="","",Tienda_1!F5) -> Juan Fernandez | E5: =IF($A5="","",Tienda_1!I5) -> Nequi | F5: =IF($A5="","",VALUE(RIGHT(Tienda_1!E5,4))) -> 2022 | G5: =IF($A5="","",Tienda_1!C5) -> 757500 | H5: =IF($A5="","",Tienda_1!D5) -> 41000 | I5: =IF($A5="","",Tienda_1!H5) -> 4 | J5: =IF($A5="",0,IF(AND(OR('Cuadro-de-mando'!$B$4="(Todas)",'Cuadro-de-mando'!$B$4=$A5),OR('Cuadro-de-mando'!$E$4="(Todas)",'Cuadro-de-mando'!$E$4=$B5),OR('Cuadro-de-mando'!$H$4="(Todas)",'Cuadro-de-mando'!$H$4=$C5),OR('Cuadro-de-mando'!$K$4="(Todas)",'Cuadro-de-mando'!$K$4=$E5),OR('Cuadro-de-mando'!$N$4="(Todos)",'Cuadro-de-mando'!$N$4=$F5)),1,0)) -> 1 | N5: =Análisis!C5 -> Tienda 2 | O5: =Análisis!A19 -> Deportes y diversión | P5: =Análisis!A31 -> Barranquilla | Q5: =Análisis!A80 -> Nequi | R5: =Análisis!A72 -> 2021 | T5: =N6 -> Tienda 3 | U5: =SUMIFS(Datos_Consolidados!$G$2:$G$9601,Datos_Consolidados!$J$2:$J$9601,1,Datos_Consolidados!$A$2:$A$9601,$T5) -> 1098019600 | W5: =O6 -> Electrodomésticos | X5: =SUMIFS(Datos_Consolidados!$G$2:$G$9601,Datos_Consolidados!$J$2:$J$9601,1,Datos_Consolidados!$B$2:$B$9601,$W5) -> 1324751100 | Y5: =X5-ROW()*0.000001 -> 1.3247511e+09 | Z5: =IFERROR(INDEX($W$3:$W$10,MATCH(LARGE($Y$3:$Y$10,3),$Y$3:$Y$10,0)),"") -> Muebles | AA5: =IFERROR(INDEX($X$3:$X$10,MATCH(LARGE($Y$3:$Y$10,3),$Y$3:$Y$10,0)),0) -> 757661000
A6: =IF(Tienda_1!$A6="","","Tienda 1") -> Tienda 1 | B6: =IF($A6="","",Tienda_1!B6) -> Muebles | C6: =IF($A6="","",Tienda_1!G6) -> Medellín | D6: =IF($A6="","",Tienda_1!F6) -> Maria Alfonso | E6: =IF($A6="","",Tienda_1!I6) -> Nequi | F6: =IF($A6="","",VALUE(RIGHT(Tienda_1!E6,4))) -> 2020 | G6: =IF($A6="","",Tienda_1!C6) -> 335200 | H6: =IF($A6="","",Tienda_1!D6) -> 20200 | I6: =IF($A6="","",Tienda_1!H6) -> 5 | J6: =IF($A6="",0,IF(AND(OR('Cuadro-de-mando'!$B$4="(Todas)",'Cuadro-de-mando'!$B$4=$A6),OR('Cuadro-de-mando'!$E$4="(Todas)",'Cuadro-de-mando'!$E$4=$B6),OR('Cuadro-de-mando'!$H$4="(Todas)",'Cuadro-de-mando'!$H$4=$C6),OR('Cuadro-de-mando'!$K$4="(Todas)",'Cuadro-de-mando'!$K$4=$E6),OR('Cuadro-de-mando'!$N$4="(Todos)",'Cuadro-de-mando'!$N$4=$F6)),1,0)) -> 1 | N6: =Análisis!D5 -> Tienda 3 | O6: =Análisis!A20 -> Electrodomésticos | P6: =Análisis!A32 -> Bogotá | Q6: =Análisis!A81 -> Tarjeta de crédito | R6: =Análisis!A73 -> 2022 | T6: =N7 -> Tienda 4 | U6: =SUMIFS(Datos_Consolidados!$G$2:$G$9601,Datos_Consolidados!$J$2:$J$9601,1,Datos_Consolidados!$A$2:$A$9601,$T6) -> 1038375700 | W6: =O7 -> Electrónicos | X6: =SUMIFS(Datos_Consolidados!$G$2:$G$9601,Datos_Consolidados!$J$2:$J$9601,1,Datos_Consolidados!$B$2:$B$9601,$W6) -> 1660576500 | Y6: =X6-ROW()*0.000001 -> 1.6605765e+09 | Z6: =IFERROR(INDEX($W$3:$W$10,MATCH(LARGE($Y$3:$Y$10,4),$Y$3:$Y$10,0)),"") -> Instrumentos musicales | AA6: =IFERROR(INDEX($X$3:$X$10,MATCH(LARGE($Y$3:$Y$10,4),$Y$3:$Y$10,0)),0) -> 348772600
A7: =IF(Tienda_1!$A7="","","Tienda 1") -> Tienda 1 | B7: =IF($A7="","",Tienda_1!B7) -> Juguetes | C7: =IF($A7="","",Tienda_1!G7) -> Cali | D7: =IF($A7="","",Tienda_1!F7) -> Beatriz Morales | E7: =IF($A7="","",Tienda_1!I7) -> Cupón | F7: =IF($A7="","",VALUE(RIGHT(Tienda_1!E7,4))) -> 2020 | G7: =IF($A7="","",Tienda_1!C7) -> 24200 | H7: =IF($A7="","",Tienda_1!D7) -> 0 | I7: =IF($A7="","",Tienda_1!H7) -> 5 | J7: =IF($A7="",0,IF(AND(OR('Cuadro-de-mando'!$B$4="(Todas)",'Cuadro-de-mando'!$B$4=$A7),OR('Cuadro-de-mando'!$E$4="(Todas)",'Cuadro-de-mando'!$E$4=$B7),OR('Cuadro-de-mando'!$H$4="(Todas)",'Cuadro-de-mando'!$H$4=$C7),OR('Cuadro-de-mando'!$K$4="(Todas)",'Cuadro-de-mando'!$K$4=$E7),OR('Cuadro-de-mando'!$N$4="(Todos)",'Cuadro-de-mando'!$N$4=$F7)),1,0)) -> 1 | N7: =Análisis!E5 -> Tienda 4 | O7: =Análisis!A21 -> Electrónicos | P7: =Análisis!A33 -> Bucaramanga | Q7: =Análisis!A82 -> Tarjeta de débito | R7: =Análisis!A74 -> 2023 | W7: =O8 -> Instrumentos musicales | X7: =SUMIFS(Datos_Consolidados!$G$2:$G$9601,Datos_Consolidados!$J$2:$J$9601,1,Datos_Consolidados!$B$2:$B$9601,$W7) -> 348772600 | Y7: =X7-ROW()*0.000001 -> 3.487726e+08 | Z7: =IFERROR(INDEX($W$3:$W$10,MATCH(LARGE($Y$3:$Y$10,5),$Y$3:$Y$10,0)),"") -> Deportes y diversión | AA7: =IFERROR(INDEX($X$3:$X$10,MATCH(LARGE($Y$3:$Y$10,5),$Y$3:$Y$10,0)),0) -> 142977700
A8: =IF(Tienda_1!$A8="","","Tienda 1") -> Tienda 1 | B8: =IF($A8="","",Tienda_1!B8) -> Juguetes | C8: =IF($A8="","",Tienda_1!G8) -> Bogotá | D8: =IF($A8="","",Tienda_1!F8) -> Juan Fernandez | E8: =IF($A8="","",Tienda_1!I8) -> Nequi | F8: =IF($A8="","",VALUE(RIGHT(Tienda_1!E8,4))) -> 2021 | G8: =IF($A8="","",Tienda_1!C8) -> 44200 | H8: =IF($A8="","",Tienda_1!D8) -> 0 | I8: =IF($A8="","",Tienda_1!H8) -> 3 | J8: =IF($A8="",0,IF(AND(OR('Cuadro-de-mando'!$B$4="(Todas)",'Cuadro-de-mando'!$B$4=$A8),OR('Cuadro-de-mando'!$E$4="(Todas)",'Cuadro-de-mando'!$E$4=$B8),OR('Cuadro-de-mando'!$H$4="(Todas)",'Cuadro-de-mando'!$H$4=$C8),OR('Cuadro-de-mando'!$K$4="(Todas)",'Cuadro-de-mando'!$K$4=$E8),OR('Cuadro-de-mando'!$N$4="(Todos)",'Cuadro-de-mando'!$N$4=$F8)),1,0)) -> 1 | O8: =Análisis!A22 -> Instrumentos musicales | P8: =Análisis!A34 -> Cali | W8: =O9 -> Juguetes | X8: =SUMIFS(Datos_Consolidados!$G$2:$G$9601,Datos_Consolidados!$J$2:$J$9601,1,Datos_Consolidados!$B$2:$B$9601,$W8) -> 73604400 | Y8: =X8-ROW()*0.000001 -> 73604400 | Z8: =IFERROR(INDEX($W$3:$W$10,MATCH(LARGE($Y$3:$Y$10,6),$Y$3:$Y$10,0)),"") -> Juguetes | AA8: =IFERROR(INDEX($X$3:$X$10,MATCH(LARGE($Y$3:$Y$10,6),$Y$3:$Y$10,0)),0) -> 73604400
A9: =IF(Tienda_1!$A9="","","Tienda 1") -> Tienda 1 | B9: =IF($A9="","",Tienda_1!B9) -> Electrodomésticos | C9: =IF($A9="","",Tienda_1!G9) -> Santa Marta | D9: =IF($A9="","",Tienda_1!F9) -> Felipe Santos | E9: =IF($A9="","",Tienda_1!I9) -> Tarjeta de crédito | F9: =IF($A9="","",VALUE(RIGHT(Tienda_1!E9,4))) -> 2021 | G9: =IF($A9="","",Tienda_1!C9) -> 1189700 | H9: =IF($A9="","",Tienda_1!D9) -> 63700 | I9: =IF($A9="","",Tienda_1!H9) -> 5 | J9: =IF($A9="",0,IF(AND(OR('Cuadro-de-mando'!$B$4="(Todas)",'Cuadro-de-mando'!$B$4=$A9),OR('Cuadro-de-mando'!$E$4="(Todas)",'Cuadro-de-mando'!$E$4=$B9),OR('Cuadro-de-mando'!$H$4="(Todas)",'Cuadro-de-mando'!$H$4=$C9),OR('Cuadro-de-mando'!$K$4="(Todas)",'Cuadro-de-mando'!$K$4=$E9),OR('Cuadro-de-mando'!$N$4="(Todos)",'Cuadro-de-mando'!$N$4=$F9)),1,0)) -> 1 | O9: =Análisis!A23 -> Juguetes | P9: =Análisis!A35 -> Cartagena | T9: Año | U9: Ingresos | W9: =O10 -> Libros | X9: =SUMIFS(Datos_Consolidados!$G$2:$G$9601,Datos_Consolidados!$J$2:$J$9601,1,Datos_Consolidados!$B$2:$B$9601,$W9) -> 37696100 | Y9: =X9-ROW()*0.000001 -> 37696100 | Z9: =IFERROR(INDEX($W$3:$W$10,MATCH(LARGE($Y$3:$Y$10,7),$Y$3:$Y$10,0)),"") -> Artículos para el hogar | AA9: =IFERROR(INDEX($X$3:$X$10,MATCH(LARGE($Y$3:$Y$10,7),$Y$3:$Y$10,0)),0) -> 57579800
A10: =IF(Tienda_1!$A10="","","Tienda 1") -> Tienda 1 | B10: =IF($A10="","",Tienda_1!B10) -> Electrodomésticos | C10: =IF($A10="","",Tienda_1!G10) -> Bogotá | D10: =IF($A10="","",Tienda_1!F10) -> Izabela de León | E10: =IF($A10="","",Tienda_1!I10) -> Tarjeta de crédito | F10: =IF($A10="","",VALUE(RIGHT(Tienda_1!E10,4))) -> 2022 | G10: =IF($A10="","",Tienda_1!C10) -> 1518200 | H10: =IF($A10="","",Tienda_1!D10) -> 79000 | I10: =IF($A10="","",Tienda_1!H10) -> 1 | J10: =IF($A10="",0,IF(AND(OR('Cuadro-de-mando'!$B$4="(Todas)",'Cuadro-de-mando'!$B$4=$A10),OR('Cuadro-de-mando'!$E$4="(Todas)",'Cuadro-de-mando'!$E$4=$B10),OR('Cuadro-de-mando'!$H$4="(Todas)",'Cuadro-de-mando'!$H$4=$C10),OR('Cuadro-de-mando'!$K$4="(Todas)",'Cuadro-de-mando'!$K$4=$E10),OR('Cuadro-de-mando'!$N$4="(Todos)",'Cuadro-de-mando'!$N$4=$F10)),1,0)) -> 1 | O10: =Análisis!A24 -> Libros | P10: =Análisis!A36 -> Cúcuta | T10: =TEXT(R4,"0") -> 2020 | U10: =SUMIFS(Datos_Consolidados!$G$2:$G$9601,Datos_Consolidados!$J$2:$J$9601,1,Datos_Consolidados!$F$2:$F$9601,R4) -> 1341955000 | W10: =O11 -> Muebles | X10: =SUMIFS(Datos_Consolidados!$G$2:$G$9601,Datos_Consolidados!$J$2:$J$9601,1,Datos_Consolidados!$B$2:$B$9601,$W10) -> 757661000 | Y10: =X10-ROW()*0.000001 -> 7.57661e+08 | Z10: =IFERROR(INDEX($W$3:$W$10,MATCH(LARGE($Y$3:$Y$10,8),$Y$3:$Y$10,0)),"") -> Libros | AA10: =IFERROR(INDEX($X$3:$X$10,MATCH(LARGE($Y$3:$Y$10,8),$Y$3:$Y$10,0)),0) -> 37696100
A11: =IF(Tienda_1!$A11="","","Tienda 1") -> Tienda 1 | B11: =IF($A11="","",Tienda_1!B11) -> Juguetes | C11: =IF($A11="","",Tienda_1!G11) -> Bogotá | D11: =IF($A11="","",Tienda_1!F11) -> Beatriz Morales | E11: =IF($A11="","",Tienda_1!I11) -> Nequi | F11: =IF($A11="","",VALUE(RIGHT(Tienda_1!E11,4))) -> 2020 | G11: =IF($A11="","",Tienda_1!C11) -> 75200 | H11: =IF($A11="","",Tienda_1!D11) -> 5100 | I11: =IF($A11="","",Tienda_1!H11) -> 5 | J11: =IF($A11="",0,IF(AND(OR('Cuadro-de-mando'!$B$4="(Todas)",'Cuadro-de-mando'!$B$4=$A11),OR('Cuadro-de-mando'!$E$4="(Todas)",'Cuadro-de-mando'!$E$4=$B11),OR('Cuadro-de-mando'!$H$4="(Todas)",'Cuadro-de-mando'!$H$4=$C11),OR('Cuadro-de-mando'!$K$4="(Todas)",'Cuadro-de-mando'!$K$4=$E11),OR('Cuadro-de-mando'!$N$4="(Todos)",'Cuadro-de-mando'!$N$4=$F11)),1,0)) -> 1 | O11: =Análisis!A25 -> Muebles | P11: =Análisis!A37 -> Inírida | T11: =TEXT(R5,"0") -> 2021 | U11: =SUMIFS(Datos_Consolidados!$G$2:$G$9601,Datos_Consolidados!$J$2:$J$9601,1,Datos_Consolidados!$F$2:$F$9601,R5) -> 1424114300
A12: =IF(Tienda_1!$A12="","","Tienda 1") -> Tienda 1 | B12: =IF($A12="","",Tienda_1!B12) -> Electrodomésticos | C12: =IF($A12="","",Tienda_1!G12) -> Bogotá | D12: =IF($A12="","",Tienda_1!F12) -> Blanca Ramirez | E12: =IF($A12="","",Tienda_1!I12) -> Tarjeta de crédito | F12: =IF($A12="","",VALUE(RIGHT(Tienda_1!E12,4))) -> 2020 | G12: =IF($A12="","",Tienda_1!C12) -> 2431300 | H12: =IF($A12="","",Tienda_1!D12) -> 127600 | I12: =IF($A12="","",Tienda_1!H12) -> 5 | J12: =IF($A12="",0,IF(AND(OR('Cuadro-de-mando'!$B$4="(Todas)",'Cuadro-de-mando'!$B$4=$A12),OR('Cuadro-de-mando'!$E$4="(Todas)",'Cuadro-de-mando'!$E$4=$B12),OR('Cuadro-de-mando'!$H$4="(Todas)",'Cuadro-de-mando'!$H$4=$C12),OR('Cuadro-de-mando'!$K$4="(Todas)",'Cuadro-de-mando'!$K$4=$E12),OR('Cuadro-de-mando'!$N$4="(Todos)",'Cuadro-de-mando'!$N$4=$F12)),1,0)) -> 1 | P12: =Análisis!A38 -> Leticia | T12: =TEXT(R6,"0") -> 2022 | U12: =SUMIFS(Datos_Consolidados!$G$2:$G$9601,Datos_Consolidados!$J$2:$J$9601,1,Datos_Consolidados!$F$2:$F$9601,R6) -> 1327451900 | W12: Ciudad | X12: Ingresos | Y12: Desempate | Z12: Top 10 ciudades | AA12: Ingresos
A13: =IF(Tienda_1!$A13="","","Tienda 1") -> Tienda 1 | B13: =IF($A13="","",Tienda_1!B13) -> Electrodomésticos | C13: =IF($A13="","",Tienda_1!G13) -> Cartagena | D13: =IF($A13="","",Tienda_1!F13) -> Rafael Acosta | E13: =IF($A13="","",Tienda_1!I13) -> Tarjeta de crédito | F13: =IF($A13="","",VALUE(RIGHT(Tienda_1!E13,4))) -> 2021 | G13: =IF($A13="","",Tienda_1!C13) -> 1417100 | H13: =IF($A13="","",Tienda_1!D13) -> 75700 | I13: =IF($A13="","",Tienda_1!H13) -> 5 | J13: =IF($A13="",0,IF(AND(OR('Cuadro-de-mando'!$B$4="(Todas)",'Cuadro-de-mando'!$B$4=$A13),OR('Cuadro-de-mando'!$E$4="(Todas)",'Cuadro-de-mando'!$E$4=$B13),OR('Cuadro-de-mando'!$H$4="(Todas)",'Cuadro-de-mando'!$H$4=$C13),OR('Cuadro-de-mando'!$K$4="(Todas)",'Cuadro-de-mando'!$K$4=$E13),OR('Cuadro-de-mando'!$N$4="(Todos)",'Cuadro-de-mando'!$N$4=$F13)),1,0)) -> 1 | P13: =Análisis!A39 -> Manizales | T13: =TEXT(R7,"0") -> 2023 | U13: =SUMIFS(Datos_Consolidados!$G$2:$G$9601,Datos_Consolidados!$J$2:$J$9601,1,Datos_Consolidados!$F$2:$F$9601,R7) -> 310098000 | W13: =P4 -> Armenia | X13: =SUMIFS(Datos_Consolidados!$G$2:$G$9601,Datos_Consolidados!$J$2:$J$9601,1,Datos_Consolidados!$C$2:$C$9601,$W13) -> 12242900 | Y13: =X13-ROW()*0.000001 -> 12242900 | Z13: =IFERROR(INDEX($W$13:$W$31,MATCH(LARGE($Y$13:$Y$31,1),$Y$13:$Y$31,0)),"") -> Bogotá | AA13: =IFERROR(INDEX($X$13:$X$31,MATCH(LARGE($Y$13:$Y$31,1),$Y$13:$Y$31,0)),0) -> 1814858300
A14: =IF(Tienda_1!$A14="","","Tienda 1") -> Tienda 1 | B14: =IF($A14="","",Tienda_1!B14) -> Electrónicos | C14: =IF($A14="","",Tienda_1!G14) -> Medellín | D14: =IF($A14="","",Tienda_1!F14) -> Rafael Acosta | E14: =IF($A14="","",Tienda_1!I14) -> Tarjeta de crédito | F14: =IF($A14="","",VALUE(RIGHT(Tienda_1!E14,4))) -> 2020 | G14: =IF($A14="","",Tienda_1!C14) -> 91800 | H14: =IF($A14="","",Tienda_1!D14) -> 5300 | I14: =IF($A14="","",Tienda_1!H14) -> 1 | J14: =IF($A14="",0,IF(AND(OR('Cuadro-de-mando'!$B$4="(Todas)",'Cuadro-de-mando'!$B$4=$A14),OR('Cuadro-de-mando'!$E$4="(Todas)",'Cuadro-de-mando'!$E$4=$B14),OR('Cuadro-de-mando'!$H$4="(Todas)",'Cuadro-de-mando'!$H$4=$C14),OR('Cuadro-de-mando'!$K$4="(Todas)",'Cuadro-de-mando'!$K$4=$E14),OR('Cuadro-de-mando'!$N$4="(Todos)",'Cuadro-de-mando'!$N$4=$F14)),1,0)) -> 1 | P14: =Análisis!A40 -> Medellín | W14: =P5 -> Barranquilla | X14: =SUMIFS(Datos_Consolidados!$G$2:$G$9601,Datos_Consolidados!$J$2:$J$9601,1,Datos_Consolidados!$C$2:$C$9601,$W14) -> 132040500 | Y14: =X14-ROW()*0.000001 -> 1.320405e+08 | Z14: =IFERROR(INDEX($W$13:$W$31,MATCH(LARGE($Y$13:$Y$31,2),$Y$13:$Y$31,0)),"") -> Medellín | AA14: =IFERROR(INDEX($X$13:$X$31,MATCH(LARGE($Y$13:$Y$31,2),$Y$13:$Y$31,0)),0) -> 1096669200
A15: =IF(Tienda_1!$A15="","","Tienda 1") -> Tienda 1 | B15: =IF($A15="","",Tienda_1!B15) -> Artículos para el hogar | C15: =IF($A15="","",Tienda_1!G15) -> Pereira | D15: =IF($A15="","",Tienda_1!F15) -> Izabela de León | E15: =IF($A15="","",Tienda_1!I15) -> Tarjeta de crédito | F15: =IF($A15="","",VALUE(RIGHT(Tienda_1!E15,4))) -> 2020 | G15: =IF($A15="","",Tienda_1!C15) -> 66700 | H15: =IF($A15="","",Tienda_1!D15) -> 1700 | I15: =IF($A15="","",Tienda_1!H15) -> 4 | J15: =IF($A15="",0,IF(AND(OR('Cuadro-de-mando'!$B$4="(Todas)",'Cuadro-de-mando'!$B$4=$A15),OR('Cuadro-de-mando'!$E$4="(Todas)",'Cuadro-de-mando'!$E$4=$B15),OR('Cuadro-de-mando'!$H$4="(Todas)",'Cuadro-de-mando'!$H$4=$C15),OR('Cuadro-de-mando'!$K$4="(Todas)",'Cuadro-de-mando'!$K$4=$E15),OR('Cuadro-de-mando'!$N$4="(Todos)",'Cuadro-de-mando'!$N$4=$F15)),1,0)) -> 1 | P15: =Análisis!A41 -> Neiva | W15: =P6 -> Bogotá | X15: =SUMIFS(Datos_Consolidados!$G$2:$G$9601,Datos_Consolidados!$J$2:$J$9601,1,Datos_Consolidados!$C$2:$C$9601,$W15) -> 1814858300 | Y15: =X15-ROW()*0.000001 -> 1.8148583e+09 | Z15: =IFERROR(INDEX($W$13:$W$31,MATCH(LARGE($Y$13:$Y$31,3),$Y$13:$Y$31,0)),"") -> Cali | AA15: =IFERROR(INDEX($X$13:$X$31,MATCH(LARGE($Y$13:$Y$31,3),$Y$13:$Y$31,0)),0) -> 506526100
A16: =IF(Tienda_1!$A16="","","Tienda 1") -> Tienda 1 | B16: =IF($A16="","",Tienda_1!B16) -> Deportes y diversión | C16: =IF($A16="","",Tienda_1!G16) -> Bogotá | D16: =IF($A16="","",Tienda_1!F16) -> Juan Fernandez | E16: =IF($A16="","",Tienda_1!I16) -> Tarjeta de crédito | F16: =IF($A16="","",VALUE(RIGHT(Tienda_1!E16,4))) -> 2020 | G16: =IF($A16="","",Tienda_1!C16) -> 613300 | H16: =IF($A16="","",Tienda_1!D16) -> 30800 | I16: =IF($A16="","",Tienda_1!H16) -> 2 | J16: =IF($A16="",0,IF(AND(OR('Cuadro-de-mando'!$B$4="(Todas)",'Cuadro-de-mando'!$B$4=$A16),OR('Cuadro-de-mando'!$E$4="(Todas)",'Cuadro-de-mando'!$E$4=$B16),OR('Cuadro-de-mando'!$H$4="(Todas)",'Cuadro-de-mando'!$H$4=$C16),OR('Cuadro-de-mando'!$K$4="(Todas)",'Cuadro-de-mando'!$K$4=$E16),OR('Cuadro-de-mando'!$N$4="(Todos)",'Cuadro-de-mando'!$N$4=$F16)),1,0)) -> 1 | P16: =Análisis!A42 -> Pasto | T16: Método de pago | U16: Ingresos | W16: =P7 -> Bucaramanga | X16: =SUMIFS(Datos_Consolidados!$G$2:$G$9601,Datos_Consolidados!$J$2:$J$9601,1,Datos_Consolidados!$C$2:$C$9601,$W16) -> 90573300 | Y16: =X16-ROW()*0.000001 -> 90573300 | Z16: =IFERROR(INDEX($W$13:$W$31,MATCH(LARGE($Y$13:$Y$31,4),$Y$13:$Y$31,0)),"") -> Pereira | AA16: =IFERROR(INDEX($X$13:$X$31,MATCH(LARGE($Y$13:$Y$31,4),$Y$13:$Y$31,0)),0) -> 225927300
A17: =IF(Tienda_1!$A17="","","Tienda 1") -> Tienda 1 | B17: =IF($A17="","",Tienda_1!B17) -> Libros | C17: =IF($A17="","",Tienda_1!G17) -> Cali | D17: =IF($A17="","",Tienda_1!F17) -> Izabela de León | E17: =IF($A17="","",Tienda_1!I17) -> Tarjeta de crédito | F17: =IF($A17="","",VALUE(RIGHT(Tienda_1!E17,4))) -> 2020 | G17: =IF($A17="","",Tienda_1!C17) -> 56900 | H17: =IF($A17="","",Tienda_1!D17) -> 1200 | I17: =IF($A17="","",Tienda_1!H17) -> 5 | J17: =IF($A17="",0,IF(AND(OR('Cuadro-de-mando'!$B$4="(Todas)",'Cuadro-de-mando'!$B$4=$A17),OR('Cuadro-de-mando'!$E$4="(Todas)",'Cuadro-de-mando'!$E$4=$B17),OR('Cuadro-de-mando'!$H$4="(Todas)",'Cuadro-de-mando'!$H$4=$C17),OR('Cuadro-de-mando'!$K$4="(Todas)",'Cuadro-de-mando'!$K$4=$E17),OR('Cuadro-de-mando'!$N$4="(Todos)",'Cuadro-de-mando'!$N$4=$F17)),1,0)) -> 1 | P17: =Análisis!A43 -> Pereira | T17: =Q4 -> Cupón | U17: =SUMIFS(Datos_Consolidados!$G$2:$G$9601,Datos_Consolidados!$J$2:$J$9601,1,Datos_Consolidados!$E$2:$E$9601,$T17) -> 235869600 | W17: =P8 -> Cali | X17: =SUMIFS(Datos_Consolidados!$G$2:$G$9601,Datos_Consolidados!$J$2:$J$9601,1,Datos_Consolidados!$C$2:$C$9601,$W17) -> 506526100 | Y17: =X17-ROW()*0.000001 -> 5.065261e+08 | Z17: =IFERROR(INDEX($W$13:$W$31,MATCH(LARGE($Y$13:$Y$31,5),$Y$13:$Y$31,0)),"") -> Barranquilla | AA17: =IFERROR(INDEX($X$13:$X$31,MATCH(LARGE($Y$13:$Y$31,5),$Y$13:$Y$31,0)),0) -> 132040500
A18: =IF(Tienda_1!$A18="","","Tienda 1") -> Tienda 1 | B18: =IF($A18="","",Tienda_1!B18) -> Deportes y diversión | C18: =IF($A18="","",Tienda_1!G18) -> Medellín | D18: =IF($A18="","",Tienda_1!F18) -> Pedro Gomez | E18: =IF($A18="","",Tienda_1!I18) -> Nequi | F18: =IF($A18="","",VALUE(RIGHT(Tienda_1!E18,4))) -> 2022 | G18: =IF($A18="","",Tienda_1!C18) -> 58900 | H18: =IF($A18="","",Tienda_1!D18) -> 1300 | I18: =IF($A18="","",Tienda_1!H18) -> 2 | J18: =IF($A18="",0,IF(AND(OR('Cuadro-de-mando'!$B$4="(Todas)",'Cuadro-de-mando'!$B$4=$A18),OR('Cuadro-de-mando'!$E$4="(Todas)",'Cuadro-de-mando'!$E$4=$B18),OR('Cuadro-de-mando'!$H$4="(Todas)",'Cuadro-de-mando'!$H$4=$C18),OR('Cuadro-de-mando'!$K$4="(Todas)",'Cuadro-de-mando'!$K$4=$E18),OR('Cuadro-de-mando'!$N$4="(Todos)",'Cuadro-de-mando'!$N$4=$F18)),1,0)) -> 1 | P18: =Análisis!A44 -> Riohacha | T18: =Q5 -> Nequi | U18: =SUMIFS(Datos_Consolidados!$G$2:$G$9601,Datos_Consolidados!$J$2:$J$9601,1,Datos_Consolidados!$E$2:$E$9601,$T18) -> 880684200 | W18: =P9 -> Cartagena | X18: =SUMIFS(Datos_Consolidados!$G$2:$G$9601,Datos_Consolidados!$J$2:$J$9601,1,Datos_Consolidados!$C$2:$C$9601,$W18) -> 102376700 | Y18: =X18-ROW()*0.000001 -> 1.023767e+08 | Z18: =IFERROR(INDEX($W$13:$W$31,MATCH(LARGE($Y$13:$Y$31,6),$Y$13:$Y$31,0)),"") -> Cartagena | AA18: =IFERROR(INDEX($X$13:$X$31,MATCH(LARGE($Y$13:$Y$31,6),$Y$13:$Y$31,0)),0) -> 102376700
A19: =IF(Tienda_1!$A19="","","Tienda 1") -> Tienda 1 | B19: =IF($A19="","",Tienda_1!B19) -> Juguetes | C19: =IF($A19="","",Tienda_1!G19) -> Santa Marta | D19: =IF($A19="","",Tienda_1!F19) -> Izabela de León | E19: =IF($A19="","",Tienda_1!I19) -> Tarjeta de crédito | F19: =IF($A19="","",VALUE(RIGHT(Tienda_1!E19,4))) -> 2021 | G19: =IF($A19="","",Tienda_1!C19) -> 29600 | H19: =IF($A19="","",Tienda_1!D19) -> 1800 | I19: =IF($A19="","",Tienda_1!H19) -> 5 | J19: =IF($A19="",0,IF(AND(OR('Cuadro-de-mando'!$B$4="(Todas)",'Cuadro-de-mando'!$B$4=$A19),OR('Cuadro-de-mando'!$E$4="(Todas)",'Cuadro-de-mando'!$E$4=$B19),OR('Cuadro-de-mando'!$H$4="(Todas)",'Cuadro-de-mando'!$H$4=$C19),OR('Cuadro-de-mando'!$K$4="(Todas)",'Cuadro-de-mando'!$K$4=$E19),OR('Cuadro-de-mando'!$N$4="(Todos)",'Cuadro-de-mando'!$N$4=$F19)),1,0)) -> 1 | P19: =Análisis!A45 -> Santa Marta | T19: =Q6 -> Tarjeta de crédito | U19: =SUMIFS(Datos_Consolidados!$G$2:$G$9601,Datos_Consolidados!$J$2:$J$9601,1,Datos_Consolidados!$E$2:$E$9601,$T19) -> 3230607100 | W19: =P10 -> Cúcuta | X19: =SUMIFS(Datos_Consolidados!$G$2:$G$9601,Datos_Consolidados!$J$2:$J$9601,1,Datos_Consolidados!$C$2:$C$9601,$W19) -> 99369100 | Y19: =X19-ROW()*0.000001 -> 99369100 | Z19: =IFERROR(INDEX($W$13:$W$31,MATCH(LARGE($Y$13:$Y$31,7),$Y$13:$Y$31,0)),"") -> Cúcuta | AA19: =IFERROR(INDEX($X$13:$X$31,MATCH(LARGE($Y$13:$Y$31,7),$Y$13:$Y$31,0)),0) -> 99369100
A20: =IF(Tienda_1!$A20="","","Tienda 1") -> Tienda 1 | B20: =IF($A20="","",Tienda_1!B20) -> Electrónicos | C20: =IF($A20="","",Tienda_1!G20) -> Bogotá | D20: =IF($A20="","",Tienda_1!F20) -> Beatriz Morales | E20: =IF($A20="","",Tienda_1!I20) -> Tarjeta de crédito | F20: =IF($A20="","",VALUE(RIGHT(Tienda_1!E20,4))) -> 2022 | G20: =IF($A20="","",Tienda_1!C20) -> 1891700 | H20: =IF($A20="","",Tienda_1!D20) -> 107900 | I20: =IF($A20="","",Tienda_1!H20) -> 3 | J20: =IF($A20="",0,IF(AND(OR('Cuadro-de-mando'!$B$4="(Todas)",'Cuadro-de-mando'!$B$4=$A20),OR('Cuadro-de-mando'!$E$4="(Todas)",'Cuadro-de-mando'!$E$4=$B20),OR('Cuadro-de-mando'!$H$4="(Todas)",'Cuadro-de-mando'!$H$4=$C20),OR('Cuadro-de-mando'!$K$4="(Todas)",'Cuadro-de-mando'!$K$4=$E20),OR('Cuadro-de-mando'!$N$4="(Todos)",'Cuadro-de-mando'!$N$4=$F20)),1,0)) -> 1 | P20: =Análisis!A46 -> Soacha | T20: =Q7 -> Tarjeta de débito | U20: =SUMIFS(Datos_Consolidados!$G$2:$G$9601,Datos_Consolidados!$J$2:$J$9601,1,Datos_Consolidados!$E$2:$E$9601,$T20) -> 56458300 | W20: =P11 -> Inírida | X20: =SUMIFS(Datos_Consolidados!$G$2:$G$9601,Datos_Consolidados!$J$2:$J$9601,1,Datos_Consolidados!$C$2:$C$9601,$W20) -> 8087900 | Y20: =X20-ROW()*0.000001 -> 8087900 | Z20: =IFERROR(INDEX($W$13:$W$31,MATCH(LARGE($Y$13:$Y$31,8),$Y$13:$Y$31,0)),"") -> Bucaramanga | AA20: =IFERROR(INDEX($X$13:$X$31,MATCH(LARGE($Y$13:$Y$31,8),$Y$13:$Y$31,0)),0) -> 90573300
A21: =IF(Tienda_1!$A21="","","Tienda 1") -> Tienda 1 | B21: =IF($A21="","",Tienda_1!B21) -> Juguetes | C21: =IF($A21="","",Tienda_1!G21) -> Medellín | D21: =IF($A21="","",Tienda_1!F21) -> Izabela de León | E21: =IF($A21="","",Tienda_1!I21) -> Tarjeta de crédito | F21: =IF($A21="","",VALUE(RIGHT(Tienda_1!E21,4))) -> 2020 | G21: =IF($A21="","",Tienda_1!C21) -> 138900 | H21: =IF($A21="","",Tienda_1!D21) -> 9800 | I21: =IF($A21="","",Tienda_1!H21) -> 4 | J21: =IF($A21="",0,IF(AND(OR('Cuadro-de-mando'!$B$4="(Todas)",'Cuadro-de-mando'!$B$4=$A21),OR('Cuadro-de-mando'!$E$4="(Todas)",'Cuadro-de-mando'!$E$4=$B21),OR('Cuadro-de-mando'!$H$4="(Todas)",'Cuadro-de-mando'!$H$4=$C21),OR('Cuadro-de-mando'!$K$4="(Todas)",'Cuadro-de-mando'!$K$4=$E21),OR('Cuadro-de-mando'!$N$4="(Todos)",'Cuadro-de-mando'!$N$4=$F21)),1,0)) -> 1 | P21: =Análisis!A47 -> Valledupar | W21: =P12 -> Leticia | X21: =SUMIFS(Datos_Consolidados!$G$2:$G$9601,Datos_Consolidados!$J$2:$J$9601,1,Datos_Consolidados!$C$2:$C$9601,$W21) -> 67149900 | Y21: =X21-ROW()*0.000001 -> 67149900 | Z21: =IFERROR(INDEX($W$13:$W$31,MATCH(LARGE($Y$13:$Y$31,9),$Y$13:$Y$31,0)),"") -> Riohacha | AA21: =IFERROR(INDEX($X$13:$X$31,MATCH(LARGE($Y$13:$Y$31,9),$Y$13:$Y$31,0)),0) -> 73879700
A22: =IF(Tienda_1!$A22="","","Tienda 1") -> Tienda 1 | B22: =IF($A22="","",Tienda_1!B22) -> Electrodomésticos | C22: =IF($A22="","",Tienda_1!G22) -> Cali | D22: =IF($A22="","",Tienda_1!F22) -> Izabela de León | E22: =IF($A22="","",Tienda_1!I22) -> Cupón | F22: =IF($A22="","",VALUE(RIGHT(Tienda_1!E22,4))) -> 2021 | G22: =IF($A22="","",Tienda_1!C22) -> 435700 | H22: =IF($A22="","",Tienda_1!D22) -> 23400 | I22: =IF($A22="","",Tienda_1!H22) -> 5 | J22: =IF($A22="",0,IF(AND(OR('Cuadro-de-mando'!$B$4="(Todas)",'Cuadro-de-mando'!$B$4=$A22),OR('Cuadro-de-mando'!$E$4="(Todas)",'Cuadro-de-mando'!$E$4=$B22),OR('Cuadro-de-mando'!$H$4="(Todas)",'Cuadro-de-mando'!$H$4=$C22),OR('Cuadro-de-mando'!$K$4="(Todas)",'Cuadro-de-mando'!$K$4=$E22),OR('Cuadro-de-mando'!$N$4="(Todos)",'Cuadro-de-mando'!$N$4=$F22)),1,0)) -> 1 | P22: =Análisis!A48 -> Villavicencio | W22: =P13 -> Manizales | X22: =SUMIFS(Datos_Consolidados!$G$2:$G$9601,Datos_Consolidados!$J$2:$J$9601,1,Datos_Consolidados!$C$2:$C$9601,$W22) -> 19367900 | Y22: =X22-ROW()*0.000001 -> 19367900 | Z22: =IFERROR(INDEX($W$13:$W$31,MATCH(LARGE($Y$13:$Y$31,10),$Y$13:$Y$31,0)),"") -> Leticia | AA22: =IFERROR(INDEX($X$13:$X$31,MATCH(LARGE($Y$13:$Y$31,10),$Y$13:$Y$31,0)),0) -> 67149900
A23: =IF(Tienda_1!$A23="","","Tienda 1") -> Tienda 1 | B23: =IF($A23="","",Tienda_1!B23) -> Deportes y diversión | C23: =IF($A23="","",Tienda_1!G23) -> Bogotá | D23: =IF($A23="","",Tienda_1!F23) -> Camila Rivera | E23: =IF($A23="","",Tienda_1!I23) -> Tarjeta de crédito | F23: =IF($A23="","",VALUE(RIGHT(Tienda_1!E23,4))) -> 2022 | G23: =IF($A23="","",Tienda_1!C23) -> 50800 | H23: =IF($A23="","",Tienda_1!D23) -> 3100 | I23: =IF($A23="","",Tienda_1!H23) -> 5 | J23: =IF($A23="",0,IF(AND(OR('Cuadro-de-mando'!$B$4="(Todas)",'Cuadro-de-mando'!$B$4=$A23),OR('Cuadro-de-mando'!$E$4="(Todas)",'Cuadro-de-mando'!$E$4=$B23),OR('Cuadro-de-mando'!$H$4="(Todas)",'Cuadro-de-mando'!$H$4=$C23),OR('Cuadro-de-mando'!$K$4="(Todas)",'Cuadro-de-mando'!$K$4=$E23),OR('Cuadro-de-mando'!$N$4="(Todos)",'Cuadro-de-mando'!$N$4=$F23)),1,0)) -> 1 | W23: =P14 -> Medellín | X23: =SUMIFS(Datos_Consolidados!$G$2:$G$9601,Datos_Consolidados!$J$2:$J$9601,1,Datos_Consolidados!$C$2:$C$9601,$W23) -> 1096669200 | Y23: =X23-ROW()*0.000001 -> 1.0966692e+09
A24: =IF(Tienda_1!$A24="","","Tienda 1") -> Tienda 1 | B24: =IF($A24="","",Tienda_1!B24) -> Deportes y diversión | C24: =IF($A24="","",Tienda_1!G24) -> Medellín | D24: =IF($A24="","",Tienda_1!F24) -> Maria Alfonso | E24: =IF($A24="","",Tienda_1!I24) -> Tarjeta de crédito | F24: =IF($A24="","",VALUE(RIGHT(Tienda_1!E24,4))) -> 2022 | G24: =IF($A24="","",Tienda_1!C24) -> 514500 | H24: =IF($A24="","",Tienda_1!D24) -> 27600 | I24: =IF($A24="","",Tienda_1!H24) -> 3 | J24: =IF($A24="",0,IF(AND(OR('Cuadro-de-mando'!$B$4="(Todas)",'Cuadro-de-mando'!$B$4=$A24),OR('Cuadro-de-mando'!$E$4="(Todas)",'Cuadro-de-mando'!$E$4=$B24),OR('Cuadro-de-mando'!$H$4="(Todas)",'Cuadro-de-mando'!$H$4=$C24),OR('Cuadro-de-mando'!$K$4="(Todas)",'Cuadro-de-mando'!$K$4=$E24),OR('Cuadro-de-mando'!$N$4="(Todos)",'Cuadro-de-mando'!$N$4=$F24)),1,0)) -> 1 | W24: =P15 -> Neiva | X24: =SUMIFS(Datos_Consolidados!$G$2:$G$9601,Datos_Consolidados!$J$2:$J$9601,1,Datos_Consolidados!$C$2:$C$9601,$W24) -> 20898000 | Y24: =X24-ROW()*0.000001 -> 20898000
A25: =IF(Tienda_1!$A25="","","Tienda 1") -> Tienda 1 | B25: =IF($A25="","",Tienda_1!B25) -> Muebles | C25: =IF($A25="","",Tienda_1!G25) -> Bogotá | D25: =IF($A25="","",Tienda_1!F25) -> Camila Rivera | E25: =IF($A25="","",Tienda_1!I25) -> Tarjeta de crédito | F25: =IF($A25="","",VALUE(RIGHT(Tienda_1!E25,4))) -> 2023 | G25: =IF($A25="","",Tienda_1!C25) -> 293500 | H25: =IF($A25="","",Tienda_1!D25) -> 13800 | I25: =IF($A25="","",Tienda_1!H25) -> 4 | J25: =IF($A25="",0,IF(AND(OR('Cuadro-de-mando'!$B$4="(Todas)",'Cuadro-de-mando'!$B$4=$A25),OR('Cuadro-de-mando'!$E$4="(Todas)",'Cuadro-de-mando'!$E$4=$B25),OR('Cuadro-de-mando'!$H$4="(Todas)",'Cuadro-de-mando'!$H$4=$C25),OR('Cuadro-de-mando'!$K$4="(Todas)",'Cuadro-de-mando'!$K$4=$E25),OR('Cuadro-de-mando'!$N$4="(Todos)",'Cuadro-de-mando'!$N$4=$F25)),1,0)) -> 1 | W25: =P16 -> Pasto | X25: =SUMIFS(Datos_Consolidados!$G$2:$G$9601,Datos_Consolidados!$J$2:$J$9601,1,Datos_Consolidados!$C$2:$C$9601,$W25) -> 49014300 | Y25: =X25-ROW()*0.000001 -> 49014300 | Z25: Top 8 vendedores | AA25: Ingresos
A26: =IF(Tienda_1!$A26="","","Tienda 1") -> Tienda 1 | B26: =IF($A26="","",Tienda_1!B26) -> Libros | C26: =IF($A26="","",Tienda_1!G26) -> Medellín | D26: =IF($A26="","",Tienda_1!F26) -> Pedro Gomez | E26: =IF($A26="","",Tienda_1!I26) -> Tarjeta de crédito | F26: =IF($A26="","",VALUE(RIGHT(Tienda_1!E26,4))) -> 2023 | G26: =IF($A26="","",Tienda_1!C26) -> 33500 | H26: =IF($A26="","",Tienda_1!D26) -> 0 | I26: =IF($A26="","",Tienda_1!H26) -> 5 | J26: =IF($A26="",0,IF(AND(OR('Cuadro-de-mando'!$B$4="(Todas)",'Cuadro-de-mando'!$B$4=$A26),OR('Cuadro-de-mando'!$E$4="(Todas)",'Cuadro-de-mando'!$E$4=$B26),OR('Cuadro-de-mando'!$H$4="(Todas)",'Cuadro-de-mando'!$H$4=$C26),OR('Cuadro-de-mando'!$K$4="(Todas)",'Cuadro-de-mando'!$K$4=$E26),OR('Cuadro-de-mando'!$N$4="(Todos)",'Cuadro-de-mando'!$N$4=$F26)),1,0)) -> 1 | W26: =P17 -> Pereira | X26: =SUMIFS(Datos_Consolidados!$G$2:$G$9601,Datos_Consolidados!$J$2:$J$9601,1,Datos_Consolidados!$C$2:$C$9601,$W26) -> 225927300 | Y26: =X26-ROW()*0.000001 -> 2.259273e+08 | Z26: =IFERROR(INDEX($W$34:$W$47,MATCH(LARGE($Y$34:$Y$47,1),$Y$34:$Y$47,0)),"") -> Felipe Santos | AA26: =IFERROR(INDEX($X$34:$X$47,MATCH(LARGE($Y$34:$Y$47,1),$Y$34:$Y$47,0)),0) -> 353796000
A27: =IF(Tienda_1!$A27="","","Tienda 1") -> Tienda 1 | B27: =IF($A27="","",Tienda_1!B27) -> Artículos para el hogar | C27: =IF($A27="","",Tienda_1!G27) -> Bogotá | D27: =IF($A27="","",Tienda_1!F27) -> Juan Fernandez | E27: =IF($A27="","",Tienda_1!I27) -> Nequi | F27: =IF($A27="","",VALUE(RIGHT(Tienda_1!E27,4))) -> 2021 | G27: =IF($A27="","",Tienda_1!C27) -> 47900 | H27: =IF($A27="","",Tienda_1!D27) -> 3300 | I27: =IF($A27="","",Tienda_1!H27) -> 5 | J27: =IF($A27="",0,IF(AND(OR('Cuadro-de-mando'!$B$4="(Todas)",'Cuadro-de-mando'!$B$4=$A27),OR('Cuadro-de-mando'!$E$4="(Todas)",'Cuadro-de-mando'!$E$4=$B27),OR('Cuadro-de-mando'!$H$4="(Todas)",'Cuadro-de-mando'!$H$4=$C27),OR('Cuadro-de-mando'!$K$4="(Todas)",'Cuadro-de-mando'!$K$4=$E27),OR('Cuadro-de-mando'!$N$4="(Todos)",'Cuadro-de-mando'!$N$4=$F27)),1,0)) -> 1 | W27: =P18 -> Riohacha | X27: =SUMIFS(Datos_Consolidados!$G$2:$G$9601,Datos_Consolidados!$J$2:$J$9601,1,Datos_Consolidados!$C$2:$C$9601,$W27) -> 73879700 | Y27: =X27-ROW()*0.000001 -> 73879700 | Z27: =IFERROR(INDEX($W$34:$W$47,MATCH(LARGE($Y$34:$Y$47,2),$Y$34:$Y$47,0)),"") -> Izabela de León | AA27: =IFERROR(INDEX($X$34:$X$47,MATCH(LARGE($Y$34:$Y$47,2),$Y$34:$Y$47,0)),0) -> 350342400
A28: =IF(Tienda_1!$A28="","","Tienda 1") -> Tienda 1 | B28: =IF($A28="","",Tienda_1!B28) -> Artículos para el hogar | C28: =IF($A28="","",Tienda_1!G28) -> Medellín | D28: =IF($A28="","",Tienda_1!F28) -> Beatriz Morales | E28: =IF($A28="","",Tienda_1!I28) -> Nequi | F28: =IF($A28="","",VALUE(RIGHT(Tienda_1!E28,4))) -> 2023 | G28: =IF($A28="","",Tienda_1!C28) -> 139300 | H28: =IF($A28="","",Tienda_1!D28) -> 8100 | I28: =IF($A28="","",Tienda_1!H28) -> 5 | J28: =IF($A28="",0,IF(AND(OR('Cuadro-de-mando'!$B$4="(Todas)",'Cuadro-de-mando'!$B$4=$A28),OR('Cuadro-de-mando'!$E$4="(Todas)",'Cuadro-de-mando'!$E$4=$B28),OR('Cuadro-de-mando'!$H$4="(Todas)",'Cuadro-de-mando'!$H$4=$C28),OR('Cuadro-de-mando'!$K$4="(Todas)",'Cuadro-de-mando'!$K$4=$E28),OR('Cuadro-de-mando'!$N$4="(Todos)",'Cuadro-de-mando'!$N$4=$F28)),1,0)) -> 1 | W28: =P19 -> Santa Marta | X28: =SUMIFS(Datos_Consolidados!$G$2:$G$9601,Datos_Consolidados!$J$2:$J$9601,1,Datos_Consolidados!$C$2:$C$9601,$W28) -> 53100500 | Y28: =X28-ROW()*0.000001 -> 53100500 | Z28: =IFERROR(INDEX($W$34:$W$47,MATCH(LARGE($Y$34:$Y$47,3),$Y$34:$Y$47,0)),"") -> Maria Alfonso | AA28: =IFERROR(INDEX($X$34:$X$47,MATCH(LARGE($Y$34:$Y$47,3),$Y$34:$Y$47,0)),0) -> 349694800
A29: =IF(Tienda_1!$A29="","","Tienda 1") -> Tienda 1 | B29: =IF($A29="","",Tienda_1!B29) -> Instrumentos musicales | C29: =IF($A29="","",Tienda_1!G29) -> Bogotá | D29: =IF($A29="","",Tienda_1!F29) -> Juliana Costa | E29: =IF($A29="","",Tienda_1!I29) -> Tarjeta de crédito | F29: =IF($A29="","",VALUE(RIGHT(Tienda_1!E29,4))) -> 2020 | G29: =IF($A29="","",Tienda_1!C29) -> 583900 | H29: =IF($A29="","",Tienda_1!D29) -> 29300 | I29: =IF($A29="","",Tienda_1!H29) -> 1 | J29: =IF($A29="",0,IF(AND(OR('Cuadro-de-mando'!$B$4="(Todas)",'Cuadro-de-mando'!$B$4=$A29),OR('Cuadro-de-mando'!$E$4="(Todas)",'Cuadro-de-mando'!$E$4=$B29),OR('Cuadro-de-mando'!$H$4="(Todas)",'Cuadro-de-mando'!$H$4=$C29),OR('Cuadro-de-mando'!$K$4="(Todas)",'Cuadro-de-mando'!$K$4=$E29),OR('Cuadro-de-mando'!$N$4="(Todos)",'Cuadro-de-mando'!$N$4=$F29)),1,0)) -> 1 | W29: =P20 -> Soacha | X29: =SUMIFS(Datos_Consolidados!$G$2:$G$9601,Datos_Consolidados!$J$2:$J$9601,1,Datos_Consolidados!$C$2:$C$9601,$W29) -> 12317700 | Y29: =X29-ROW()*0.000001 -> 12317700 | Z29: =IFERROR(INDEX($W$34:$W$47,MATCH(LARGE($Y$34:$Y$47,4),$Y$34:$Y$47,0)),"") -> Juliana Costa | AA29: =IFERROR(INDEX($X$34:$X$47,MATCH(LARGE($Y$34:$Y$47,4),$Y$34:$Y$47,0)),0) -> 338364700
A30: =IF(Tienda_1!$A30="","","Tienda 1") -> Tienda 1 | B30: =IF($A30="","",Tienda_1!B30) -> Deportes y diversión | C30: =IF($A30="","",Tienda_1!G30) -> Barranquilla | D30: =IF($A30="","",Tienda_1!F30) -> Felipe Santos | E30: =IF($A30="","",Tienda_1!I30) -> Tarjeta de crédito | F30: =IF($A30="","",VALUE(RIGHT(Tienda_1!E30,4))) -> 2020 | G30: =IF($A30="","",Tienda_1!C30) -> 18400 | H30: =IF($A30="","",Tienda_1!D30) -> 1200 | I30: =IF($A30="","",Tienda_1!H30) -> 1 | J30: =IF($A30="",0,IF(AND(OR('Cuadro-de-mando'!$B$4="(Todas)",'Cuadro-de-mando'!$B$4=$A30),OR('Cuadro-de-mando'!$E$4="(Todas)",'Cuadro-de-mando'!$E$4=$B30),OR('Cuadro-de-mando'!$H$4="(Todas)",'Cuadro-de-mando'!$H$4=$C30),OR('Cuadro-de-mando'!$K$4="(Todas)",'Cuadro-de-mando'!$K$4=$E30),OR('Cuadro-de-mando'!$N$4="(Todos)",'Cuadro-de-mando'!$N$4=$F30)),1,0)) -> 1 | W30: =P21 -> Valledupar | X30: =SUMIFS(Datos_Consolidados!$G$2:$G$9601,Datos_Consolidados!$J$2:$J$9601,1,Datos_Consolidados!$C$2:$C$9601,$W30) -> 5886300 | Y30: =X30-ROW()*0.000001 -> 5886300 | Z30: =IFERROR(INDEX($W$34:$W$47,MATCH(LARGE($Y$34:$Y$47,5),$Y$34:$Y$47,0)),"") -> Pedro Gomez | AA30: =IFERROR(INDEX($X$34:$X$47,MATCH(LARGE($Y$34:$Y$47,5),$Y$34:$Y$47,0)),0) -> 313350900
A31: =IF(Tienda_1!$A31="","","Tienda 1") -> Tienda 1 | B31: =IF($A31="","",Tienda_1!B31) -> Juguetes | C31: =IF($A31="","",Tienda_1!G31) -> Bogotá | D31: =IF($A31="","",Tienda_1!F31) -> Ángel Rodriguez | E31: =IF($A31="","",Tienda_1!I31) -> Cupón | F31: =IF($A31="","",VALUE(RIGHT(Tienda_1!E31,4))) -> 2021 | G31: =IF($A31="","",Tienda_1!C31) -> 79100 | H31: =IF($A31="","",Tienda_1!D31) -> 2400 | I31: =IF($A31="","",Tienda_1!H31) -> 4 | J31: =IF($A31="",0,IF(AND(OR('Cuadro-de-mando'!$B$4="(Todas)",'Cuadro-de-mando'!$B$4=$A31),OR('Cuadro-de-mando'!$E$4="(Todas)",'Cuadro-de-mando'!$E$4=$B31),OR('Cuadro-de-mando'!$H$4="(Todas)",'Cuadro-de-mando'!$H$4=$C31),OR('Cuadro-de-mando'!$K$4="(Todas)",'Cuadro-de-mando'!$K$4=$E31),OR('Cuadro-de-mando'!$N$4="(Todos)",'Cuadro-de-mando'!$N$4=$F31)),1,0)) -> 1 | W31: =P22 -> Villavicencio | X31: =SUMIFS(Datos_Consolidados!$G$2:$G$9601,Datos_Consolidados!$J$2:$J$9601,1,Datos_Consolidados!$C$2:$C$9601,$W31) -> 13333600 | Y31: =X31-ROW()*0.000001 -> 13333600 | Z31: =IFERROR(INDEX($W$34:$W$47,MATCH(LARGE($Y$34:$Y$47,6),$Y$34:$Y$47,0)),"") -> Rafael Acosta | AA31: =IFERROR(INDEX($X$34:$X$47,MATCH(LARGE($Y$34:$Y$47,6),$Y$34:$Y$47,0)),0) -> 310292300
A32: =IF(Tienda_1!$A32="","","Tienda 1") -> Tienda 1 | B32: =IF($A32="","",Tienda_1!B32) -> Electrodomésticos | C32: =IF($A32="","",Tienda_1!G32) -> Medellín | D32: =IF($A32="","",Tienda_1!F32) -> Mariana Herrera | E32: =IF($A32="","",Tienda_1!I32) -> Tarjeta de crédito | F32: =IF($A32="","",VALUE(RIGHT(Tienda_1!E32,4))) -> 2021 | G32: =IF($A32="","",Tienda_1!C32) -> 564200 | H32: =IF($A32="","",Tienda_1!D32) -> 28200 | I32: =IF($A32="","",Tienda_1!H32) -> 1 | J32: =IF($A32="",0,IF(AND(OR('Cuadro-de-mando'!$B$4="(Todas)",'Cuadro-de-mando'!$B$4=$A32),OR('Cuadro-de-mando'!$E$4="(Todas)",'Cuadro-de-mando'!$E$4=$B32),OR('Cuadro-de-mando'!$H$4="(Todas)",'Cuadro-de-mando'!$H$4=$C32),OR('Cuadro-de-mando'!$K$4="(Todas)",'Cuadro-de-mando'!$K$4=$E32),OR('Cuadro-de-mando'!$N$4="(Todos)",'Cuadro-de-mando'!$N$4=$F32)),1,0)) -> 1 | Z32: =IFERROR(INDEX($W$34:$W$47,MATCH(LARGE($Y$34:$Y$47,7),$Y$34:$Y$47,0)),"") -> Juan Fernandez | AA32: =IFERROR(INDEX($X$34:$X$47,MATCH(LARGE($Y$34:$Y$47,7),$Y$34:$Y$47,0)),0) -> 308562100
A33: =IF(Tienda_1!$A33="","","Tienda 1") -> Tienda 1 | B33: =IF($A33="","",Tienda_1!B33) -> Juguetes | C33: =IF($A33="","",Tienda_1!G33) -> Medellín | D33: =IF($A33="","",Tienda_1!F33) -> Ángel Rodriguez | E33: =IF($A33="","",Tienda_1!I33) -> Tarjeta de crédito | F33: =IF($A33="","",VALUE(RIGHT(Tienda_1!E33,4))) -> 2021 | G33: =IF($A33="","",Tienda_1!C33) -> 153900 | H33: =IF($A33="","",Tienda_1!D33) -> 6400 | I33: =IF($A33="","",Tienda_1!H33) -> 3 | J33: =IF($A33="",0,IF(AND(OR('Cuadro-de-mando'!$B$4="(Todas)",'Cuadro-de-mando'!$B$4=$A33),OR('Cuadro-de-mando'!$E$4="(Todas)",'Cuadro-de-mando'!$E$4=$B33),OR('Cuadro-de-mando'!$H$4="(Todas)",'Cuadro-de-mando'!$H$4=$C33),OR('Cuadro-de-mando'!$K$4="(Todas)",'Cuadro-de-mando'!$K$4=$E33),OR('Cuadro-de-mando'!$N$4="(Todos)",'Cuadro-de-mando'!$N$4=$F33)),1,0)) -> 1 | W33: Vendedor | X33: Ingresos | Y33: Desempate | Z33: =IFERROR(INDEX($W$34:$W$47,MATCH(LARGE($Y$34:$Y$47,8),$Y$34:$Y$47,0)),"") -> Lucas Olivera | AA33: =IFERROR(INDEX($X$34:$X$47,MATCH(LARGE($Y$34:$Y$47,8),$Y$34:$Y$47,0)),0) -> 305403600
A34: =IF(Tienda_1!$A34="","","Tienda 1") -> Tienda 1 | B34: =IF($A34="","",Tienda_1!B34) -> Muebles | C34: =IF($A34="","",Tienda_1!G34) -> Medellín | D34: =IF($A34="","",Tienda_1!F34) -> Felipe Santos | E34: =IF($A34="","",Tienda_1!I34) -> Tarjeta de crédito | F34: =IF($A34="","",VALUE(RIGHT(Tienda_1!E34,4))) -> 2020 | G34: =IF($A34="","",Tienda_1!C34) -> 331400 | H34: =IF($A34="","",Tienda_1!D34) -> 17900 | I34: =IF($A34="","",Tienda_1!H34) -> 2 | J34: =IF($A34="",0,IF(AND(OR('Cuadro-de-mando'!$B$4="(Todas)",'Cuadro-de-mando'!$B$4=$A34),OR('Cuadro-de-mando'!$E$4="(Todas)",'Cuadro-de-mando'!$E$4=$B34),OR('Cuadro-de-mando'!$H$4="(Todas)",'Cuadro-de-mando'!$H$4=$C34),OR('Cuadro-de-mando'!$K$4="(Todas)",'Cuadro-de-mando'!$K$4=$E34),OR('Cuadro-de-mando'!$N$4="(Todos)",'Cuadro-de-mando'!$N$4=$F34)),1,0)) -> 1 | W34: =Análisis!A53 -> Beatriz Morales | X34: =SUMIFS(Datos_Consolidados!$G$2:$G$9601,Datos_Consolidados!$J$2:$J$9601,1,Datos_Consolidados!$D$2:$D$9601,$W34) -> 302695600 | Y34: =X34-ROW()*0.000001 -> 3.026956e+08
A35: =IF(Tienda_1!$A35="","","Tienda 1") -> Tienda 1 | B35: =IF($A35="","",Tienda_1!B35) -> Deportes y diversión | C35: =IF($A35="","",Tienda_1!G35) -> Bogotá | D35: =IF($A35="","",Tienda_1!F35) -> Juliana Costa | E35: =IF($A35="","",Tienda_1!I35) -> Tarjeta de crédito | F35: =IF($A35="","",VALUE(RIGHT(Tienda_1!E35,4))) -> 2020 | G35: =IF($A35="","",Tienda_1!C35) -> 55600 | H35: =IF($A35="","",Tienda_1!D35) -> 7700 | I35: =IF($A35="","",Tienda_1!H35) -> 5 | J35: =IF($A35="",0,IF(AND(OR('Cuadro-de-mando'!$B$4="(Todas)",'Cuadro-de-mando'!$B$4=$A35),OR('Cuadro-de-mando'!$E$4="(Todas)",'Cuadro-de-mando'!$E$4=$B35),OR('Cuadro-de-mando'!$H$4="(Todas)",'Cuadro-de-mando'!$H$4=$C35),OR('Cuadro-de-mando'!$K$4="(Todas)",'Cuadro-de-mando'!$K$4=$E35),OR('Cuadro-de-mando'!$N$4="(Todos)",'Cuadro-de-mando'!$N$4=$F35)),1,0)) -> 1 | W35: =Análisis!A54 -> Blanca Ramirez | X35: =SUMIFS(Datos_Consolidados!$G$2:$G$9601,Datos_Consolidados!$J$2:$J$9601,1,Datos_Consolidados!$D$2:$D$9601,$W35) -> 299586600 | Y35: =X35-ROW()*0.000001 -> 2.995866e+08
A36: =IF(Tienda_1!$A36="","","Tienda 1") -> Tienda 1 | B36: =IF($A36="","",Tienda_1!B36) -> Juguetes | C36: =IF($A36="","",Tienda_1!G36) -> Bogotá | D36: =IF($A36="","",Tienda_1!F36) -> Blanca Ramirez | E36: =IF($A36="","",Tienda_1!I36) -> Tarjeta de crédito | F36: =IF($A36="","",VALUE(RIGHT(Tienda_1!E36,4))) -> 2021 | G36: =IF($A36="","",Tienda_1!C36) -> 24700 | H36: =IF($A36="","",Tienda_1!D36) -> 1700 | I36: =IF($A36="","",Tienda_1!H36) -> 5 | J36: =IF($A36="",0,IF(AND(OR('Cuadro-de-mando'!$B$4="(Todas)",'Cuadro-de-mando'!$B$4=$A36),OR('Cuadro-de-mando'!$E$4="(Todas)",'Cuadro-de-mando'!$E$4=$B36),OR('Cuadro-de-mando'!$H$4="(Todas)",'Cuadro-de-mando'!$H$4=$C36),OR('Cuadro-de-mando'!$K$4="(Todas)",'Cuadro-de-mando'!$K$4=$E36),OR('Cuadro-de-mando'!$N$4="(Todos)",'Cuadro-de-mando'!$N$4=$F36)),1,0)) -> 1 | W36: =Análisis!A55 -> Camila Rivera | X36: =SUMIFS(Datos_Consolidados!$G$2:$G$9601,Datos_Consolidados!$J$2:$J$9601,1,Datos_Consolidados!$D$2:$D$9601,$W36) -> 303184200 | Y36: =X36-ROW()*0.000001 -> 3.031842e+08
A37: =IF(Tienda_1!$A37="","","Tienda 1") -> Tienda 1 | B37: =IF($A37="","",Tienda_1!B37) -> Deportes y diversión | C37: =IF($A37="","",Tienda_1!G37) -> Medellín | D37: =IF($A37="","",Tienda_1!F37) -> Felipe Santos | E37: =IF($A37="","",Tienda_1!I37) -> Tarjeta de crédito | F37: =IF($A37="","",VALUE(RIGHT(Tienda_1!E37,4))) -> 2022 | G37: =IF($A37="","",Tienda_1!C37) -> 62300 | H37: =IF($A37="","",Tienda_1!D37) -> 1500 | I37: =IF($A37="","",Tienda_1!H37) -> 3 | J37: =IF($A37="",0,IF(AND(OR('Cuadro-de-mando'!$B$4="(Todas)",'Cuadro-de-mando'!$B$4=$A37),OR('Cuadro-de-mando'!$E$4="(Todas)",'Cuadro-de-mando'!$E$4=$B37),OR('Cuadro-de-mando'!$H$4="(Todas)",'Cuadro-de-mando'!$H$4=$C37),OR('Cuadro-de-mando'!$K$4="(Todas)",'Cuadro-de-mando'!$K$4=$E37),OR('Cuadro-de-mando'!$N$4="(Todos)",'Cuadro-de-mando'!$N$4=$F37)),1,0)) -> 1 | W37: =Análisis!A56 -> Felipe Santos | X37: =SUMIFS(Datos_Consolidados!$G$2:$G$9601,Datos_Consolidados!$J$2:$J$9601,1,Datos_Consolidados!$D$2:$D$9601,$W37) -> 353796000 | Y37: =X37-ROW()*0.000001 -> 3.53796e+08
A38: =IF(Tienda_1!$A38="","","Tienda 1") -> Tienda 1 | B38: =IF($A38="","",Tienda_1!B38) -> Electrónicos | C38: =IF($A38="","",Tienda_1!G38) -> Bogotá | D38: =IF($A38="","",Tienda_1!F38) -> Blanca Ramirez | E38: =IF($A38="","",Tienda_1!I38) -> Tarjeta de crédito | F38: =IF($A38="","",VALUE(RIGHT(Tienda_1!E38,4))) -> 2021 | G38: =IF($A38="","",Tienda_1!C38) -> 300200 | H38: =IF($A38="","",Tienda_1!D38) -> 16200 | I38: =IF($A38="","",Tienda_1!H38) -> 5 | J38: =IF($A38="",0,IF(AND(OR('Cuadro-de-mando'!$B$4="(Todas)",'Cuadro-de-mando'!$B$4=$A38),OR('Cuadro-de-mando'!$E$4="(Todas)",'Cuadro-de-mando'!$E$4=$B38),OR('Cuadro-de-mando'!$H$4="(Todas)",'Cuadro-de-mando'!$H$4=$C38),OR('Cuadro-de-mando'!$K$4="(Todas)",'Cuadro-de-mando'!$K$4=$E38),OR('Cuadro-de-mando'!$N$4="(Todos)",'Cuadro-de-mando'!$N$4=$F38)),1,0)) -> 1 | W38: =Análisis!A57 -> Izabela de León | X38: =SUMIFS(Datos_Consolidados!$G$2:$G$9601,Datos_Consolidados!$J$2:$J$9601,1,Datos_Consolidados!$D$2:$D$9601,$W38) -> 350342400 | Y38: =X38-ROW()*0.000001 -> 3.503424e+08
A39: =IF(Tienda_1!$A39="","","Tienda 1") -> Tienda 1 | B39: =IF($A39="","",Tienda_1!B39) -> Muebles | C39: =IF($A39="","",Tienda_1!G39) -> Cali | D39: =IF($A39="","",Tienda_1!F39) -> Camila Rivera | E39: =IF($A39="","",Tienda_1!I39) -> Tarjeta de crédito | F39: =IF($A39="","",VALUE(RIGHT(Tienda_1!E39,4))) -> 2021 | G39: =IF($A39="","",Tienda_1!C39) -> 305400 | H39: =IF($A39="","",Tienda_1!D39) -> 16700 | I39: =IF($A39="","",Tienda_1!H39) -> 5 | J39: =IF($A39="",0,IF(AND(OR('Cuadro-de-mando'!$B$4="(Todas)",'Cuadro-de-mando'!$B$4=$A39),OR('Cuadro-de-mando'!$E$4="(Todas)",'Cuadro-de-mando'!$E$4=$B39),OR('Cuadro-de-mando'!$H$4="(Todas)",'Cuadro-de-mando'!$H$4=$C39),OR('Cuadro-de-mando'!$K$4="(Todas)",'Cuadro-de-mando'!$K$4=$E39),OR('Cuadro-de-mando'!$N$4="(Todos)",'Cuadro-de-mando'!$N$4=$F39)),1,0)) -> 1 | W39: =Análisis!A58 -> Juan Fernandez | X39: =SUMIFS(Datos_Consolidados!$G$2:$G$9601,Datos_Consolidados!$J$2:$J$9601,1,Datos_Consolidados!$D$2:$D$9601,$W39) -> 308562100 | Y39: =X39-ROW()*0.000001 -> 3.085621e+08
A40: =IF(Tienda_1!$A40="","","Tienda 1") -> Tienda 1 | B40: =IF($A40="","",Tienda_1!B40) -> Libros | C40: =IF($A40="","",Tienda_1!G40) -> Bogotá | D40: =IF($A40="","",Tienda_1!F40) -> Ángel Rodriguez | E40: =IF($A40="","",Tienda_1!I40) -> Tarjeta de crédito | F40: =IF($A40="","",VALUE(RIGHT(Tienda_1!E40,4))) -> 2020 | G40: =IF($A40="","",Tienda_1!C40) -> 30500 | H40: =IF($A40="","",Tienda_1!D40) -> 7500 | I40: =IF($A40="","",Tienda_1!H40) -> 5 | J40: =IF($A40="",0,IF(AND(OR('Cuadro-de-mando'!$B$4="(Todas)",'Cuadro-de-mando'!$B$4=$A40),OR('Cuadro-de-mando'!$E$4="(Todas)",'Cuadro-de-mando'!$E$4=$B40),OR('Cuadro-de-mando'!$H$4="(Todas)",'Cuadro-de-mando'!$H$4=$C40),OR('Cuadro-de-mando'!$K$4="(Todas)",'Cuadro-de-mando'!$K$4=$E40),OR('Cuadro-de-mando'!$N$4="(Todos)",'Cuadro-de-mando'!$N$4=$F40)),1,0)) -> 1 | W40: =Análisis!A59 -> Juliana Costa | X40: =SUMIFS(Datos_Consolidados!$G$2:$G$9601,Datos_Consolidados!$J$2:$J$9601,1,Datos_Consolidados!$D$2:$D$9601,$W40) -> 338364700 | Y40: =X40-ROW()*0.000001 -> 3.383647e+08
A41: =IF(Tienda_1!$A41="","","Tienda 1") -> Tienda 1 | B41: =IF($A41="","",Tienda_1!B41) -> Muebles | C41: =IF($A41="","",Tienda_1!G41) -> Villavicencio | D41: =IF($A41="","",Tienda_1!F41) -> Mariana Herrera | E41: =IF($A41="","",Tienda_1!I41) -> Tarjeta de crédito | F41: =IF($A41="","",VALUE(RIGHT(Tienda_1!E41,4))) -> 2021 | G41: =IF($A41="","",Tienda_1!C41) -> 327200 | H41: =IF($A41="","",Tienda_1!D41) -> 15600 | I41: =IF($A41="","",Tienda_1!H41) -> 5 | J41: =IF($A41="",0,IF(AND(OR('Cuadro-de-mando'!$B$4="(Todas)",'Cuadro-de-mando'!$B$4=$A41),OR('Cuadro-de-mando'!$E$4="(Todas)",'Cuadro-de-mando'!$E$4=$B41),OR('Cuadro-de-mando'!$H$4="(Todas)",'Cuadro-de-mando'!$H$4=$C41),OR('Cuadro-de-mando'!$K$4="(Todas)",'Cuadro-de-mando'!$K$4=$E41),OR('Cuadro-de-mando'!$N$4="(Todos)",'Cuadro-de-mando'!$N$4=$F41)),1,0)) -> 1 | W41: =Análisis!A60 -> Lucas Olivera | X41: =SUMIFS(Datos_Consolidados!$G$2:$G$9601,Datos_Consolidados!$J$2:$J$9601,1,Datos_Consolidados!$D$2:$D$9601,$W41) -> 305403600 | Y41: =X41-ROW()*0.000001 -> 3.054036e+08
A42: =IF(Tienda_1!$A42="","","Tienda 1") -> Tienda 1 | B42: =IF($A42="","",Tienda_1!B42) -> Electrónicos | C42: =IF($A42="","",Tienda_1!G42) -> Cali | D42: =IF($A42="","",Tienda_1!F42) -> Rafael Acosta | E42: =IF($A42="","",Tienda_1!I42) -> Cupón | F42: =IF($A42="","",VALUE(RIGHT(Tienda_1!E42,4))) -> 2022 | G42: =IF($A42="","",Tienda_1!C42) -> 68300 | H42: =IF($A42="","",Tienda_1!D42) -> 1800 | I42: =IF($A42="","",Tienda_1!H42) -> 5 | J42: =IF($A42="",0,IF(AND(OR('Cuadro-de-mando'!$B$4="(Todas)",'Cuadro-de-mando'!$B$4=$A42),OR('Cuadro-de-mando'!$E$4="(Todas)",'Cuadro-de-mando'!$E$4=$B42),OR('Cuadro-de-mando'!$H$4="(Todas)",'Cuadro-de-mando'!$H$4=$C42),OR('Cuadro-de-mando'!$K$4="(Todas)",'Cuadro-de-mando'!$K$4=$E42),OR('Cuadro-de-mando'!$N$4="(Todos)",'Cuadro-de-mando'!$N$4=$F42)),1,0)) -> 1 | W42: =Análisis!A61 -> Maria Alfonso | X42: =SUMIFS(Datos_Consolidados!$G$2:$G$9601,Datos_Consolidados!$J$2:$J$9601,1,Datos_Consolidados!$D$2:$D$9601,$W42) -> 349694800 | Y42: =X42-ROW()*0.000001 -> 3.496948e+08
A43: =IF(Tienda_1!$A43="","","Tienda 1") -> Tienda 1 | B43: =IF($A43="","",Tienda_1!B43) -> Muebles | C43: =IF($A43="","",Tienda_1!G43) -> Cali | D43: =IF($A43="","",Tienda_1!F43) -> Mariana Herrera | E43: =IF($A43="","",Tienda_1!I43) -> Tarjeta de crédito | F43: =IF($A43="","",VALUE(RIGHT(Tienda_1!E43,4))) -> 2021 | G43: =IF($A43="","",Tienda_1!C43) -> 513400 | H43: =IF($A43="","",Tienda_1!D43) -> 25500 | I43: =IF($A43="","",Tienda_1!H43) -> 5 | J43: =IF($A43="",0,IF(AND(OR('Cuadro-de-mando'!$B$4="(Todas)",'Cuadro-de-mando'!$B$4=$A43),OR('Cuadro-de-mando'!$E$4="(Todas)",'Cuadro-de-mando'!$E$4=$B43),OR('Cuadro-de-mando'!$H$4="(Todas)",'Cuadro-de-mando'!$H$4=$C43),OR('Cuadro-de-mando'!$K$4="(Todas)",'Cuadro-de-mando'!$K$4=$E43),OR('Cuadro-de-mando'!$N$4="(Todos)",'Cuadro-de-mando'!$N$4=$F43)),1,0)) -> 1 | W43: =Análisis!A62 -> Mariana Herrera | X43: =SUMIFS(Datos_Consolidados!$G$2:$G$9601,Datos_Consolidados!$J$2:$J$9601,1,Datos_Consolidados!$D$2:$D$9601,$W43) -> 283302600 | Y43: =X43-ROW()*0.000001 -> 2.833026e+08
A44: =IF(Tienda_1!$A44="","","Tienda 1") -> Tienda 1 | B44: =IF($A44="","",Tienda_1!B44) -> Juguetes | C44: =IF($A44="","",Tienda_1!G44) -> Medellín | D44: =IF($A44="","",Tienda_1!F44) -> Izabela de León | E44: =IF($A44="","",Tienda_1!I44) -> Nequi | F44: =IF($A44="","",VALUE(RIGHT(Tienda_1!E44,4))) -> 2021 | G44: =IF($A44="","",Tienda_1!C44) -> 13900 | H44: =IF($A44="","",Tienda_1!D44) -> 3100 | I44: =IF($A44="","",Tienda_1!H44) -> 4 | J44: =IF($A44="",0,IF(AND(OR('Cuadro-de-mando'!$B$4="(Todas)",'Cuadro-de-mando'!$B$4=$A44),OR('Cuadro-de-mando'!$E$4="(Todas)",'Cuadro-de-mando'!$E$4=$B44),OR('Cuadro-de-mando'!$H$4="(Todas)",'Cuadro-de-mando'!$H$4=$C44),OR('Cuadro-de-mando'!$K$4="(Todas)",'Cuadro-de-mando'!$K$4=$E44),OR('Cuadro-de-mando'!$N$4="(Todos)",'Cuadro-de-mando'!$N$4=$F44)),1,0)) -> 1 | W44: =Análisis!A63 -> Pedro Gomez | X44: =SUMIFS(Datos_Consolidados!$G$2:$G$9601,Datos_Consolidados!$J$2:$J$9601,1,Datos_Consolidados!$D$2:$D$9601,$W44) -> 313350900 | Y44: =X44-ROW()*0.000001 -> 3.133509e+08
A45: =IF(Tienda_1!$A45="","","Tienda 1") -> Tienda 1 | B45: =IF($A45="","",Tienda_1!B45) -> Electrodomésticos | C45: =IF($A45="","",Tienda_1!G45) -> Bogotá | D45: =IF($A45="","",Tienda_1!F45) -> Juliana Costa | E45: =IF($A45="","",Tienda_1!I45) -> Tarjeta de crédito | F45: =IF($A45="","",VALUE(RIGHT(Tienda_1!E45,4))) -> 2021 | G45: =IF($A45="","",Tienda_1!C45) -> 362000 | H45: =IF($A45="","",Tienda_1!D45) -> 17500 | I45: =IF($A45="","",Tienda_1!H45) -> 1 | J45: =IF($A45="",0,IF(AND(OR('Cuadro-de-mando'!$B$4="(Todas)",'Cuadro-de-mando'!$B$4=$A45),OR('Cuadro-de-mando'!$E$4="(Todas)",'Cuadro-de-mando'!$E$4=$B45),OR('Cuadro-de-mando'!$H$4="(Todas)",'Cuadro-de-mando'!$H$4=$C45),OR('Cuadro-de-mando'!$K$4="(Todas)",'Cuadro-de-mando'!$K$4=$E45),OR('Cuadro-de-mando'!$N$4="(Todos)",'Cuadro-de-mando'!$N$4=$F45)),1,0)) -> 1 | W45: =Análisis!A64 -> Rafael Acosta | X45: =SUMIFS(Datos_Consolidados!$G$2:$G$9601,Datos_Consolidados!$J$2:$J$9601,1,Datos_Consolidados!$D$2:$D$9601,$W45) -> 310292300 | Y45: =X45-ROW()*0.000001 -> 3.102923e+08
... A47: =IF(Tienda_1!$A47="","","Tienda 1") -> Tienda 1 | B47: =IF($A47="","",Tienda_1!B47) -> Deportes y diversión | C47: =IF($A47="","",Tienda_1!G47) -> Medellín | D47: =IF($A47="","",Tienda_1!F47) -> Juliana Costa | E47: =IF($A47="","",Tienda_1!I47) -> Tarjeta de crédito | F47: =IF($A47="","",VALUE(RIGHT(Tienda_1!E47,4))) -> 2021 | G47: =IF($A47="","",Tienda_1!C47) -> 428300 | H47: =IF($A47="","",Tienda_1!D47) -> 21000 | I47: =IF($A47="","",Tienda_1!H47) -> 5 | J47: =IF($A47="",0,IF(AND(OR('Cuadro-de-mando'!$B$4="(Todas)",'Cuadro-de-mando'!$B$4=$A47),OR('Cuadro-de-mando'!$E$4="(Todas)",'Cuadro-de-mando'!$E$4=$B47),OR('Cuadro-de-mando'!$H$4="(Todas)",'Cuadro-de-mando'!$H$4=$C47),OR('Cuadro-de-mando'!$K$4="(Todas)",'Cuadro-de-mando'!$K$4=$E47),OR('Cuadro-de-mando'!$N$4="(Todos)",'Cuadro-de-mando'!$N$4=$F47)),1,0)) -> 1 | W47: =Análisis!A66 -> Ángel Rodriguez | X47: =SUMIFS(Datos_Consolidados!$G$2:$G$9601,Datos_Consolidados!$J$2:$J$9601,1,Datos_Consolidados!$D$2:$D$9601,$W47) -> 291625200 | Y47: =X47-ROW()*0.000001 -> 2.916252e+08
A48: =IF(Tienda_1!$A48="","","Tienda 1") -> Tienda 1 | B48: =IF($A48="","",Tienda_1!B48) -> Instrumentos musicales | C48: =IF($A48="","",Tienda_1!G48) -> Inírida | D48: =IF($A48="","",Tienda_1!F48) -> Juan Fernandez | E48: =IF($A48="","",Tienda_1!I48) -> Tarjeta de crédito | F48: =IF($A48="","",VALUE(RIGHT(Tienda_1!E48,4))) -> 2023 | G48: =IF($A48="","",Tienda_1!C48) -> 679000 | H48: =IF($A48="","",Tienda_1!D48) -> 34300 | I48: =IF($A48="","",Tienda_1!H48) -> 4 | J48: =IF($A48="",0,IF(AND(OR('Cuadro-de-mando'!$B$4="(Todas)",'Cuadro-de-mando'!$B$4=$A48),OR('Cuadro-de-mando'!$E$4="(Todas)",'Cuadro-de-mando'!$E$4=$B48),OR('Cuadro-de-mando'!$H$4="(Todas)",'Cuadro-de-mando'!$H$4=$C48),OR('Cuadro-de-mando'!$K$4="(Todas)",'Cuadro-de-mando'!$K$4=$E48),OR('Cuadro-de-mando'!$N$4="(Todos)",'Cuadro-de-mando'!$N$4=$F48)),1,0)) -> 1
A49: =IF(Tienda_1!$A49="","","Tienda 1") -> Tienda 1 | B49: =IF($A49="","",Tienda_1!B49) -> Artículos para el hogar | C49: =IF($A49="","",Tienda_1!G49) -> Medellín | D49: =IF($A49="","",Tienda_1!F49) -> Mariana Herrera | E49: =IF($A49="","",Tienda_1!I49) -> Tarjeta de crédito | F49: =IF($A49="","",VALUE(RIGHT(Tienda_1!E49,4))) -> 2021 | G49: =IF($A49="","",Tienda_1!C49) -> 100900 | H49: =IF($A49="","",Tienda_1!D49) -> 5600 | I49: =IF($A49="","",Tienda_1!H49) -> 5 | J49: =IF($A49="",0,IF(AND(OR('Cuadro-de-mando'!$B$4="(Todas)",'Cuadro-de-mando'!$B$4=$A49),OR('Cuadro-de-mando'!$E$4="(Todas)",'Cuadro-de-mando'!$E$4=$B49),OR('Cuadro-de-mando'!$H$4="(Todas)",'Cuadro-de-mando'!$H$4=$C49),OR('Cuadro-de-mando'!$K$4="(Todas)",'Cuadro-de-mando'!$K$4=$E49),OR('Cuadro-de-mando'!$N$4="(Todos)",'Cuadro-de-mando'!$N$4=$F49)),1,0)) -> 1
A50: =IF(Tienda_1!$A50="","","Tienda 1") -> Tienda 1 | B50: =IF($A50="","",Tienda_1!B50) -> Electrodomésticos | C50: =IF($A50="","",Tienda_1!G50) -> Cali | D50: =IF($A50="","",Tienda_1!F50) -> Izabela de León | E50: =IF($A50="","",Tienda_1!I50) -> Nequi | F50: =IF($A50="","",VALUE(RIGHT(Tienda_1!E50,4))) -> 2020 | G50: =IF($A50="","",Tienda_1!C50) -> 739700 | H50: =IF($A50="","",Tienda_1!D50) -> 39900 | I50: =IF($A50="","",Tienda_1!H50) -> 5 | J50: =IF($A50="",0,IF(AND(OR('Cuadro-de-mando'!$B$4="(Todas)",'Cuadro-de-mando'!$B$4=$A50),OR('Cuadro-de-mando'!$E$4="(Todas)",'Cuadro-de-mando'!$E$4=$B50),OR('Cuadro-de-mando'!$H$4="(Todas)",'Cuadro-de-mando'!$H$4=$C50),OR('Cuadro-de-mando'!$K$4="(Todas)",'Cuadro-de-mando'!$K$4=$E50),OR('Cuadro-de-mando'!$N$4="(Todos)",'Cuadro-de-mando'!$N$4=$F50)),1,0)) -> 1
A51: =IF(Tienda_1!$A51="","","Tienda 1") -> Tienda 1 | B51: =IF($A51="","",Tienda_1!B51) -> Muebles | C51: =IF($A51="","",Tienda_1!G51) -> Cúcuta | D51: =IF($A51="","",Tienda_1!F51) -> Rafael Acosta | E51: =IF($A51="","",Tienda_1!I51) -> Tarjeta de crédito | F51: =IF($A51="","",VALUE(RIGHT(Tienda_1!E51,4))) -> 2022 | G51: =IF($A51="","",Tienda_1!C51) -> 630000 | H51: =IF($A51="","",Tienda_1!D51) -> 31700 | I51: =IF($A51="","",Tienda_1!H51) -> 2 | J51: =IF($A51="",0,IF(AND(OR('Cuadro-de-mando'!$B$4="(Todas)",'Cuadro-de-mando'!$B$4=$A51),OR('Cuadro-de-mando'!$E$4="(Todas)",'Cuadro-de-mando'!$E$4=$B51),OR('Cuadro-de-mando'!$H$4="(Todas)",'Cuadro-de-mando'!$H$4=$C51),OR('Cuadro-de-mando'!$K$4="(Todas)",'Cuadro-de-mando'!$K$4=$E51),OR('Cuadro-de-mando'!$N$4="(Todos)",'Cuadro-de-mando'!$N$4=$F51)),1,0)) -> 1
A52: =IF(Tienda_1!$A52="","","Tienda 1") -> Tienda 1 | B52: =IF($A52="","",Tienda_1!B52) -> Electrónicos | C52: =IF($A52="","",Tienda_1!G52) -> Cali | D52: =IF($A52="","",Tienda_1!F52) -> Mariana Herrera | E52: =IF($A52="","",Tienda_1!I52) -> Tarjeta de crédito | F52: =IF($A52="","",VALUE(RIGHT(Tienda_1!E52,4))) -> 2023 | G52: =IF($A52="","",Tienda_1!C52) -> 1130300 | H52: =IF($A52="","",Tienda_1!D52) -> 58400 | I52: =IF($A52="","",Tienda_1!H52) -> 5 | J52: =IF($A52="",0,IF(AND(OR('Cuadro-de-mando'!$B$4="(Todas)",'Cuadro-de-mando'!$B$4=$A52),OR('Cuadro-de-mando'!$E$4="(Todas)",'Cuadro-de-mando'!$E$4=$B52),OR('Cuadro-de-mando'!$H$4="(Todas)",'Cuadro-de-mando'!$H$4=$C52),OR('Cuadro-de-mando'!$K$4="(Todas)",'Cuadro-de-mando'!$K$4=$E52),OR('Cuadro-de-mando'!$N$4="(Todos)",'Cuadro-de-mando'!$N$4=$F52)),1,0)) -> 1
A53: =IF(Tienda_1!$A53="","","Tienda 1") -> Tienda 1 | B53: =IF($A53="","",Tienda_1!B53) -> Muebles | C53: =IF($A53="","",Tienda_1!G53) -> Medellín | D53: =IF($A53="","",Tienda_1!F53) -> Lucas Olivera | E53: =IF($A53="","",Tienda_1!I53) -> Nequi | F53: =IF($A53="","",VALUE(RIGHT(Tienda_1!E53,4))) -> 2021 | G53: =IF($A53="","",Tienda_1!C53) -> 318900 | H53: =IF($A53="","",Tienda_1!D53) -> 17200 | I53: =IF($A53="","",Tienda_1!H53) -> 5 | J53: =IF($A53="",0,IF(AND(OR('Cuadro-de-mando'!$B$4="(Todas)",'Cuadro-de-mando'!$B$4=$A53),OR('Cuadro-de-mando'!$E$4="(Todas)",'Cuadro-de-mando'!$E$4=$B53),OR('Cuadro-de-mando'!$H$4="(Todas)",'Cuadro-de-mando'!$H$4=$C53),OR('Cuadro-de-mando'!$K$4="(Todas)",'Cuadro-de-mando'!$K$4=$E53),OR('Cuadro-de-mando'!$N$4="(Todos)",'Cuadro-de-mando'!$N$4=$F53)),1,0)) -> 1
A54: =IF(Tienda_1!$A54="","","Tienda 1") -> Tienda 1 | B54: =IF($A54="","",Tienda_1!B54) -> Electrónicos | C54: =IF($A54="","",Tienda_1!G54) -> Bogotá | D54: =IF($A54="","",Tienda_1!F54) -> Mariana Herrera | E54: =IF($A54="","",Tienda_1!I54) -> Tarjeta de crédito | F54: =IF($A54="","",VALUE(RIGHT(Tienda_1!E54,4))) -> 2022 | G54: =IF($A54="","",Tienda_1!C54) -> 297000 | H54: =IF($A54="","",Tienda_1!D54) -> 16200 | I54: =IF($A54="","",Tienda_1!H54) -> 4 | J54: =IF($A54="",0,IF(AND(OR('Cuadro-de-mando'!$B$4="(Todas)",'Cuadro-de-mando'!$B$4=$A54),OR('Cuadro-de-mando'!$E$4="(Todas)",'Cuadro-de-mando'!$E$4=$B54),OR('Cuadro-de-mando'!$H$4="(Todas)",'Cuadro-de-mando'!$H$4=$C54),OR('Cuadro-de-mando'!$K$4="(Todas)",'Cuadro-de-mando'!$K$4=$E54),OR('Cuadro-de-mando'!$N$4="(Todos)",'Cuadro-de-mando'!$N$4=$F54)),1,0)) -> 1
A55: =IF(Tienda_1!$A55="","","Tienda 1") -> Tienda 1 | B55: =IF($A55="","",Tienda_1!B55) -> Instrumentos musicales | C55: =IF($A55="","",Tienda_1!G55) -> Cali | D55: =IF($A55="","",Tienda_1!F55) -> Camila Rivera | E55: =IF($A55="","",Tienda_1!I55) -> Tarjeta de crédito | F55: =IF($A55="","",VALUE(RIGHT(Tienda_1!E55,4))) -> 2020 | G55: =IF($A55="","",Tienda_1!C55) -> 402200 | H55: =IF($A55="","",Tienda_1!D55) -> 21800 | I55: =IF($A55="","",Tienda_1!H55) -> 5 | J55: =IF($A55="",0,IF(AND(OR('Cuadro-de-mando'!$B$4="(Todas)",'Cuadro-de-mando'!$B$4=$A55),OR('Cuadro-de-mando'!$E$4="(Todas)",'Cuadro-de-mando'!$E$4=$B55),OR('Cuadro-de-mando'!$H$4="(Todas)",'Cuadro-de-mando'!$H$4=$C55),OR('Cuadro-de-mando'!$K$4="(Todas)",'Cuadro-de-mando'!$K$4=$E55),OR('Cuadro-de-mando'!$N$4="(Todos)",'Cuadro-de-mando'!$N$4=$F55)),1,0)) -> 1
A56: =IF(Tienda_1!$A56="","","Tienda 1") -> Tienda 1 | B56: =IF($A56="","",Tienda_1!B56) -> Juguetes | C56: =IF($A56="","",Tienda_1!G56) -> Medellín | D56: =IF($A56="","",Tienda_1!F56) -> Camila Rivera | E56: =IF($A56="","",Tienda_1!I56) -> Nequi | F56: =IF($A56="","",VALUE(RIGHT(Tienda_1!E56,4))) -> 2021 | G56: =IF($A56="","",Tienda_1!C56) -> 17100 | H56: =IF($A56="","",Tienda_1!D56) -> 0 | I56: =IF($A56="","",Tienda_1!H56) -> 4 | J56: =IF($A56="",0,IF(AND(OR('Cuadro-de-mando'!$B$4="(Todas)",'Cuadro-de-mando'!$B$4=$A56),OR('Cuadro-de-mando'!$E$4="(Todas)",'Cuadro-de-mando'!$E$4=$B56),OR('Cuadro-de-mando'!$H$4="(Todas)",'Cuadro-de-mando'!$H$4=$C56),OR('Cuadro-de-mando'!$K$4="(Todas)",'Cuadro-de-mando'!$K$4=$E56),OR('Cuadro-de-mando'!$N$4="(Todos)",'Cuadro-de-mando'!$N$4=$F56)),1,0)) -> 1
A57: =IF(Tienda_1!$A57="","","Tienda 1") -> Tienda 1 | B57: =IF($A57="","",Tienda_1!B57) -> Artículos para el hogar | C57: =IF($A57="","",Tienda_1!G57) -> Bogotá | D57: =IF($A57="","",Tienda_1!F57) -> Rafael Acosta | E57: =IF($A57="","",Tienda_1!I57) -> Tarjeta de crédito | F57: =IF($A57="","",VALUE(RIGHT(Tienda_1!E57,4))) -> 2020 | G57: =IF($A57="","",Tienda_1!C57) -> 38700 | H57: =IF($A57="","",Tienda_1!D57) -> 2500 | I57: =IF($A57="","",Tienda_1!H57) -> 1 | J57: =IF($A57="",0,IF(AND(OR('Cuadro-de-mando'!$B$4="(Todas)",'Cuadro-de-mando'!$B$4=$A57),OR('Cuadro-de-mando'!$E$4="(Todas)",'Cuadro-de-mando'!$E$4=$B57),OR('Cuadro-de-mando'!$H$4="(Todas)",'Cuadro-de-mando'!$H$4=$C57),OR('Cuadro-de-mando'!$K$4="(Todas)",'Cuadro-de-mando'!$K$4=$E57),OR('Cuadro-de-mando'!$N$4="(Todos)",'Cuadro-de-mando'!$N$4=$F57)),1,0)) -> 1
A58: =IF(Tienda_1!$A58="","","Tienda 1") -> Tienda 1 | B58: =IF($A58="","",Tienda_1!B58) -> Electrónicos | C58: =IF($A58="","",Tienda_1!G58) -> Cúcuta | D58: =IF($A58="","",Tienda_1!F58) -> Maria Alfonso | E58: =IF($A58="","",Tienda_1!I58) -> Tarjeta de crédito | F58: =IF($A58="","",VALUE(RIGHT(Tienda_1!E58,4))) -> 2023 | G58: =IF($A58="","",Tienda_1!C58) -> 605800 | H58: =IF($A58="","",Tienda_1!D58) -> 33500 | I58: =IF($A58="","",Tienda_1!H58) -> 4 | J58: =IF($A58="",0,IF(AND(OR('Cuadro-de-mando'!$B$4="(Todas)",'Cuadro-de-mando'!$B$4=$A58),OR('Cuadro-de-mando'!$E$4="(Todas)",'Cuadro-de-mando'!$E$4=$B58),OR('Cuadro-de-mando'!$H$4="(Todas)",'Cuadro-de-mando'!$H$4=$C58),OR('Cuadro-de-mando'!$K$4="(Todas)",'Cuadro-de-mando'!$K$4=$E58),OR('Cuadro-de-mando'!$N$4="(Todos)",'Cuadro-de-mando'!$N$4=$F58)),1,0)) -> 1
A59: =IF(Tienda_1!$A59="","","Tienda 1") -> Tienda 1 | B59: =IF($A59="","",Tienda_1!B59) -> Electrodomésticos | C59: =IF($A59="","",Tienda_1!G59) -> Bogotá | D59: =IF($A59="","",Tienda_1!F59) -> Juan Fernandez | E59: =IF($A59="","",Tienda_1!I59) -> Tarjeta de crédito | F59: =IF($A59="","",VALUE(RIGHT(Tienda_1!E59,4))) -> 2020 | G59: =IF($A59="","",Tienda_1!C59) -> 1122700 | H59: =IF($A59="","",Tienda_1!D59) -> 60000 | I59: =IF($A59="","",Tienda_1!H59) -> 3 | J59: =IF($A59="",0,IF(AND(OR('Cuadro-de-mando'!$B$4="(Todas)",'Cuadro-de-mando'!$B$4=$A59),OR('Cuadro-de-mando'!$E$4="(Todas)",'Cuadro-de-mando'!$E$4=$B59),OR('Cuadro-de-mando'!$H$4="(Todas)",'Cuadro-de-mando'!$H$4=$C59),OR('Cuadro-de-mando'!$K$4="(Todas)",'Cuadro-de-mando'!$K$4=$E59),OR('Cuadro-de-mando'!$N$4="(Todos)",'Cuadro-de-mando'!$N$4=$F59)),1,0)) -> 1
... A2401: =IF(Tienda_1!$A2401="","","Tienda 1") | B2401: =IF($A2401="","",Tienda_1!B2401) | C2401: =IF($A2401="","",Tienda_1!G2401) | D2401: =IF($A2401="","",Tienda_1!F2401) | E2401: =IF($A2401="","",Tienda_1!I2401) | F2401: =IF($A2401="","",VALUE(RIGHT(Tienda_1!E2401,4))) | G2401: =IF($A2401="","",Tienda_1!C2401) | H2401: =IF($A2401="","",Tienda_1!D2401) | I2401: =IF($A2401="","",Tienda_1!H2401) | J2401: =IF($A2401="",0,IF(AND(OR('Cuadro-de-mando'!$B$4="(Todas)",'Cuadro-de-mando'!$B$4=$A2401),OR('Cuadro-de-mando'!$E$4="(Todas)",'Cuadro-de-mando'!$E$4=$B2401),OR('Cuadro-de-mando'!$H$4="(Todas)",'Cuadro-de-mando'!$H$4=$C2401),OR('Cuadro-de-mando'!$K$4="(Todas)",'Cuadro-de-mando'!$K$4=$E2401),OR('Cuadro-de-mando'!$N$4="(Todos)",'Cuadro-de-mando'!$N$4=$F2401)),1,0)) -> 0
A2402: =IF(Tienda_2!$A2="","","Tienda 2") -> Tienda 2 | B2402: =IF($A2402="","",Tienda_2!B2) -> Muebles | C2402: =IF($A2402="","",Tienda_2!G2) -> Medellín | D2402: =IF($A2402="","",Tienda_2!F2) -> Izabela de León | E2402: =IF($A2402="","",Tienda_2!I2) -> Nequi | F2402: =IF($A2402="","",VALUE(RIGHT(Tienda_2!E2,4))) -> 2021 | G2402: =IF($A2402="","",Tienda_2!C2) -> 283600 | H2402: =IF($A2402="","",Tienda_2!D2) -> 15300 | I2402: =IF($A2402="","",Tienda_2!H2) -> 1 | J2402: =IF($A2402="",0,IF(AND(OR('Cuadro-de-mando'!$B$4="(Todas)",'Cuadro-de-mando'!$B$4=$A2402),OR('Cuadro-de-mando'!$E$4="(Todas)",'Cuadro-de-mando'!$E$4=$B2402),OR('Cuadro-de-mando'!$H$4="(Todas)",'Cuadro-de-mando'!$H$4=$C2402),OR('Cuadro-de-mando'!$K$4="(Todas)",'Cuadro-de-mando'!$K$4=$E2402),OR('Cuadro-de-mando'!$N$4="(Todos)",'Cuadro-de-mando'!$N$4=$F2402)),1,0)) -> 1
A2403: =IF(Tienda_2!$A3="","","Tienda 2") -> Tienda 2 | B2403: =IF($A2403="","",Tienda_2!B3) -> Instrumentos musicales | C2403: =IF($A2403="","",Tienda_2!G3) -> Medellín | D2403: =IF($A2403="","",Tienda_2!F3) -> Blanca Ramirez | E2403: =IF($A2403="","",Tienda_2!I3) -> Tarjeta de crédito | F2403: =IF($A2403="","",VALUE(RIGHT(Tienda_2!E3,4))) -> 2020 | G2403: =IF($A2403="","",Tienda_2!C3) -> 76800 | H2403: =IF($A2403="","",Tienda_2!D3) -> 2300 | I2403: =IF($A2403="","",Tienda_2!H3) -> 3 | J2403: =IF($A2403="",0,IF(AND(OR('Cuadro-de-mando'!$B$4="(Todas)",'Cuadro-de-mando'!$B$4=$A2403),OR('Cuadro-de-mando'!$E$4="(Todas)",'Cuadro-de-mando'!$E$4=$B2403),OR('Cuadro-de-mando'!$H$4="(Todas)",'Cuadro-de-mando'!$H$4=$C2403),OR('Cuadro-de-mando'!$K$4="(Todas)",'Cuadro-de-mando'!$K$4=$E2403),OR('Cuadro-de-mando'!$N$4="(Todos)",'Cuadro-de-mando'!$N$4=$F2403)),1,0)) -> 1
A2404: =IF(Tienda_2!$A4="","","Tienda 2") -> Tienda 2 | B2404: =IF($A2404="","",Tienda_2!B4) -> Muebles | C2404: =IF($A2404="","",Tienda_2!G4) -> Pereira | D2404: =IF($A2404="","",Tienda_2!F4) -> Izabela de León | E2404: =IF($A2404="","",Tienda_2!I4) -> Tarjeta de crédito | F2404: =IF($A2404="","",VALUE(RIGHT(Tienda_2!E4,4))) -> 2021 | G2404: =IF($A2404="","",Tienda_2!C4) -> 443300 | H2404: =IF($A2404="","",Tienda_2!D4) -> 23800 | I2404: =IF($A2404="","",Tienda_2!H4) -> 5 | J2404: =IF($A2404="",0,IF(AND(OR('Cuadro-de-mando'!$B$4="(Todas)",'Cuadro-de-mando'!$B$4=$A2404),OR('Cuadro-de-mando'!$E$4="(Todas)",'Cuadro-de-mando'!$E$4=$B2404),OR('Cuadro-de-mando'!$H$4="(Todas)",'Cuadro-de-mando'!$H$4=$C2404),OR('Cuadro-de-mando'!$K$4="(Todas)",'Cuadro-de-mando'!$K$4=$E2404),OR('Cuadro-de-mando'!$N$4="(Todos)",'Cuadro-de-mando'!$N$4=$F2404)),1,0)) -> 1
A2405: =IF(Tienda_2!$A5="","","Tienda 2") -> Tienda 2 | B2405: =IF($A2405="","",Tienda_2!B5) -> Muebles | C2405: =IF($A2405="","",Tienda_2!G5) -> Cali | D2405: =IF($A2405="","",Tienda_2!F5) -> Maria Alfonso | E2405: =IF($A2405="","",Tienda_2!I5) -> Tarjeta de crédito | F2405: =IF($A2405="","",VALUE(RIGHT(Tienda_2!E5,4))) -> 2022 | G2405: =IF($A2405="","",Tienda_2!C5) -> 906200 | H2405: =IF($A2405="","",Tienda_2!D5) -> 46400 | I2405: =IF($A2405="","",Tienda_2!H5) -> 5 | J2405: =IF($A2405="",0,IF(AND(OR('Cuadro-de-mando'!$B$4="(Todas)",'Cuadro-de-mando'!$B$4=$A2405),OR('Cuadro-de-mando'!$E$4="(Todas)",'Cuadro-de-mando'!$E$4=$B2405),OR('Cuadro-de-mando'!$H$4="(Todas)",'Cuadro-de-mando'!$H$4=$C2405),OR('Cuadro-de-mando'!$K$4="(Todas)",'Cuadro-de-mando'!$K$4=$E2405),OR('Cuadro-de-mando'!$N$4="(Todos)",'Cuadro-de-mando'!$N$4=$F2405)),1,0)) -> 1
A2406: =IF(Tienda_2!$A6="","","Tienda 2") -> Tienda 2 | B2406: =IF($A2406="","",Tienda_2!B6) -> Muebles | C2406: =IF($A2406="","",Tienda_2!G6) -> Bogotá | D2406: =IF($A2406="","",Tienda_2!F6) -> Lucas Olivera | E2406: =IF($A2406="","",Tienda_2!I6) -> Tarjeta de crédito | F2406: =IF($A2406="","",VALUE(RIGHT(Tienda_2!E6,4))) -> 2022 | G2406: =IF($A2406="","",Tienda_2!C6) -> 397800 | H2406: =IF($A2406="","",Tienda_2!D6) -> 19400 | I2406: =IF($A2406="","",Tienda_2!H6) -> 4 | J2406: =IF($A2406="",0,IF(AND(OR('Cuadro-de-mando'!$B$4="(Todas)",'Cuadro-de-mando'!$B$4=$A2406),OR('Cuadro-de-mando'!$E$4="(Todas)",'Cuadro-de-mando'!$E$4=$B2406),OR('Cuadro-de-mando'!$H$4="(Todas)",'Cuadro-de-mando'!$H$4=$C2406),OR('Cuadro-de-mando'!$K$4="(Todas)",'Cuadro-de-mando'!$K$4=$E2406),OR('Cuadro-de-mando'!$N$4="(Todos)",'Cuadro-de-mando'!$N$4=$F2406)),1,0)) -> 1
A2407: =IF(Tienda_2!$A7="","","Tienda 2") -> Tienda 2 | B2407: =IF($A2407="","",Tienda_2!B7) -> Instrumentos musicales | C2407: =IF($A2407="","",Tienda_2!G7) -> Leticia | D2407: =IF($A2407="","",Tienda_2!F7) -> Beatriz Morales | E2407: =IF($A2407="","",Tienda_2!I7) -> Tarjeta de crédito | F2407: =IF($A2407="","",VALUE(RIGHT(Tienda_2!E7,4))) -> 2021 | G2407: =IF($A2407="","",Tienda_2!C7) -> 298400 | H2407: =IF($A2407="","",Tienda_2!D7) -> 16100 | I2407: =IF($A2407="","",Tienda_2!H7) -> 5 | J2407: =IF($A2407="",0,IF(AND(OR('Cuadro-de-mando'!$B$4="(Todas)",'Cuadro-de-mando'!$B$4=$A2407),OR('Cuadro-de-mando'!$E$4="(Todas)",'Cuadro-de-mando'!$E$4=$B2407),OR('Cuadro-de-mando'!$H$4="(Todas)",'Cuadro-de-mando'!$H$4=$C2407),OR('Cuadro-de-mando'!$K$4="(Todas)",'Cuadro-de-mando'!$K$4=$E2407),OR('Cuadro-de-mando'!$N$4="(Todos)",'Cuadro-de-mando'!$N$4=$F2407)),1,0)) -> 1
A2408: =IF(Tienda_2!$A8="","","Tienda 2") -> Tienda 2 | B2408: =IF($A2408="","",Tienda_2!B8) -> Deportes y diversión | C2408: =IF($A2408="","",Tienda_2!G8) -> Bogotá | D2408: =IF($A2408="","",Tienda_2!F8) -> Blanca Ramirez | E2408: =IF($A2408="","",Tienda_2!I8) -> Cupón | F2408: =IF($A2408="","",VALUE(RIGHT(Tienda_2!E8,4))) -> 2020 | G2408: =IF($A2408="","",Tienda_2!C8) -> 105900 | H2408: =IF($A2408="","",Tienda_2!D8) -> 9000 | I2408: =IF($A2408="","",Tienda_2!H8) -> 1 | J2408: =IF($A2408="",0,IF(AND(OR('Cuadro-de-mando'!$B$4="(Todas)",'Cuadro-de-mando'!$B$4=$A2408),OR('Cuadro-de-mando'!$E$4="(Todas)",'Cuadro-de-mando'!$E$4=$B2408),OR('Cuadro-de-mando'!$H$4="(Todas)",'Cuadro-de-mando'!$H$4=$C2408),OR('Cuadro-de-mando'!$K$4="(Todas)",'Cuadro-de-mando'!$K$4=$E2408),OR('Cuadro-de-mando'!$N$4="(Todos)",'Cuadro-de-mando'!$N$4=$F2408)),1,0)) -> 1
A2409: =IF(Tienda_2!$A9="","","Tienda 2") -> Tienda 2 | B2409: =IF($A2409="","",Tienda_2!B9) -> Electrónicos | C2409: =IF($A2409="","",Tienda_2!G9) -> Medellín | D2409: =IF($A2409="","",Tienda_2!F9) -> Juliana Costa | E2409: =IF($A2409="","",Tienda_2!I9) -> Nequi | F2409: =IF($A2409="","",VALUE(RIGHT(Tienda_2!E9,4))) -> 2022 | G2409: =IF($A2409="","",Tienda_2!C9) -> 962600 | H2409: =IF($A2409="","",Tienda_2!D9) -> 49400 | I2409: =IF($A2409="","",Tienda_2!H9) -> 4 | J2409: =IF($A2409="",0,IF(AND(OR('Cuadro-de-mando'!$B$4="(Todas)",'Cuadro-de-mando'!$B$4=$A2409),OR('Cuadro-de-mando'!$E$4="(Todas)",'Cuadro-de-mando'!$E$4=$B2409),OR('Cuadro-de-mando'!$H$4="(Todas)",'Cuadro-de-mando'!$H$4=$C2409),OR('Cuadro-de-mando'!$K$4="(Todas)",'Cuadro-de-mando'!$K$4=$E2409),OR('Cuadro-de-mando'!$N$4="(Todos)",'Cuadro-de-mando'!$N$4=$F2409)),1,0)) -> 1
A2410: =IF(Tienda_2!$A10="","","Tienda 2") -> Tienda 2 | B2410: =IF($A2410="","",Tienda_2!B10) -> Artículos para el hogar | C2410: =IF($A2410="","",Tienda_2!G10) -> Barranquilla | D2410: =IF($A2410="","",Tienda_2!F10) -> Izabela de León | E2410: =IF($A2410="","",Tienda_2!I10) -> Nequi | F2410: =IF($A2410="","",VALUE(RIGHT(Tienda_2!E10,4))) -> 2022 | G2410: =IF($A2410="","",Tienda_2!C10) -> 82800 | H2410: =IF($A2410="","",Tienda_2!D10) -> 4800 | I2410: =IF($A2410="","",Tienda_2!H10) -> 5 | J2410: =IF($A2410="",0,IF(AND(OR('Cuadro-de-mando'!$B$4="(Todas)",'Cuadro-de-mando'!$B$4=$A2410),OR('Cuadro-de-mando'!$E$4="(Todas)",'Cuadro-de-mando'!$E$4=$B2410),OR('Cuadro-de-mando'!$H$4="(Todas)",'Cuadro-de-mando'!$H$4=$C2410),OR('Cuadro-de-mando'!$K$4="(Todas)",'Cuadro-de-mando'!$K$4=$E2410),OR('Cuadro-de-mando'!$N$4="(Todos)",'Cuadro-de-mando'!$N$4=$F2410)),1,0)) -> 1
A2411: =IF(Tienda_2!$A11="","","Tienda 2") -> Tienda 2 | B2411: =IF($A2411="","",Tienda_2!B11) -> Juguetes | C2411: =IF($A2411="","",Tienda_2!G11) -> Bogotá | D2411: =IF($A2411="","",Tienda_2!F11) -> Camila Rivera | E2411: =IF($A2411="","",Tienda_2!I11) -> Tarjeta de crédito | F2411: =IF($A2411="","",VALUE(RIGHT(Tienda_2!E11,4))) -> 2021 | G2411: =IF($A2411="","",Tienda_2!C11) -> 9100 | H2411: =IF($A2411="","",Tienda_2!D11) -> 3800 | I2411: =IF($A2411="","",Tienda_2!H11) -> 5 | J2411: =IF($A2411="",0,IF(AND(OR('Cuadro-de-mando'!$B$4="(Todas)",'Cuadro-de-mando'!$B$4=$A2411),OR('Cuadro-de-mando'!$E$4="(Todas)",'Cuadro-de-mando'!$E$4=$B2411),OR('Cuadro-de-mando'!$H$4="(Todas)",'Cuadro-de-mando'!$H$4=$C2411),OR('Cuadro-de-mando'!$K$4="(Todas)",'Cuadro-de-mando'!$K$4=$E2411),OR('Cuadro-de-mando'!$N$4="(Todos)",'Cuadro-de-mando'!$N$4=$F2411)),1,0)) -> 1
A2412: =IF(Tienda_2!$A12="","","Tienda 2") -> Tienda 2 | B2412: =IF($A2412="","",Tienda_2!B12) -> Deportes y diversión | C2412: =IF($A2412="","",Tienda_2!G12) -> Medellín | D2412: =IF($A2412="","",Tienda_2!F12) -> Izabela de León | E2412: =IF($A2412="","",Tienda_2!I12) -> Tarjeta de crédito | F2412: =IF($A2412="","",VALUE(RIGHT(Tienda_2!E12,4))) -> 2020 | G2412: =IF($A2412="","",Tienda_2!C12) -> 86800 | H2412: =IF($A2412="","",Tienda_2!D12) -> 9300 | I2412: =IF($A2412="","",Tienda_2!H12) -> 5 | J2412: =IF($A2412="",0,IF(AND(OR('Cuadro-de-mando'!$B$4="(Todas)",'Cuadro-de-mando'!$B$4=$A2412),OR('Cuadro-de-mando'!$E$4="(Todas)",'Cuadro-de-mando'!$E$4=$B2412),OR('Cuadro-de-mando'!$H$4="(Todas)",'Cuadro-de-mando'!$H$4=$C2412),OR('Cuadro-de-mando'!$K$4="(Todas)",'Cuadro-de-mando'!$K$4=$E2412),OR('Cuadro-de-mando'!$N$4="(Todos)",'Cuadro-de-mando'!$N$4=$F2412)),1,0)) -> 1
A2413: =IF(Tienda_2!$A13="","","Tienda 2") -> Tienda 2 | B2413: =IF($A2413="","",Tienda_2!B13) -> Electrodomésticos | C2413: =IF($A2413="","",Tienda_2!G13) -> Barranquilla | D2413: =IF($A2413="","",Tienda_2!F13) -> Rafael Acosta | E2413: =IF($A2413="","",Tienda_2!I13) -> Tarjeta de crédito | F2413: =IF($A2413="","",VALUE(RIGHT(Tienda_2!E13,4))) -> 2021 | G2413: =IF($A2413="","",Tienda_2!C13) -> 878900 | H2413: =IF($A2413="","",Tienda_2!D13) -> 47000 | I2413: =IF($A2413="","",Tienda_2!H13) -> 1 | J2413: =IF($A2413="",0,IF(AND(OR('Cuadro-de-mando'!$B$4="(Todas)",'Cuadro-de-mando'!$B$4=$A2413),OR('Cuadro-de-mando'!$E$4="(Todas)",'Cuadro-de-mando'!$E$4=$B2413),OR('Cuadro-de-mando'!$H$4="(Todas)",'Cuadro-de-mando'!$H$4=$C2413),OR('Cuadro-de-mando'!$K$4="(Todas)",'Cuadro-de-mando'!$K$4=$E2413),OR('Cuadro-de-mando'!$N$4="(Todos)",'Cuadro-de-mando'!$N$4=$F2413)),1,0)) -> 1
... A4801: =IF(Tienda_2!$A2401="","","Tienda 2") | B4801: =IF($A4801="","",Tienda_2!B2401) | C4801: =IF($A4801="","",Tienda_2!G2401) | D4801: =IF($A4801="","",Tienda_2!F2401) | E4801: =IF($A4801="","",Tienda_2!I2401) | F4801: =IF($A4801="","",VALUE(RIGHT(Tienda_2!E2401,4))) | G4801: =IF($A4801="","",Tienda_2!C2401) | H4801: =IF($A4801="","",Tienda_2!D2401) | I4801: =IF($A4801="","",Tienda_2!H2401) | J4801: =IF($A4801="",0,IF(AND(OR('Cuadro-de-mando'!$B$4="(Todas)",'Cuadro-de-mando'!$B$4=$A4801),OR('Cuadro-de-mando'!$E$4="(Todas)",'Cuadro-de-mando'!$E$4=$B4801),OR('Cuadro-de-mando'!$H$4="(Todas)",'Cuadro-de-mando'!$H$4=$C4801),OR('Cuadro-de-mando'!$K$4="(Todas)",'Cuadro-de-mando'!$K$4=$E4801),OR('Cuadro-de-mando'!$N$4="(Todos)",'Cuadro-de-mando'!$N$4=$F4801)),1,0)) -> 0
A4802: =IF(Tienda_3!$A2="","","Tienda 3") -> Tienda 3 | B4802: =IF($A4802="","",Tienda_3!B2) -> Electrodomésticos | C4802: =IF($A4802="","",Tienda_3!G2) -> Santa Marta | D4802: =IF($A4802="","",Tienda_3!F2) -> Camila Rivera | E4802: =IF($A4802="","",Tienda_3!I2) -> Tarjeta de crédito | F4802: =IF($A4802="","",VALUE(RIGHT(Tienda_3!E2,4))) -> 2021 | G4802: =IF($A4802="","",Tienda_3!C2) -> 1285100 | H4802: =IF($A4802="","",Tienda_3!D2) -> 66600 | I4802: =IF($A4802="","",Tienda_3!H2) -> 4 | J4802: =IF($A4802="",0,IF(AND(OR('Cuadro-de-mando'!$B$4="(Todas)",'Cuadro-de-mando'!$B$4=$A4802),OR('Cuadro-de-mando'!$E$4="(Todas)",'Cuadro-de-mando'!$E$4=$B4802),OR('Cuadro-de-mando'!$H$4="(Todas)",'Cuadro-de-mando'!$H$4=$C4802),OR('Cuadro-de-mando'!$K$4="(Todas)",'Cuadro-de-mando'!$K$4=$E4802),OR('Cuadro-de-mando'!$N$4="(Todos)",'Cuadro-de-mando'!$N$4=$F4802)),1,0)) -> 1
A4803: =IF(Tienda_3!$A3="","","Tienda 3") -> Tienda 3 | B4803: =IF($A4803="","",Tienda_3!B3) -> Muebles | C4803: =IF($A4803="","",Tienda_3!G3) -> Cali | D4803: =IF($A4803="","",Tienda_3!F3) -> Maria Alfonso | E4803: =IF($A4803="","",Tienda_3!I3) -> Tarjeta de crédito | F4803: =IF($A4803="","",VALUE(RIGHT(Tienda_3!E3,4))) -> 2021 | G4803: =IF($A4803="","",Tienda_3!C3) -> 290100 | H4803: =IF($A4803="","",Tienda_3!D3) -> 13600 | I4803: =IF($A4803="","",Tienda_3!H3) -> 3 | J4803: =IF($A4803="",0,IF(AND(OR('Cuadro-de-mando'!$B$4="(Todas)",'Cuadro-de-mando'!$B$4=$A4803),OR('Cuadro-de-mando'!$E$4="(Todas)",'Cuadro-de-mando'!$E$4=$B4803),OR('Cuadro-de-mando'!$H$4="(Todas)",'Cuadro-de-mando'!$H$4=$C4803),OR('Cuadro-de-mando'!$K$4="(Todas)",'Cuadro-de-mando'!$K$4=$E4803),OR('Cuadro-de-mando'!$N$4="(Todos)",'Cuadro-de-mando'!$N$4=$F4803)),1,0)) -> 1
A4804: =IF(Tienda_3!$A4="","","Tienda 3") -> Tienda 3 | B4804: =IF($A4804="","",Tienda_3!B4) -> Instrumentos musicales | C4804: =IF($A4804="","",Tienda_3!G4) -> Bogotá | D4804: =IF($A4804="","",Tienda_3!F4) -> Lucas Olivera | E4804: =IF($A4804="","",Tienda_3!I4) -> Tarjeta de crédito | F4804: =IF($A4804="","",VALUE(RIGHT(Tienda_3!E4,4))) -> 2023 | G4804: =IF($A4804="","",Tienda_3!C4) -> 303500 | H4804: =IF($A4804="","",Tienda_3!D4) -> 17400 | I4804: =IF($A4804="","",Tienda_3!H4) -> 5 | J4804: =IF($A4804="",0,IF(AND(OR('Cuadro-de-mando'!$B$4="(Todas)",'Cuadro-de-mando'!$B$4=$A4804),OR('Cuadro-de-mando'!$E$4="(Todas)",'Cuadro-de-mando'!$E$4=$B4804),OR('Cuadro-de-mando'!$H$4="(Todas)",'Cuadro-de-mando'!$H$4=$C4804),OR('Cuadro-de-mando'!$K$4="(Todas)",'Cuadro-de-mando'!$K$4=$E4804),OR('Cuadro-de-mando'!$N$4="(Todos)",'Cuadro-de-mando'!$N$4=$F4804)),1,0)) -> 1
A4805: =IF(Tienda_3!$A5="","","Tienda 3") -> Tienda 3 | B4805: =IF($A4805="","",Tienda_3!B5) -> Deportes y diversión | C4805: =IF($A4805="","",Tienda_3!G5) -> Barranquilla | D4805: =IF($A4805="","",Tienda_3!F5) -> Pedro Gomez | E4805: =IF($A4805="","",Tienda_3!I5) -> Tarjeta de crédito | F4805: =IF($A4805="","",VALUE(RIGHT(Tienda_3!E5,4))) -> 2022 | G4805: =IF($A4805="","",Tienda_3!C5) -> 58800 | H4805: =IF($A4805="","",Tienda_3!D5) -> 3300 | I4805: =IF($A4805="","",Tienda_3!H5) -> 4 | J4805: =IF($A4805="",0,IF(AND(OR('Cuadro-de-mando'!$B$4="(Todas)",'Cuadro-de-mando'!$B$4=$A4805),OR('Cuadro-de-mando'!$E$4="(Todas)",'Cuadro-de-mando'!$E$4=$B4805),OR('Cuadro-de-mando'!$H$4="(Todas)",'Cuadro-de-mando'!$H$4=$C4805),OR('Cuadro-de-mando'!$K$4="(Todas)",'Cuadro-de-mando'!$K$4=$E4805),OR('Cuadro-de-mando'!$N$4="(Todos)",'Cuadro-de-mando'!$N$4=$F4805)),1,0)) -> 1
A4806: =IF(Tienda_3!$A6="","","Tienda 3") -> Tienda 3 | B4806: =IF($A4806="","",Tienda_3!B6) -> Muebles | C4806: =IF($A4806="","",Tienda_3!G6) -> Bogotá | D4806: =IF($A4806="","",Tienda_3!F6) -> Blanca Ramirez | E4806: =IF($A4806="","",Tienda_3!I6) -> Tarjeta de crédito | F4806: =IF($A4806="","",VALUE(RIGHT(Tienda_3!E6,4))) -> 2022 | G4806: =IF($A4806="","",Tienda_3!C6) -> 521100 | H4806: =IF($A4806="","",Tienda_3!D6) -> 25900 | I4806: =IF($A4806="","",Tienda_3!H6) -> 1 | J4806: =IF($A4806="",0,IF(AND(OR('Cuadro-de-mando'!$B$4="(Todas)",'Cuadro-de-mando'!$B$4=$A4806),OR('Cuadro-de-mando'!$E$4="(Todas)",'Cuadro-de-mando'!$E$4=$B4806),OR('Cuadro-de-mando'!$H$4="(Todas)",'Cuadro-de-mando'!$H$4=$C4806),OR('Cuadro-de-mando'!$K$4="(Todas)",'Cuadro-de-mando'!$K$4=$E4806),OR('Cuadro-de-mando'!$N$4="(Todos)",'Cuadro-de-mando'!$N$4=$F4806)),1,0)) -> 1
A4807: =IF(Tienda_3!$A7="","","Tienda 3") -> Tienda 3 | B4807: =IF($A4807="","",Tienda_3!B7) -> Electrónicos | C4807: =IF($A4807="","",Tienda_3!G7) -> Medellín | D4807: =IF($A4807="","",Tienda_3!F7) -> Mariana Herrera | E4807: =IF($A4807="","",Tienda_3!I7) -> Tarjeta de crédito | F4807: =IF($A4807="","",VALUE(RIGHT(Tienda_3!E7,4))) -> 2022 | G4807: =IF($A4807="","",Tienda_3!C7) -> 230700 | H4807: =IF($A4807="","",Tienda_3!D7) -> 10500 | I4807: =IF($A4807="","",Tienda_3!H7) -> 5 | J4807: =IF($A4807="",0,IF(AND(OR('Cuadro-de-mando'!$B$4="(Todas)",'Cuadro-de-mando'!$B$4=$A4807),OR('Cuadro-de-mando'!$E$4="(Todas)",'Cuadro-de-mando'!$E$4=$B4807),OR('Cuadro-de-mando'!$H$4="(Todas)",'Cuadro-de-mando'!$H$4=$C4807),OR('Cuadro-de-mando'!$K$4="(Todas)",'Cuadro-de-mando'!$K$4=$E4807),OR('Cuadro-de-mando'!$N$4="(Todos)",'Cuadro-de-mando'!$N$4=$F4807)),1,0)) -> 1
A4808: =IF(Tienda_3!$A8="","","Tienda 3") -> Tienda 3 | B4808: =IF($A4808="","",Tienda_3!B8) -> Juguetes | C4808: =IF($A4808="","",Tienda_3!G8) -> Bogotá | D4808: =IF($A4808="","",Tienda_3!F8) -> Ángel Rodriguez | E4808: =IF($A4808="","",Tienda_3!I8) -> Nequi | F4808: =IF($A4808="","",VALUE(RIGHT(Tienda_3!E8,4))) -> 2020 | G4808: =IF($A4808="","",Tienda_3!C8) -> 55700 | H4808: =IF($A4808="","",Tienda_3!D8) -> 3200 | I4808: =IF($A4808="","",Tienda_3!H8) -> 2 | J4808: =IF($A4808="",0,IF(AND(OR('Cuadro-de-mando'!$B$4="(Todas)",'Cuadro-de-mando'!$B$4=$A4808),OR('Cuadro-de-mando'!$E$4="(Todas)",'Cuadro-de-mando'!$E$4=$B4808),OR('Cuadro-de-mando'!$H$4="(Todas)",'Cuadro-de-mando'!$H$4=$C4808),OR('Cuadro-de-mando'!$K$4="(Todas)",'Cuadro-de-mando'!$K$4=$E4808),OR('Cuadro-de-mando'!$N$4="(Todos)",'Cuadro-de-mando'!$N$4=$F4808)),1,0)) -> 1
A4809: =IF(Tienda_3!$A9="","","Tienda 3") -> Tienda 3 | B4809: =IF($A4809="","",Tienda_3!B9) -> Muebles | C4809: =IF($A4809="","",Tienda_3!G9) -> Bogotá | D4809: =IF($A4809="","",Tienda_3!F9) -> Santiago Silva | E4809: =IF($A4809="","",Tienda_3!I9) -> Nequi | F4809: =IF($A4809="","",VALUE(RIGHT(Tienda_3!E9,4))) -> 2022 | G4809: =IF($A4809="","",Tienda_3!C9) -> 464600 | H4809: =IF($A4809="","",Tienda_3!D9) -> 25100 | I4809: =IF($A4809="","",Tienda_3!H9) -> 5 | J4809: =IF($A4809="",0,IF(AND(OR('Cuadro-de-mando'!$B$4="(Todas)",'Cuadro-de-mando'!$B$4=$A4809),OR('Cuadro-de-mando'!$E$4="(Todas)",'Cuadro-de-mando'!$E$4=$B4809),OR('Cuadro-de-mando'!$H$4="(Todas)",'Cuadro-de-mando'!$H$4=$C4809),OR('Cuadro-de-mando'!$K$4="(Todas)",'Cuadro-de-mando'!$K$4=$E4809),OR('Cuadro-de-mando'!$N$4="(Todos)",'Cuadro-de-mando'!$N$4=$F4809)),1,0)) -> 1
A4810: =IF(Tienda_3!$A10="","","Tienda 3") -> Tienda 3 | B4810: =IF($A4810="","",Tienda_3!B10) -> Instrumentos musicales | C4810: =IF($A4810="","",Tienda_3!G10) -> Medellín | D4810: =IF($A4810="","",Tienda_3!F10) -> Maria Alfonso | E4810: =IF($A4810="","",Tienda_3!I10) -> Tarjeta de crédito | F4810: =IF($A4810="","",VALUE(RIGHT(Tienda_3!E10,4))) -> 2021 | G4810: =IF($A4810="","",Tienda_3!C10) -> 43500 | H4810: =IF($A4810="","",Tienda_3!D10) -> 2700 | I4810: =IF($A4810="","",Tienda_3!H10) -> 5 | J4810: =IF($A4810="",0,IF(AND(OR('Cuadro-de-mando'!$B$4="(Todas)",'Cuadro-de-mando'!$B$4=$A4810),OR('Cuadro-de-mando'!$E$4="(Todas)",'Cuadro-de-mando'!$E$4=$B4810),OR('Cuadro-de-mando'!$H$4="(Todas)",'Cuadro-de-mando'!$H$4=$C4810),OR('Cuadro-de-mando'!$K$4="(Todas)",'Cuadro-de-mando'!$K$4=$E4810),OR('Cuadro-de-mando'!$N$4="(Todos)",'Cuadro-de-mando'!$N$4=$F4810)),1,0)) -> 1
A4811: =IF(Tienda_3!$A11="","","Tienda 3") -> Tienda 3 | B4811: =IF($A4811="","",Tienda_3!B11) -> Artículos para el hogar | C4811: =IF($A4811="","",Tienda_3!G11) -> Medellín | D4811: =IF($A4811="","",Tienda_3!F11) -> Felipe Santos | E4811: =IF($A4811="","",Tienda_3!I11) -> Nequi | F4811: =IF($A4811="","",VALUE(RIGHT(Tienda_3!E11,4))) -> 2022 | G4811: =IF($A4811="","",Tienda_3!C11) -> 33500 | H4811: =IF($A4811="","",Tienda_3!D11) -> 0 | I4811: =IF($A4811="","",Tienda_3!H11) -> 5 | J4811: =IF($A4811="",0,IF(AND(OR('Cuadro-de-mando'!$B$4="(Todas)",'Cuadro-de-mando'!$B$4=$A4811),OR('Cuadro-de-mando'!$E$4="(Todas)",'Cuadro-de-mando'!$E$4=$B4811),OR('Cuadro-de-mando'!$H$4="(Todas)",'Cuadro-de-mando'!$H$4=$C4811),OR('Cuadro-de-mando'!$K$4="(Todas)",'Cuadro-de-mando'!$K$4=$E4811),OR('Cuadro-de-mando'!$N$4="(Todos)",'Cuadro-de-mando'!$N$4=$F4811)),1,0)) -> 1
A4812: =IF(Tienda_3!$A12="","","Tienda 3") -> Tienda 3 | B4812: =IF($A4812="","",Tienda_3!B12) -> Juguetes | C4812: =IF($A4812="","",Tienda_3!G12) -> Neiva | D4812: =IF($A4812="","",Tienda_3!F12) -> Beatriz Morales | E4812: =IF($A4812="","",Tienda_3!I12) -> Nequi | F4812: =IF($A4812="","",VALUE(RIGHT(Tienda_3!E12,4))) -> 2021 | G4812: =IF($A4812="","",Tienda_3!C12) -> 45500 | H4812: =IF($A4812="","",Tienda_3!D12) -> 0 | I4812: =IF($A4812="","",Tienda_3!H12) -> 5 | J4812: =IF($A4812="",0,IF(AND(OR('Cuadro-de-mando'!$B$4="(Todas)",'Cuadro-de-mando'!$B$4=$A4812),OR('Cuadro-de-mando'!$E$4="(Todas)",'Cuadro-de-mando'!$E$4=$B4812),OR('Cuadro-de-mando'!$H$4="(Todas)",'Cuadro-de-mando'!$H$4=$C4812),OR('Cuadro-de-mando'!$K$4="(Todas)",'Cuadro-de-mando'!$K$4=$E4812),OR('Cuadro-de-mando'!$N$4="(Todos)",'Cuadro-de-mando'!$N$4=$F4812)),1,0)) -> 1
A4813: =IF(Tienda_3!$A13="","","Tienda 3") -> Tienda 3 | B4813: =IF($A4813="","",Tienda_3!B13) -> Muebles | C4813: =IF($A4813="","",Tienda_3!G13) -> Cúcuta | D4813: =IF($A4813="","",Tienda_3!F13) -> Felipe Santos | E4813: =IF($A4813="","",Tienda_3!I13) -> Tarjeta de crédito | F4813: =IF($A4813="","",VALUE(RIGHT(Tienda_3!E13,4))) -> 2022 | G4813: =IF($A4813="","",Tienda_3!C13) -> 435200 | H4813: =IF($A4813="","",Tienda_3!D13) -> 21400 | I4813: =IF($A4813="","",Tienda_3!H13) -> 2 | J4813: =IF($A4813="",0,IF(AND(OR('Cuadro-de-mando'!$B$4="(Todas)",'Cuadro-de-mando'!$B$4=$A4813),OR('Cuadro-de-mando'!$E$4="(Todas)",'Cuadro-de-mando'!$E$4=$B4813),OR('Cuadro-de-mando'!$H$4="(Todas)",'Cuadro-de-mando'!$H$4=$C4813),OR('Cuadro-de-mando'!$K$4="(Todas)",'Cuadro-de-mando'!$K$4=$E4813),OR('Cuadro-de-mando'!$N$4="(Todos)",'Cuadro-de-mando'!$N$4=$F4813)),1,0)) -> 1
... A7201: =IF(Tienda_3!$A2401="","","Tienda 3") | B7201: =IF($A7201="","",Tienda_3!B2401) | C7201: =IF($A7201="","",Tienda_3!G2401) | D7201: =IF($A7201="","",Tienda_3!F2401) | E7201: =IF($A7201="","",Tienda_3!I2401) | F7201: =IF($A7201="","",VALUE(RIGHT(Tienda_3!E2401,4))) | G7201: =IF($A7201="","",Tienda_3!C2401) | H7201: =IF($A7201="","",Tienda_3!D2401) | I7201: =IF($A7201="","",Tienda_3!H2401) | J7201: =IF($A7201="",0,IF(AND(OR('Cuadro-de-mando'!$B$4="(Todas)",'Cuadro-de-mando'!$B$4=$A7201),OR('Cuadro-de-mando'!$E$4="(Todas)",'Cuadro-de-mando'!$E$4=$B7201),OR('Cuadro-de-mando'!$H$4="(Todas)",'Cuadro-de-mando'!$H$4=$C7201),OR('Cuadro-de-mando'!$K$4="(Todas)",'Cuadro-de-mando'!$K$4=$E7201),OR('Cuadro-de-mando'!$N$4="(Todos)",'Cuadro-de-mando'!$N$4=$F7201)),1,0)) -> 0
A7202: =IF(Tienda_4!$A2="","","Tienda 4") -> Tienda 4 | B7202: =IF($A7202="","",Tienda_4!B2) -> Electrodomésticos | C7202: =IF($A7202="","",Tienda_4!G2) -> Bogotá | D7202: =IF($A7202="","",Tienda_4!F2) -> Rafael Acosta | E7202: =IF($A7202="","",Tienda_4!I2) -> Tarjeta de crédito | F7202: =IF($A7202="","",VALUE(RIGHT(Tienda_4!E2,4))) -> 2022 | G7202: =IF($A7202="","",Tienda_4!C2) -> 1084800 | H7202: =IF($A7202="","",Tienda_4!D2) -> 56000 | I7202: =IF($A7202="","",Tienda_4!H2) -> 4 | J7202: =IF($A7202="",0,IF(AND(OR('Cuadro-de-mando'!$B$4="(Todas)",'Cuadro-de-mando'!$B$4=$A7202),OR('Cuadro-de-mando'!$E$4="(Todas)",'Cuadro-de-mando'!$E$4=$B7202),OR('Cuadro-de-mando'!$H$4="(Todas)",'Cuadro-de-mando'!$H$4=$C7202),OR('Cuadro-de-mando'!$K$4="(Todas)",'Cuadro-de-mando'!$K$4=$E7202),OR('Cuadro-de-mando'!$N$4="(Todos)",'Cuadro-de-mando'!$N$4=$F7202)),1,0)) -> 1
A7203: =IF(Tienda_4!$A3="","","Tienda 4") -> Tienda 4 | B7203: =IF($A7203="","",Tienda_4!B3) -> Muebles | C7203: =IF($A7203="","",Tienda_4!G3) -> Cúcuta | D7203: =IF($A7203="","",Tienda_4!F3) -> Izabela de León | E7203: =IF($A7203="","",Tienda_4!I3) -> Tarjeta de crédito | F7203: =IF($A7203="","",VALUE(RIGHT(Tienda_4!E3,4))) -> 2020 | G7203: =IF($A7203="","",Tienda_4!C3) -> 473800 | H7203: =IF($A7203="","",Tienda_4!D3) -> 25400 | I7203: =IF($A7203="","",Tienda_4!H3) -> 5 | J7203: =IF($A7203="",0,IF(AND(OR('Cuadro-de-mando'!$B$4="(Todas)",'Cuadro-de-mando'!$B$4=$A7203),OR('Cuadro-de-mando'!$E$4="(Todas)",'Cuadro-de-mando'!$E$4=$B7203),OR('Cuadro-de-mando'!$H$4="(Todas)",'Cuadro-de-mando'!$H$4=$C7203),OR('Cuadro-de-mando'!$K$4="(Todas)",'Cuadro-de-mando'!$K$4=$E7203),OR('Cuadro-de-mando'!$N$4="(Todos)",'Cuadro-de-mando'!$N$4=$F7203)),1,0)) -> 1
A7204: =IF(Tienda_4!$A4="","","Tienda 4") -> Tienda 4 | B7204: =IF($A7204="","",Tienda_4!B4) -> Deportes y diversión | C7204: =IF($A7204="","",Tienda_4!G4) -> Medellín | D7204: =IF($A7204="","",Tienda_4!F4) -> Maria Alfonso | E7204: =IF($A7204="","",Tienda_4!I4) -> Nequi | F7204: =IF($A7204="","",VALUE(RIGHT(Tienda_4!E4,4))) -> 2022 | G7204: =IF($A7204="","",Tienda_4!C4) -> 23700 | H7204: =IF($A7204="","",Tienda_4!D4) -> 0 | I7204: =IF($A7204="","",Tienda_4!H4) -> 5 | J7204: =IF($A7204="",0,IF(AND(OR('Cuadro-de-mando'!$B$4="(Todas)",'Cuadro-de-mando'!$B$4=$A7204),OR('Cuadro-de-mando'!$E$4="(Todas)",'Cuadro-de-mando'!$E$4=$B7204),OR('Cuadro-de-mando'!$H$4="(Todas)",'Cuadro-de-mando'!$H$4=$C7204),OR('Cuadro-de-mando'!$K$4="(Todas)",'Cuadro-de-mando'!$K$4=$E7204),OR('Cuadro-de-mando'!$N$4="(Todos)",'Cuadro-de-mando'!$N$4=$F7204)),1,0)) -> 1
A7205: =IF(Tienda_4!$A5="","","Tienda 4") -> Tienda 4 | B7205: =IF($A7205="","",Tienda_4!B5) -> Libros | C7205: =IF($A7205="","",Tienda_4!G5) -> Medellín | D7205: =IF($A7205="","",Tienda_4!F5) -> Lucas Olivera | E7205: =IF($A7205="","",Tienda_4!I5) -> Nequi | F7205: =IF($A7205="","",VALUE(RIGHT(Tienda_4!E5,4))) -> 2021 | G7205: =IF($A7205="","",Tienda_4!C5) -> 57700 | H7205: =IF($A7205="","",Tienda_4!D5) -> 1300 | I7205: =IF($A7205="","",Tienda_4!H5) -> 3 | J7205: =IF($A7205="",0,IF(AND(OR('Cuadro-de-mando'!$B$4="(Todas)",'Cuadro-de-mando'!$B$4=$A7205),OR('Cuadro-de-mando'!$E$4="(Todas)",'Cuadro-de-mando'!$E$4=$B7205),OR('Cuadro-de-mando'!$H$4="(Todas)",'Cuadro-de-mando'!$H$4=$C7205),OR('Cuadro-de-mando'!$K$4="(Todas)",'Cuadro-de-mando'!$K$4=$E7205),OR('Cuadro-de-mando'!$N$4="(Todos)",'Cuadro-de-mando'!$N$4=$F7205)),1,0)) -> 1
A7206: =IF(Tienda_4!$A6="","","Tienda 4") -> Tienda 4 | B7206: =IF($A7206="","",Tienda_4!B6) -> Electrónicos | C7206: =IF($A7206="","",Tienda_4!G6) -> Bogotá | D7206: =IF($A7206="","",Tienda_4!F6) -> Blanca Ramirez | E7206: =IF($A7206="","",Tienda_4!I6) -> Tarjeta de crédito | F7206: =IF($A7206="","",VALUE(RIGHT(Tienda_4!E6,4))) -> 2022 | G7206: =IF($A7206="","",Tienda_4!C6) -> 138900 | H7206: =IF($A7206="","",Tienda_4!D6) -> 5600 | I7206: =IF($A7206="","",Tienda_4!H6) -> 4 | J7206: =IF($A7206="",0,IF(AND(OR('Cuadro-de-mando'!$B$4="(Todas)",'Cuadro-de-mando'!$B$4=$A7206),OR('Cuadro-de-mando'!$E$4="(Todas)",'Cuadro-de-mando'!$E$4=$B7206),OR('Cuadro-de-mando'!$H$4="(Todas)",'Cuadro-de-mando'!$H$4=$C7206),OR('Cuadro-de-mando'!$K$4="(Todas)",'Cuadro-de-mando'!$K$4=$E7206),OR('Cuadro-de-mando'!$N$4="(Todos)",'Cuadro-de-mando'!$N$4=$F7206)),1,0)) -> 1
A7207: =IF(Tienda_4!$A7="","","Tienda 4") -> Tienda 4 | B7207: =IF($A7207="","",Tienda_4!B7) -> Electrodomésticos | C7207: =IF($A7207="","",Tienda_4!G7) -> Cartagena | D7207: =IF($A7207="","",Tienda_4!F7) -> Beatriz Morales | E7207: =IF($A7207="","",Tienda_4!I7) -> Tarjeta de crédito | F7207: =IF($A7207="","",VALUE(RIGHT(Tienda_4!E7,4))) -> 2020 | G7207: =IF($A7207="","",Tienda_4!C7) -> 1591900 | H7207: =IF($A7207="","",Tienda_4!D7) -> 83000 | I7207: =IF($A7207="","",Tienda_4!H7) -> 1 | J7207: =IF($A7207="",0,IF(AND(OR('Cuadro-de-mando'!$B$4="(Todas)",'Cuadro-de-mando'!$B$4=$A7207),OR('Cuadro-de-mando'!$E$4="(Todas)",'Cuadro-de-mando'!$E$4=$B7207),OR('Cuadro-de-mando'!$H$4="(Todas)",'Cuadro-de-mando'!$H$4=$C7207),OR('Cuadro-de-mando'!$K$4="(Todas)",'Cuadro-de-mando'!$K$4=$E7207),OR('Cuadro-de-mando'!$N$4="(Todos)",'Cuadro-de-mando'!$N$4=$F7207)),1,0)) -> 1
A7208: =IF(Tienda_4!$A8="","","Tienda 4") -> Tienda 4 | B7208: =IF($A7208="","",Tienda_4!B8) -> Instrumentos musicales | C7208: =IF($A7208="","",Tienda_4!G8) -> Medellín | D7208: =IF($A7208="","",Tienda_4!F8) -> Izabela de León | E7208: =IF($A7208="","",Tienda_4!I8) -> Tarjeta de crédito | F7208: =IF($A7208="","",VALUE(RIGHT(Tienda_4!E8,4))) -> 2021 | G7208: =IF($A7208="","",Tienda_4!C8) -> 626200 | H7208: =IF($A7208="","",Tienda_4!D8) -> 38000 | I7208: =IF($A7208="","",Tienda_4!H8) -> 5 | J7208: =IF($A7208="",0,IF(AND(OR('Cuadro-de-mando'!$B$4="(Todas)",'Cuadro-de-mando'!$B$4=$A7208),OR('Cuadro-de-mando'!$E$4="(Todas)",'Cuadro-de-mando'!$E$4=$B7208),OR('Cuadro-de-mando'!$H$4="(Todas)",'Cuadro-de-mando'!$H$4=$C7208),OR('Cuadro-de-mando'!$K$4="(Todas)",'Cuadro-de-mando'!$K$4=$E7208),OR('Cuadro-de-mando'!$N$4="(Todos)",'Cuadro-de-mando'!$N$4=$F7208)),1,0)) -> 1
A7209: =IF(Tienda_4!$A9="","","Tienda 4") -> Tienda 4 | B7209: =IF($A7209="","",Tienda_4!B9) -> Electrónicos | C7209: =IF($A7209="","",Tienda_4!G9) -> Medellín | D7209: =IF($A7209="","",Tienda_4!F9) -> Santiago Silva | E7209: =IF($A7209="","",Tienda_4!I9) -> Tarjeta de crédito | F7209: =IF($A7209="","",VALUE(RIGHT(Tienda_4!E9,4))) -> 2022 | G7209: =IF($A7209="","",Tienda_4!C9) -> 94500 | H7209: =IF($A7209="","",Tienda_4!D9) -> 11900 | I7209: =IF($A7209="","",Tienda_4!H9) -> 4 | J7209: =IF($A7209="",0,IF(AND(OR('Cuadro-de-mando'!$B$4="(Todas)",'Cuadro-de-mando'!$B$4=$A7209),OR('Cuadro-de-mando'!$E$4="(Todas)",'Cuadro-de-mando'!$E$4=$B7209),OR('Cuadro-de-mando'!$H$4="(Todas)",'Cuadro-de-mando'!$H$4=$C7209),OR('Cuadro-de-mando'!$K$4="(Todas)",'Cuadro-de-mando'!$K$4=$E7209),OR('Cuadro-de-mando'!$N$4="(Todos)",'Cuadro-de-mando'!$N$4=$F7209)),1,0)) -> 1
A7210: =IF(Tienda_4!$A10="","","Tienda 4") -> Tienda 4 | B7210: =IF($A7210="","",Tienda_4!B10) -> Electrónicos | C7210: =IF($A7210="","",Tienda_4!G10) -> Bogotá | D7210: =IF($A7210="","",Tienda_4!F10) -> Camila Rivera | E7210: =IF($A7210="","",Tienda_4!I10) -> Tarjeta de crédito | F7210: =IF($A7210="","",VALUE(RIGHT(Tienda_4!E10,4))) -> 2022 | G7210: =IF($A7210="","",Tienda_4!C10) -> 2339000 | H7210: =IF($A7210="","",Tienda_4!D10) -> 122700 | I7210: =IF($A7210="","",Tienda_4!H10) -> 5 | J7210: =IF($A7210="",0,IF(AND(OR('Cuadro-de-mando'!$B$4="(Todas)",'Cuadro-de-mando'!$B$4=$A7210),OR('Cuadro-de-mando'!$E$4="(Todas)",'Cuadro-de-mando'!$E$4=$B7210),OR('Cuadro-de-mando'!$H$4="(Todas)",'Cuadro-de-mando'!$H$4=$C7210),OR('Cuadro-de-mando'!$K$4="(Todas)",'Cuadro-de-mando'!$K$4=$E7210),OR('Cuadro-de-mando'!$N$4="(Todos)",'Cuadro-de-mando'!$N$4=$F7210)),1,0)) -> 1
A7211: =IF(Tienda_4!$A11="","","Tienda 4") -> Tienda 4 | B7211: =IF($A7211="","",Tienda_4!B11) -> Muebles | C7211: =IF($A7211="","",Tienda_4!G11) -> Bogotá | D7211: =IF($A7211="","",Tienda_4!F11) -> Rafael Acosta | E7211: =IF($A7211="","",Tienda_4!I11) -> Tarjeta de crédito | F7211: =IF($A7211="","",VALUE(RIGHT(Tienda_4!E11,4))) -> 2022 | G7211: =IF($A7211="","",Tienda_4!C11) -> 273300 | H7211: =IF($A7211="","",Tienda_4!D11) -> 21900 | I7211: =IF($A7211="","",Tienda_4!H11) -> 1 | J7211: =IF($A7211="",0,IF(AND(OR('Cuadro-de-mando'!$B$4="(Todas)",'Cuadro-de-mando'!$B$4=$A7211),OR('Cuadro-de-mando'!$E$4="(Todas)",'Cuadro-de-mando'!$E$4=$B7211),OR('Cuadro-de-mando'!$H$4="(Todas)",'Cuadro-de-mando'!$H$4=$C7211),OR('Cuadro-de-mando'!$K$4="(Todas)",'Cuadro-de-mando'!$K$4=$E7211),OR('Cuadro-de-mando'!$N$4="(Todos)",'Cuadro-de-mando'!$N$4=$F7211)),1,0)) -> 1
A7212: =IF(Tienda_4!$A12="","","Tienda 4") -> Tienda 4 | B7212: =IF($A7212="","",Tienda_4!B12) -> Deportes y diversión | C7212: =IF($A7212="","",Tienda_4!G12) -> Manizales | D7212: =IF($A7212="","",Tienda_4!F12) -> Felipe Santos | E7212: =IF($A7212="","",Tienda_4!I12) -> Nequi | F7212: =IF($A7212="","",VALUE(RIGHT(Tienda_4!E12,4))) -> 2022 | G7212: =IF($A7212="","",Tienda_4!C12) -> 68000 | H7212: =IF($A7212="","",Tienda_4!D12) -> 6000 | I7212: =IF($A7212="","",Tienda_4!H12) -> 4 | J7212: =IF($A7212="",0,IF(AND(OR('Cuadro-de-mando'!$B$4="(Todas)",'Cuadro-de-mando'!$B$4=$A7212),OR('Cuadro-de-mando'!$E$4="(Todas)",'Cuadro-de-mando'!$E$4=$B7212),OR('Cuadro-de-mando'!$H$4="(Todas)",'Cuadro-de-mando'!$H$4=$C7212),OR('Cuadro-de-mando'!$K$4="(Todas)",'Cuadro-de-mando'!$K$4=$E7212),OR('Cuadro-de-mando'!$N$4="(Todos)",'Cuadro-de-mando'!$N$4=$F7212)),1,0)) -> 1
A7213: =IF(Tienda_4!$A13="","","Tienda 4") -> Tienda 4 | B7213: =IF($A7213="","",Tienda_4!B13) -> Juguetes | C7213: =IF($A7213="","",Tienda_4!G13) -> Bogotá | D7213: =IF($A7213="","",Tienda_4!F13) -> Pedro Gomez | E7213: =IF($A7213="","",Tienda_4!I13) -> Tarjeta de crédito | F7213: =IF($A7213="","",VALUE(RIGHT(Tienda_4!E13,4))) -> 2020 | G7213: =IF($A7213="","",Tienda_4!C13) -> 47500 | H7213: =IF($A7213="","",Tienda_4!D13) -> 0 | I7213: =IF($A7213="","",Tienda_4!H13) -> 5 | J7213: =IF($A7213="",0,IF(AND(OR('Cuadro-de-mando'!$B$4="(Todas)",'Cuadro-de-mando'!$B$4=$A7213),OR('Cuadro-de-mando'!$E$4="(Todas)",'Cuadro-de-mando'!$E$4=$B7213),OR('Cuadro-de-mando'!$H$4="(Todas)",'Cuadro-de-mando'!$H$4=$C7213),OR('Cuadro-de-mando'!$K$4="(Todas)",'Cuadro-de-mando'!$K$4=$E7213),OR('Cuadro-de-mando'!$N$4="(Todos)",'Cuadro-de-mando'!$N$4=$F7213)),1,0)) -> 1
... A9601: =IF(Tienda_4!$A2401="","","Tienda 4") | B9601: =IF($A9601="","",Tienda_4!B2401) | C9601: =IF($A9601="","",Tienda_4!G2401) | D9601: =IF($A9601="","",Tienda_4!F2401) | E9601: =IF($A9601="","",Tienda_4!I2401) | F9601: =IF($A9601="","",VALUE(RIGHT(Tienda_4!E2401,4))) | G9601: =IF($A9601="","",Tienda_4!C2401) | H9601: =IF($A9601="","",Tienda_4!D2401) | I9601: =IF($A9601="","",Tienda_4!H2401) | J9601: =IF($A9601="",0,IF(AND(OR('Cuadro-de-mando'!$B$4="(Todas)",'Cuadro-de-mando'!$B$4=$A9601),OR('Cuadro-de-mando'!$E$4="(Todas)",'Cuadro-de-mando'!$E$4=$B9601),OR('Cuadro-de-mando'!$H$4="(Todas)",'Cuadro-de-mando'!$H$4=$C9601),OR('Cuadro-de-mando'!$K$4="(Todas)",'Cuadro-de-mando'!$K$4=$E9601),OR('Cuadro-de-mando'!$N$4="(Todos)",'Cuadro-de-mando'!$N$4=$F9601)),1,0)) -> 0

Sheet Cuadro-de-mando
B2: CUADRO DE MANDO INTERACTIVO — VENTAS TIENDAS 1 A 4
B3: Tienda | E3: Categoría | H3: Ciudad | K3: Método de pago | N3: Año
B4: (Todas) | E4: (Todas) | H4: (Todas) | K4: (Todas) | N4: (Todos)
B6: INGRESOS (FILTRADO) | E6: N° DE VENTAS | H6: TICKET PROMEDIO | K6: COSTO DE ENVÍO | N6: CALIFICACIÓN
B7: =SUMIF(Datos_Consolidados!$J$2:$J$9601,1,Datos_Consolidados!$G$2:$G$9601) -> 4403619200 | E7: =COUNTIF(Datos_Consolidados!$J$2:$J$9601,1) -> 9435 | H7: =IFERROR(SUMIF(Datos_Consolidados!$J$2:$J$9601,1,Datos_Consolidados!$G$2:$G$9601)/COUNTIF(Datos_Consolidados!$J$2:$J$9601,1),0) -> 466732.29 | K7: =SUMIF(Datos_Consolidados!$J$2:$J$9601,1,Datos_Consolidados!$H$2:$H$9601) -> 234697000 | N7: =IFERROR(SUMIF(Datos_Consolidados!$J$2:$J$9601,1,Datos_Consolidados!$I$2:$I$9601)/COUNTIF(Datos_Consolidados!$J$2:$J$9601,1),0) -> 4.0145204
B8: ="% del total general: "&TEXT(IFERROR(SUMIF(Datos_Consolidados!$J$2:$J$9601,1,Datos_Consolidados!$G$2:$G$9601)/Análisis!$F$7,0),"0,0%") -> % del total general: 100,0% | E8: ="De "&TEXT(Análisis!$F$6,"#.##0")&" registros totales" -> De 9.435 registros totales | H8: ="General: "&TEXT(Análisis!$F$8,"$#.##0") -> General: $466.732 | K8: ="Envío/ingresos: "&TEXT(IFERROR(SUMIF(Datos_Consolidados!$J$2:$J$9601,1,Datos_Consolidados!$H$2:$H$9601)/SUMIF(Datos_Consolidados!$J$2:$J$9601,1,Datos_Consolidados!$G$2:$G$9601),0),"0,0%") -> Envío/ingresos: 5,3% | N8: ="General: "&TEXT(Análisis!$F$12,"0,00") -> General: 4,01
B44: DETALLE DE LA SELECCIÓN
B45: Tienda | D45: Ingresos | F45: % de la selección | H45: N° de ventas | J45: Calificación | L45: Insight de la selección
B46: =Datos_Consolidados!T3 -> Tienda 1 | D46: =Datos_Consolidados!U3 -> 1150880400 | F46: =IFERROR(D46/$D$50,0) -> 0.26134876 | H46: =COUNTIFS(Datos_Consolidados!$J$2:$J$9601,1,Datos_Consolidados!$A$2:$A$9601,$B46) -> 2359 | J46: =IFERROR(SUMIFS(Datos_Consolidados!$I$2:$I$9601,Datos_Consolidados!$J$2:$J$9601,1,Datos_Consolidados!$A$2:$A$9601,$B46)/H46,0) -> 3.976685 | L46: ="Con los filtros actuales (Tienda: "&$B$4&" | Categoría: "&$E$4&" | Ciudad: "&$H$4&" | Pago: "&$K$4&" | Año: "&$N$4&") la selección suma "&TEXT(SUMIF(Datos_Consolidados!$J$2:$J$9601,1,Datos_Consolidados!$G$2:$G$9601),"$#.##0")&" en "&TEXT(COUNTIF(Datos_Consolidados!$J$2:$J$9601,1),"#.##0")&" ventas, equivalentes al "&TEXT(IFERROR(SUMIF(Datos_Consolidados!$J$2:$J$9601,1,Datos_Consolidados!$G$2:$G$9601)/Análisis!$F$7,0),"0,0%")&" de los ingresos totales. La categoría líder es "&Datos_Consolidados!Z3&" ("&TEXT(IFERROR(Datos_Consolidados!AA3/SUMIF(Datos_Consolidados!$J$2:$J$9601,1,Datos_Consolidados!$G$2:$G$9601),0),"0,0%")&"), la ciudad líder es "&Datos_Consolidados!Z13&" ("&TEXT(IFERROR(Datos_Consolidados!AA13/SUMIF(Datos_Consolidados!$J$2:$J$9601,1,Datos_Consolidados!$G$2:$G$9601),0),"0,0%")&") y el vendedor con mayores ingresos es "&Datos_Consolidados!Z26&" ("&TEXT(Datos_Consolidados!AA26,"$#.##0")&")." -> Con los filtros actuales (Tienda: (Todas) | Categoría: (Todas) | Ciudad: (Todas) | Pago: (Todas) | Año: (Todos)) la selección suma $4.403.619.200 en 9.435 ventas, equivalentes al 100,0% de los ingresos totales. La categoría líder es Electrónicos (37,7%), la ciudad líder es Bogotá (41,2%) y el vendedor con mayores ingresos es Felipe Santos ($353.796.000).
B47: =Datos_Consolidados!T4 -> Tienda 2 | D47: =Datos_Consolidados!U4 -> 1116343500 | F47: =IFERROR(D47/$D$50,0) -> 0.25350591 | H47: =COUNTIFS(Datos_Consolidados!$J$2:$J$9601,1,Datos_Consolidados!$A$2:$A$9601,$B47) -> 2359 | J47: =IFERROR(SUMIFS(Datos_Consolidados!$I$2:$I$9601,Datos_Consolidados!$J$2:$J$9601,1,Datos_Consolidados!$A$2:$A$9601,$B47)/H47,0) -> 4.0373039
B48: =Datos_Consolidados!T5 -> Tienda 3 | D48: =Datos_Consolidados!U5 -> 1098019600 | F48: =IFERROR(D48/$D$50,0) -> 0.24934481 | H48: =COUNTIFS(Datos_Consolidados!$J$2:$J$9601,1,Datos_Consolidados!$A$2:$A$9601,$B48) -> 2359 | J48: =IFERROR(SUMIFS(Datos_Consolidados!$I$2:$I$9601,Datos_Consolidados!$J$2:$J$9601,1,Datos_Consolidados!$A$2:$A$9601,$B48)/H48,0) -> 4.0483256
B49: =Datos_Consolidados!T6 -> Tienda 4 | D49: =Datos_Consolidados!U6 -> 1038375700 | F49: =IFERROR(D49/$D$50,0) -> 0.23580052 | H49: =COUNTIFS(Datos_Consolidados!$J$2:$J$9601,1,Datos_Consolidados!$A$2:$A$9601,$B49) -> 2358 | J49: =IFERROR(SUMIFS(Datos_Consolidados!$I$2:$I$9601,Datos_Consolidados!$J$2:$J$9601,1,Datos_Consolidados!$A$2:$A$9601,$B49)/H49,0) -> 3.9957591
B50: Total selección | D50: =SUMIF(Datos_Consolidados!$J$2:$J$9601,1,Datos_Consolidados!$G$2:$G$9601) -> 4403619200 | F50: =SUM(F46:F49) -> 1 | H50: =COUNTIF(Datos_Consolidados!$J$2:$J$9601,1) -> 9435 | J50: =IFERROR(SUMIF(Datos_Consolidados!$J$2:$J$9601,1,Datos_Consolidados!$I$2:$I$9601)/H50,0) -> 4.0145204

Sheet Reporte
B2: REPORTE DE ANÁLISIS DE VENTAS
B3: ="Tiendas 1 a 4 | Generado el "&TEXT(TODAY(),"dd/mm/yyyy")&" | Fuente: hojas Tienda_1 a Tienda_4 del presente libro" -> Tiendas 1 a 4 | Generado el 19/09/2026 | Fuente: hojas Tienda_1 a Tienda_4 del presente libro
B5: 1. Objetivo y alcance
B6: ="Este reporte consolida las operaciones registradas en las cuatro tiendas del libro. Comprende "&TEXT(Análisis!$F$6,"#.##0")&" transacciones por un valor total de "&TEXT(Análisis!$F$7,"$#.##0")&", con un ticket promedio de "&TEXT(Análisis!$F$8,"$#.##0")&". Todas las cifras están calculadas con fórmulas vinculadas a los datos de origen, por lo que el reporte se actualiza automáticamente ante cualquier edición, alta o baja de registros." -> Este reporte consolida las operaciones registradas en las cuatro tiendas del libro. Comprende 9.435 transacciones por un valor total de $4.403.619.200, con un ticket promedio de $466.732. Todas las cifras están calculadas con fórmulas vinculadas a los datos de origen, por lo que el reporte se actualiza automáticamente ante cualquier edición, alta o baja de registros.
B7: ="Las variables analizadas son: producto y categoría, precio, costo de envío, fecha de compra, vendedor, ciudad de compra, calificación del cliente, método de pago y número de cuotas." -> Las variables analizadas son: producto y categoría, precio, costo de envío, fecha de compra, vendedor, ciudad de compra, calificación del cliente, método de pago y número de cuotas.
B9: 2. Indicadores generales
B10: Indicador | C10: Valor
B11: Número de transacciones | C11: =Análisis!$F$6 -> 9435
B12: Ingresos totales | C12: =Análisis!$F$7 -> 4403619200
B13: Ticket promedio | C13: =Análisis!$F$8 -> 466732.29
B14: Costo de envío total | C14: =Análisis!$F$9 -> 234697000
B15: Costo de envío promedio | C15: =Análisis!$F$10 -> 24875.146
B16: Ingreso neto de envíos | C16: =Análisis!$F$11 -> 4168922200
B17: Envío sobre ingresos | C17: =IFERROR(Análisis!$F$9/Análisis!$F$7,0) -> 0.053296389
B18: Calificación promedio (1-5) | C18: =Análisis!$F$12 -> 4.0145204
B19: Cuotas promedio | C19: =Análisis!$F$13 -> 2.927398
B21: 3. Desempeño por tienda
B22: Tienda | C22: Ingresos | D22: % del total | E22: Ticket promedio | F22: Calificación
B23: =Análisis!B5 -> Tienda 1 | C23: =Análisis!B7 -> 1150880400 | D23: =Análisis!B14 -> 0.26134876 | E23: =Análisis!B8 -> 487867.91 | F23: =Análisis!B12 -> 3.976685
B24: =Análisis!C5 -> Tienda 2 | C24: =Análisis!C7 -> 1116343500 | D24: =Análisis!C14 -> 0.25350591 | E24: =Análisis!C8 -> 473227.43 | F24: =Análisis!C12 -> 4.0373039
B25: =Análisis!D5 -> Tienda 3 | C25: =Análisis!D7 -> 1098019600 | D25: =Análisis!D14 -> 0.24934481 | E25: =Análisis!D8 -> 465459.77 | F25: =Análisis!D12 -> 4.0483256
B26: =Análisis!E5 -> Tienda 4 | C26: =Análisis!E7 -> 1038375700 | D26: =Análisis!E14 -> 0.23580052 | E26: =Análisis!E8 -> 440362.89 | F26: =Análisis!E12 -> 3.9957591
B27: Total | C27: =SUM(C23:C26) -> 4403619200 | D27: =SUM(D23:D26) -> 1 | E27: =Análisis!$F$8 -> 466732.29 | F27: =Análisis!$F$12 -> 4.0145204
B28: ="Lectura: "&Análisis!$B$86&" encabeza los ingresos con "&TEXT(Análisis!$C$86,"$#.##0")&" ("&TEXT(MAX($D$23:$D$26),"0,0%")&" del total), mientras que "&Análisis!$B$87&" cierra con "&TEXT(Análisis!$C$87,"$#.##0")&", un "&TEXT(1-Análisis!$C$87/Análisis!$C$86,"0,0%")&" por debajo del líder. La dispersión entre tiendas es moderada, por lo que ninguna tienda es marginal en volumen; las diferencias se explican más por ticket promedio que por número de operaciones." -> Lectura: Tienda 1 encabeza los ingresos con $1.150.880.400 (26,1% del total), mientras que Tienda 4 cierra con $1.038.375.700, un 9,8% por debajo del líder. La dispersión entre tiendas es moderada, por lo que ninguna tienda es marginal en volumen; las diferencias se explican más por ticket promedio que por número de operaciones.
B30: 4. Análisis por categoría de producto
B31: Categoría | C31: Ingresos | D31: % del total | E31: N° de ventas
B32: =INDEX(Análisis!$A$18:$A$25,MATCH(LARGE(Análisis!$F$18:$F$25,1),Análisis!$F$18:$F$25,0)) -> Electrónicos | C32: =LARGE(Análisis!$F$18:$F$25,1) -> 1660576500 | D32: =IFERROR(C32/Análisis!$F$7,0) -> 0.37709357 | E32: =INDEX(Análisis!$H$18:$H$25,MATCH(B32,Análisis!$A$18:$A$25,0)) -> 1772
B33: =INDEX(Análisis!$A$18:$A$25,MATCH(LARGE(Análisis!$F$18:$F$25,2),Análisis!$F$18:$F$25,0)) -> Electrodomésticos | C33: =LARGE(Análisis!$F$18:$F$25,2) -> 1324751100 | D33: =IFERROR(C33/Análisis!$F$7,0) -> 0.30083235 | E33: =INDEX(Análisis!$H$18:$H$25,MATCH(B33,Análisis!$A$18:$A$25,0)) -> 1149
B34: =INDEX(Análisis!$A$18:$A$25,MATCH(LARGE(Análisis!$F$18:$F$25,3),Análisis!$F$18:$F$25,0)) -> Muebles | C34: =LARGE(Análisis!$F$18:$F$25,3) -> 757661000 | D34: =IFERROR(C34/Análisis!$F$7,0) -> 0.17205416 | E34: =INDEX(Análisis!$H$18:$H$25,MATCH(B34,Análisis!$A$18:$A$25,0)) -> 1886
B35: =INDEX(Análisis!$A$18:$A$25,MATCH(LARGE(Análisis!$F$18:$F$25,4),Análisis!$F$18:$F$25,0)) -> Instrumentos musicales | C35: =LARGE(Análisis!$F$18:$F$25,4) -> 348772600 | D35: =IFERROR(C35/Análisis!$F$7,0) -> 0.079201353 | E35: =INDEX(Análisis!$H$18:$H$25,MATCH(B35,Análisis!$A$18:$A$25,0)) -> 753
B36: =INDEX(Análisis!$A$18:$A$25,MATCH(LARGE(Análisis!$F$18:$F$25,5),Análisis!$F$18:$F$25,0)) -> Deportes y diversión | C36: =LARGE(Análisis!$F$18:$F$25,5) -> 142977700 | D36: =IFERROR(C36/Análisis!$F$7,0) -> 0.032468225 | E36: =INDEX(Análisis!$H$18:$H$25,MATCH(B36,Análisis!$A$18:$A$25,0)) -> 1113
B37: =INDEX(Análisis!$A$18:$A$25,MATCH(LARGE(Análisis!$F$18:$F$25,6),Análisis!$F$18:$F$25,0)) -> Juguetes | C37: =LARGE(Análisis!$F$18:$F$25,6) -> 73604400 | D37: =IFERROR(C37/Análisis!$F$7,0) -> 0.016714524 | E37: =INDEX(Análisis!$H$18:$H$25,MATCH(B37,Análisis!$A$18:$A$25,0)) -> 1290
B38: =INDEX(Análisis!$A$18:$A$25,MATCH(LARGE(Análisis!$F$18:$F$25,7),Análisis!$F$18:$F$25,0)) -> Artículos para el hogar | C38: =LARGE(Análisis!$F$18:$F$25,7) -> 57579800 | D38: =IFERROR(C38/Análisis!$F$7,0) -> 0.013075563 | E38: =INDEX(Análisis!$H$18:$H$25,MATCH(B38,Análisis!$A$18:$A$25,0)) -> 730
B39: =INDEX(Análisis!$A$18:$A$25,MATCH(LARGE(Análisis!$F$18:$F$25,8),Análisis!$F$18:$F$25,0)) -> Libros | C39: =LARGE(Análisis!$F$18:$F$25,8) -> 37696100 | D39: =IFERROR(C39/Análisis!$F$7,0) -> 0.0085602543 | E39: =INDEX(Análisis!$H$18:$H$25,MATCH(B39,Análisis!$A$18:$A$25,0)) -> 742
B40: Total | C40: =SUM(C32:C39) -> 4403619200 | D40: =SUM(D32:D39) -> 1 | E40: =SUM(E32:E39) -> 9435
B41: ="Lectura: "&B32&" y "&B33&" concentran "&TEXT(D32+D33,"0,0%")&" de los ingresos, pese a no ser las categorías con más unidades vendidas; su peso proviene del alto valor unitario. En el extremo opuesto, "&B39&" aporta apenas "&TEXT(D39,"0,0%")&" del total. Las categorías de bajo ticket (libros, juguetes, artículos para el hogar) generan tráfico pero poco margen de facturación." -> Lectura: Electrónicos y Electrodomésticos concentran 67,8% de los ingresos, pese a no ser las categorías con más unidades vendidas; su peso proviene del alto valor unitario. En el extremo opuesto, Libros aporta apenas 0,9% del total. Las categorías de bajo ticket (libros, juguetes, artículos para el hogar) generan tráfico pero poco margen de facturación.
B43: 5. Distribución geográfica (Top 8 ciudades)
B44: Ciudad | C44: Ingresos | D44: % del total | E44: N° de ventas
B45: =INDEX(Análisis!$A$30:$A$48,MATCH(LARGE(Análisis!$F$30:$F$48,1),Análisis!$F$30:$F$48,0)) -> Bogotá | C45: =LARGE(Análisis!$F$30:$F$48,1) -> 1814858300 | D45: =IFERROR(C45/Análisis!$F$7,0) -> 0.4121288 | E45: =INDEX(Análisis!$H$30:$H$48,MATCH(B45,Análisis!$A$30:$A$48,0)) -> 3943
B46: =INDEX(Análisis!$A$30:$A$48,MATCH(LARGE(Análisis!$F$30:$F$48,2),Análisis!$F$30:$F$48,0)) -> Medellín | C46: =LARGE(Análisis!$F$30:$F$48,2) -> 1096669200 | D46: =IFERROR(C46/Análisis!$F$7,0) -> 0.24903815 | E46: =INDEX(Análisis!$H$30:$H$48,MATCH(B46,Análisis!$A$30:$A$48,0)) -> 2314
B47: =INDEX(Análisis!$A$30:$A$48,MATCH(LARGE(Análisis!$F$30:$F$48,3),Análisis!$F$30:$F$48,0)) -> Cali | C47: =LARGE(Análisis!$F$30:$F$48,3) -> 506526100 | D47: =IFERROR(C47/Análisis!$F$7,0) -> 0.11502495 | E47: =INDEX(Análisis!$H$30:$H$48,MATCH(B47,Análisis!$A$30:$A$48,0)) -> 1007
B48: =INDEX(Análisis!$A$30:$A$48,MATCH(LARGE(Análisis!$F$30:$F$48,4),Análisis!$F$30:$F$48,0)) -> Pereira | C48: =LARGE(Análisis!$F$30:$F$48,4) -> 225927300 | D48: =IFERROR(C48/Análisis!$F$7,0) -> 0.051304913 | E48: =INDEX(Análisis!$H$30:$H$48,MATCH(B48,Análisis!$A$30:$A$48,0)) -> 517
B49: =INDEX(Análisis!$A$30:$A$48,MATCH(LARGE(Análisis!$F$30:$F$48,5),Análisis!$F$30:$F$48,0)) -> Barranquilla | C49: =LARGE(Análisis!$F$30:$F$48,5) -> 132040500 | D49: =IFERROR(C49/Análisis!$F$7,0) -> 0.029984541 | E49: =INDEX(Análisis!$H$30:$H$48,MATCH(B49,Análisis!$A$30:$A$48,0)) -> 310
B50: =INDEX(Análisis!$A$30:$A$48,MATCH(LARGE(Análisis!$F$30:$F$48,6),Análisis!$F$30:$F$48,0)) -> Cartagena | C50: =LARGE(Análisis!$F$30:$F$48,6) -> 102376700 | D50: =IFERROR(C50/Análisis!$F$7,0) -> 0.023248309 | E50: =INDEX(Análisis!$H$30:$H$48,MATCH(B50,Análisis!$A$30:$A$48,0)) -> 242
B51: =INDEX(Análisis!$A$30:$A$48,MATCH(LARGE(Análisis!$F$30:$F$48,7),Análisis!$F$30:$F$48,0)) -> Cúcuta | C51: =LARGE(Análisis!$F$30:$F$48,7) -> 99369100 | D51: =IFERROR(C51/Análisis!$F$7,0) -> 0.022565325 | E51: =INDEX(Análisis!$H$30:$H$48,MATCH(B51,Análisis!$A$30:$A$48,0)) -> 186
B52: =INDEX(Análisis!$A$30:$A$48,MATCH(LARGE(Análisis!$F$30:$F$48,8),Análisis!$F$30:$F$48,0)) -> Bucaramanga | C52: =LARGE(Análisis!$F$30:$F$48,8) -> 90573300 | D52: =IFERROR(C52/Análisis!$F$7,0) -> 0.020567923 | E52: =INDEX(Análisis!$H$30:$H$48,MATCH(B52,Análisis!$A$30:$A$48,0)) -> 181
B53: Subtotal Top 8 | C53: =SUM(C45:C52) -> 4068340500 | D53: =SUM(D45:D52) -> 0.92386292 | E53: =SUM(E45:E52) -> 8700
B54: ="Lectura: la operación está fuertemente concentrada en "&B45&", que aporta "&TEXT(D45,"0,0%")&" de los ingresos, seguida de "&B46&" ("&TEXT(D46,"0,0%")&") y "&B47&" ("&TEXT(D47,"0,0%")&"). Las ocho primeras ciudades explican "&TEXT(D53,"0,0%")&" del total, lo que evidencia una cobertura amplia pero con muy baja facturación en plazas secundarias." -> Lectura: la operación está fuertemente concentrada en Bogotá, que aporta 41,2% de los ingresos, seguida de Medellín (24,9%) y Cali (11,5%). Las ocho primeras ciudades explican 92,4% del total, lo que evidencia una cobertura amplia pero con muy baja facturación en plazas secundarias.
B56: 6. Equipo comercial (Top 5 y menor desempeño)
B57: Vendedor | C57: Ingresos | D57: % del total | E57: N° de ventas
B58: =INDEX(Análisis!$A$53:$A$66,MATCH(LARGE(Análisis!$C$53:$C$66,1),Análisis!$C$53:$C$66,0)) -> Felipe Santos | C58: =LARGE(Análisis!$C$53:$C$66,1) -> 353796000 | D58: =IFERROR(C58/Análisis!$F$7,0) -> 0.080342097 | E58: =INDEX(Análisis!$B$53:$B$66,MATCH(B58,Análisis!$A$53:$A$66,0)) -> 701
B59: =INDEX(Análisis!$A$53:$A$66,MATCH(LARGE(Análisis!$C$53:$C$66,2),Análisis!$C$53:$C$66,0)) -> Izabela de León | C59: =LARGE(Análisis!$C$53:$C$66,2) -> 350342400 | D59: =IFERROR(C59/Análisis!$F$7,0) -> 0.079557833 | E59: =INDEX(Análisis!$B$53:$B$66,MATCH(B59,Análisis!$A$53:$A$66,0)) -> 744
B60: =INDEX(Análisis!$A$53:$A$66,MATCH(LARGE(Análisis!$C$53:$C$66,3),Análisis!$C$53:$C$66,0)) -> Maria Alfonso | C60: =LARGE(Análisis!$C$53:$C$66,3) -> 349694800 | D60: =IFERROR(C60/Análisis!$F$7,0) -> 0.079410772 | E60: =INDEX(Análisis!$B$53:$B$66,MATCH(B60,Análisis!$A$53:$A$66,0)) -> 679
B61: =INDEX(Análisis!$A$53:$A$66,MATCH(LARGE(Análisis!$C$53:$C$66,4),Análisis!$C$53:$C$66,0)) -> Juliana Costa | C61: =LARGE(Análisis!$C$53:$C$66,4) -> 338364700 | D61: =IFERROR(C61/Análisis!$F$7,0) -> 0.076837866 | E61: =INDEX(Análisis!$B$53:$B$66,MATCH(B61,Análisis!$A$53:$A$66,0)) -> 677
B62: =INDEX(Análisis!$A$53:$A$66,MATCH(LARGE(Análisis!$C$53:$C$66,5),Análisis!$C$53:$C$66,0)) -> Pedro Gomez | C62: =LARGE(Análisis!$C$53:$C$66,5) -> 313350900 | D62: =IFERROR(C62/Análisis!$F$7,0) -> 0.071157583 | E62: =INDEX(Análisis!$B$53:$B$66,MATCH(B62,Análisis!$A$53:$A$66,0)) -> 655
B63: ="Menor: "&INDEX(Análisis!$A$53:$A$66,MATCH(MIN(Análisis!$C$53:$C$66),Análisis!$C$53:$C$66,0)) -> Menor: Mariana Herrera | C63: =MIN(Análisis!$C$53:$C$66) -> 283302600 | D63: =IFERROR(C63/Análisis!$F$7,0) -> 0.064334037 | E63: =INDEX(Análisis!$B$53:$B$66,MATCH(MIN(Análisis!$C$53:$C$66),Análisis!$C$53:$C$66,0)) -> 656
B64: ="Lectura: el equipo comercial muestra un desempeño homogéneo. "&B58&" lidera con "&TEXT(C58,"$#.##0")&" y la diferencia frente al último puesto es de "&TEXT(C58-C63,"$#.##0")&" ("&TEXT(C58/C63-1,"0,0%")&"), una brecha baja para un equipo de 14 vendedores, lo que sugiere que los resultados dependen más de la mezcla de productos y plazas que del vendedor individual." -> Lectura: el equipo comercial muestra un desempeño homogéneo. Felipe Santos lidera con $353.796.000 y la diferencia frente al último puesto es de $70.493.400 (24,9%), una brecha baja para un equipo de 14 vendedores, lo que sugiere que los resultados dependen más de la mezcla de productos y plazas que del vendedor individual.
B66: 7. Evolución temporal
B67: Año | C67: Ingresos | D67: % del total | E67: Variación anual
B68: =Análisis!A71 -> 2020 | C68: =Análisis!F71 -> 1341955000 | D68: =Análisis!G71 -> 0.30473911 | E68: =""
B69: =Análisis!A72 -> 2021 | C69: =Análisis!F72 -> 1424114300 | D69: =Análisis!G72 -> 0.32339633 | E69: =IFERROR(C69/C68-1,"") -> 0.061223588
B70: =Análisis!A73 -> 2022 | C70: =Análisis!F73 -> 1327451900 | D70: =Análisis!G73 -> 0.30144566 | E70: =IFERROR(C70/C69-1,"") -> -0.067875451
B71: =Análisis!A74 -> 2023 | C71: =Análisis!F74 -> 310098000 | D71: =Análisis!G74 -> 0.070418895 | E71: =IFERROR(C71/C70-1,"") -> -0.76639606
B72: Total | C72: =SUM(C68:C71) -> 4403619200 | D72: =SUM(D68:D71) -> 1
B73: ="Lectura: el pico de facturación se alcanzó en "&TEXT(INDEX(B68:B71,MATCH(MAX(C68:C71),C68:C71,0)),"0")&" con "&TEXT(MAX(C68:C71),"$#.##0")&". El último año registrado ("&TEXT(B71,"0")&") muestra una variación de "&TEXT(E71,"0,0%")&" frente al año previo y representa solo "&TEXT(D71,"0,0%")&" del acumulado, patrón típico de un período parcial; antes de leerlo como una caída real conviene verificar que el año esté completo en la fuente." -> Lectura: el pico de facturación se alcanzó en 2021 con $1.424.114.300. El último año registrado (2023) muestra una variación de -76,6% frente al año previo y representa solo 7,0% del acumulado, patrón típico de un período parcial; antes de leerlo como una caída real conviene verificar que el año esté completo en la fuente.
B75: 8. Métodos de pago y financiación
B76: Método de pago | C76: Ingresos | D76: % del total | E76: N° de ventas
B77: =Análisis!A79 -> Cupón | C77: =Análisis!F79 -> 235869600 | D77: =Análisis!G79 -> 0.05356267 | E77: =Análisis!H79 -> 504
B78: =Análisis!A80 -> Nequi | C78: =Análisis!F80 -> 880684200 | D78: =Análisis!G80 -> 0.199991 | E78: =Análisis!H80 -> 1900
B79: =Análisis!A81 -> Tarjeta de crédito | C79: =Análisis!F81 -> 3230607100 | D79: =Análisis!G81 -> 0.73362545 | E79: =Análisis!H81 -> 6898
B80: =Análisis!A82 -> Tarjeta de débito | C80: =Análisis!F82 -> 56458300 | D80: =Análisis!G82 -> 0.012820886 | E80: =Análisis!H82 -> 133
B81: Total | C81: =SUM(C77:C80) -> 4403619200 | D81: =SUM(D77:D80) -> 1 | E81: =SUM(E77:E80) -> 9435
B82: ="Lectura: "&INDEX(B77:B80,MATCH(MAX(C77:C80),C77:C80,0))&" concentra "&TEXT(MAX(D77:D80),"0,0%")&" de los ingresos, con un promedio de "&TEXT(Análisis!$F$13,"0,00")&" cuotas por operación. La alta dependencia de un solo medio de pago implica exposición a sus comisiones y a eventuales fallas del proveedor; conviene incentivar los medios alternativos." -> Lectura: Tarjeta de crédito concentra 73,4% de los ingresos, con un promedio de 2,93 cuotas por operación. La alta dependencia de un solo medio de pago implica exposición a sus comisiones y a eventuales fallas del proveedor; conviene incentivar los medios alternativos.
B84: 9. Satisfacción del cliente
B85: Tienda | C85: Calificación promedio | D85: Brecha vs. promedio general
B86: =Análisis!B5 -> Tienda 1 | C86: =Análisis!B12 -> 3.976685 | D86: =C86-Análisis!$F$12 -> -0.037835367
B87: =Análisis!C5 -> Tienda 2 | C87: =Análisis!C12 -> 4.0373039 | D87: =C87-Análisis!$F$12 -> 0.02278354
B88: =Análisis!D5 -> Tienda 3 | C88: =Análisis!D12 -> 4.0483256 | D88: =C88-Análisis!$F$12 -> 0.033805159
B89: =Análisis!E5 -> Tienda 4 | C89: =Análisis!E12 -> 3.9957591 | D89: =C89-Análisis!$F$12 -> -0.018761285
B90: Promedio general | C90: =Análisis!$F$12 -> 4.0145204
B91: ="Lectura: la calificación promedio general es "&TEXT(Análisis!$F$12,"0,00")&" sobre 5. La mejor evaluada es "&Análisis!$B$88&" ("&TEXT(Análisis!$C$88,"0,00")&") y la más baja "&Análisis!$B$89&" ("&TEXT(Análisis!$C$89,"0,00")&"). La diferencia de "&TEXT(Análisis!$C$88-Análisis!$C$89,"0,00")&" puntos es pequeña, por lo que la satisfacción no discrimina de forma determinante entre tiendas, aunque sí acompaña la decisión cuando los ingresos son similares." -> Lectura: la calificación promedio general es 4,01 sobre 5. La mejor evaluada es Tienda 3 (4,05) y la más baja Tienda 1 (3,98). La diferencia de 0,07 puntos es pequeña, por lo que la satisfacción no discrimina de forma determinante entre tiendas, aunque sí acompaña la decisión cuando los ingresos son similares.
B93: 10. Conclusiones
B94: ="1. La operación consolidada alcanza "&TEXT(Análisis!$F$7,"$#.##0")&" en "&TEXT(Análisis!$F$6,"#.##0")&" transacciones, con una calificación media de "&TEXT(Análisis!$F$12,"0,00")&" sobre 5." -> 1. La operación consolidada alcanza $4.403.619.200 en 9.435 transacciones, con una calificación media de 4,01 sobre 5.
B95: ="2. "&Análisis!$B$86&" es la tienda más rentable ("&TEXT(Análisis!$C$86,"$#.##0")&") y "&Análisis!$B$87&" la de menor aporte ("&TEXT(Análisis!$C$87,"$#.##0")&"), con la calificación y el ticket promedio más bajos de su grupo." -> 2. Tienda 1 es la tienda más rentable ($1.150.880.400) y Tienda 4 la de menor aporte ($1.038.375.700), con la calificación y el ticket promedio más bajos de su grupo.
B96: ="3. El negocio depende de pocas palancas: "&B32&" y "&B33&" generan "&TEXT(D32+D33,"0,0%")&" de los ingresos y "&B45&" aporta "&TEXT(D45,"0,0%")&"." -> 3. El negocio depende de pocas palancas: Electrónicos y Electrodomésticos generan 67,8% de los ingresos y Bogotá aporta 41,2%.
B97: ="4. El "&TEXT(MAX(D77:D80),"0,0%")&" de la facturación se cobra con "&INDEX(B77:B80,MATCH(MAX(C77:C80),C77:C80,0))&", con "&TEXT(Análisis!$F$13,"0,00")&" cuotas promedio." -> 4. El 73,4% de la facturación se cobra con Tarjeta de crédito, con 2,93 cuotas promedio.
B98: ="5. El costo de envío equivale al "&TEXT(Análisis!$F$9/Análisis!$F$7,"0,0%")&" de los ingresos ("&TEXT(Análisis!$F$9,"$#.##0")&"), un rubro relevante para negociar con operadores logísticos." -> 5. El costo de envío equivale al 5,3% de los ingresos ($234.697.000), un rubro relevante para negociar con operadores logísticos.
B100: 11. Recomendaciones
B101: ="1. Revisar la operación de "&Análisis!$B$87&": es la de menores ingresos y ticket promedio; evaluar surtido de categorías de alto valor antes de considerar cualquier ajuste estructural." -> 1. Revisar la operación de Tienda 4: es la de menores ingresos y ticket promedio; evaluar surtido de categorías de alto valor antes de considerar cualquier ajuste estructural.
B102: ="2. Proteger y ampliar el negocio en "&B32&" y "&B33&", que sostienen "&TEXT(D32+D33,"0,0%")&" de la facturación: asegurar inventario, garantía y financiación en estas líneas." -> 2. Proteger y ampliar el negocio en Electrónicos y Electrodomésticos, que sostienen 67,8% de la facturación: asegurar inventario, garantía y financiación en estas líneas.
B103: ="3. Reactivar las categorías de bajo aporte ("&B39&", "&B38&") mediante paquetes o venta cruzada, o reducir su espacio en inventario." -> 3. Reactivar las categorías de bajo aporte (Libros, Artículos para el hogar) mediante paquetes o venta cruzada, o reducir su espacio en inventario.
B104: ="4. Diversificar medios de pago para reducir la dependencia del "&TEXT(MAX(D77:D80),"0,0%")&" concentrado en "&INDEX(B77:B80,MATCH(MAX(C77:C80),C77:C80,0))&" y negociar mejores comisiones." -> 4. Diversificar medios de pago para reducir la dependencia del 73,4% concentrado en Tarjeta de crédito y negociar mejores comisiones.
B105: ="5. Trabajar planes de crecimiento en plazas secundarias: fuera de las tres primeras ciudades el aporte cae por debajo del "&TEXT(D48,"0,0%")&" por ciudad." -> 5. Trabajar planes de crecimiento en plazas secundarias: fuera de las tres primeras ciudades el aporte cae por debajo del 5,1% por ciudad.
B106: ="6. Verificar la completitud del año "&TEXT(B71,"0")&" antes de interpretar la variación de "&TEXT(E71,"0,0%")&" como una caída real de demanda." -> 6. Verificar la completitud del año 2023 antes de interpretar la variación de -76,6% como una caída real de demanda.
B107: ="7. Vender "&INDEX(Análisis!$B$5:$E$5,MATCH(MIN(Análisis!$B$11:$E$11),Análisis!$B$11:$E$11,0))&": es la tienda con menores ingresos ("&TEXT(INDEX(Análisis!$B$7:$E$7,MATCH(MIN(Análisis!$B$11:$E$11),Análisis!$B$11:$E$11,0)),"$#.##0")&"), el ticket promedio más bajo ("&TEXT(INDEX(Análisis!$B$8:$E$8,MATCH(MIN(Análisis!$B$11:$E$11),Análisis!$B$11:$E$11,0)),"$#.##0")&") y el menor ingreso neto de envíos ("&TEXT(MIN(Análisis!$B$11:$E$11),"$#.##0")&"), pese a operar prácticamente el mismo número de transacciones que las demás; es la unidad cuya venta menos afecta la facturación consolidada y su calificación ("&TEXT(INDEX(Análisis!$B$12:$E$12,MATCH(MIN(Análisis!$B$11:$E$11),Análisis!$B$11:$E$11,0)),"0,00")&") está por debajo del promedio general." -> 7. Vender Tienda 4: es la tienda con menores ingresos ($1.038.375.700), el ticket promedio más bajo ($440.363) y el menor ingreso neto de envíos ($983.058.300), pese a operar prácticamente el mismo número de transacciones que las demás; es la unidad cuya venta menos afecta la facturación consolidada y su calificación (4,00) está por debajo del promedio general.
B109: 11.1 Sustento de la decisión de venta
B110: ="Criterio de decisión: se vende la unidad que menos valor aporta por transacción y menos ingreso neto genera, dado que las cuatro tiendas operan un volumen casi idéntico de operaciones ("&TEXT(MIN(Análisis!$B$6:$E$6),"#.##0")&" a "&TEXT(MAX(Análisis!$B$6:$E$6),"#.##0")&" ventas). Con volumen igualado, la diferencia de resultados es de rentabilidad por venta, no de tamaño de mercado." -> Criterio de decisión: se vende la unidad que menos valor aporta por transacción y menos ingreso neto genera, dado que las cuatro tiendas operan un volumen casi idéntico de operaciones (2.358 a 2.359 ventas). Con volumen igualado, la diferencia de resultados es de rentabilidad por venta, no de tamaño de mercado.
B112: Criterio | C112: Tienda 1 | D112: Tienda 2 | E112: Tienda 3 | F112: Tienda 4
B113: Ingresos totales | C113: =Análisis!B7 -> 1150880400 | D113: =Análisis!C7 -> 1116343500 | E113: =Análisis!D7 -> 1098019600 | F113: =Análisis!E7 -> 1038375700
B114: Participación en ingresos | C114: =Análisis!B14 -> 0.26134876 | D114: =Análisis!C14 -> 0.25350591 | E114: =Análisis!D14 -> 0.24934481 | F114: =Análisis!E14 -> 0.23580052
...
